Workbook

Sheet Monthly_Data
A1: MONTHLY BASE DATA SHEET – SOURCE FOR ALL KRI CALCULATIONS
A2: Metric | B2: Unit | C2: May-25 | D2: Jun-25 | E2: Jul-25 | F2: Aug-25 | G2: Sep-25 | H2: Oct-25 | I2: Nov-25 | J2: Dec-25 | K2: Jan-26 | L2: Feb-26 | M2: Mar-26 | N2: Apr-26 | O2: Source | P2: Formula / Note
A3: --- CREDIT RISK --- | O3: P1_Credit_Risk
A4: Gross NPA Amount (₹ Cr) | B4: ₹ Cr | C4: 16640 | D4: 16290 | E4: 15750 | F4: 15390 | G4: 15120 | H4: 14820 | I4: 14550 | J4: 14250 | K4: 13940 | L4: 13940 | M4: 14250 | N4: 14250 | O4: P1_Credit_Risk | P4: SUMIF(NPA_Category<>Standard, Outstanding)
A5: Gross Advances (₹ Cr) | B5: ₹ Cr | C5: 286900 | D5: 285900 | E5: 286200 | F5: 285100 | G5: 285400 | H5: 284800 | I5: 285200 | J5: 285000 | K5: 284700 | L5: 284600 | M5: 285000 | N5: 285000 | O5: P1_Credit_Risk | P5: SUM(Outstanding_Cr)
A6: Net NPA Amount (₹ Cr) | B6: ₹ Cr | C6: 8035 | D6: 7727 | E6: 7446 | F6: 7128 | G6: 6840 | H6: 6552 | I6: 6270 | J6: 5985 | K6: 5985 | L6: 5700 | M6: 5985 | N6: 5985 | O6: P1_Credit_Risk | P6: Gross NPA – Provisions held
A7: Net Advances (₹ Cr) | B7: ₹ Cr | C7: 286900 | D7: 285900 | E7: 286200 | F7: 285100 | G7: 285400 | H7: 284800 | I7: 285200 | J7: 285000 | K7: 284700 | L7: 284600 | M7: 285000 | N7: 285000 | O7: P1_Credit_Risk | P7: Gross Adv – Total Provisions
A8: SMA-0 Balance (₹ Cr) | B8: ₹ Cr | C8: 9726 | D8: 9440 | E8: 9589 | F8: 9609 | G8: 9572 | H8: 9377 | I8: 9177 | J8: 9120 | K8: 9120 | L8: 9120 | M8: 9120 | N8: 9120 | O8: P1_Credit_Risk | P8: SUMIF(SMA_Flag=SMA-0, Outstanding)
A9: SMA-1 Balance (₹ Cr) | B9: ₹ Cr | C9: 3446 | D9: 3202 | E9: 3161 | F9: 3159 | G9: 3151 | H9: 3302 | I9: 3304 | J9: 3420 | K9: 3420 | L9: 3420 | M9: 3420 | N9: 3420 | O9: P1_Credit_Risk | P9: SUMIF(SMA_Flag=SMA-1, Outstanding)
A10: SMA-2 Balance (₹ Cr) | B10: ₹ Cr | C10: 1721 | D10: 1751 | E10: 1723 | F10: 1720 | G10: 1714 | H10: 1709 | I10: 1705 | J10: 1995 | K10: 1995 | L10: 1995 | M10: 1995 | N10: 1995 | O10: P1_Credit_Risk | P10: SUMIF(SMA_Flag=SMA-2, Outstanding)
A11: Total Provisions (₹ Cr) | B11: ₹ Cr | C11: 12652 | D11: 12600 | E11: 12350 | F11: 12300 | G11: 12318 | H11: 12319 | I11: 12320 | J11: 12330 | K11: 12000 | L11: 12260 | M11: 12330 | N11: 12330 | O11: P1_Credit_Risk | P11: SUM(ECL_Cr)
A12: PCR Provisions (₹ Cr) | B12: ₹ Cr | C12: 12652 | D12: 11681 | E12: 11692 | F12: 10851 | G12: 10911 | H12: 10817 | I12: 11058 | J12: 10830 | K12: 10829 | L12: 10829 | M12: 10830 | N12: 10830 | O12: P1_Credit_Risk | P12: Provisions / Gross NPA * 100
A13: ECL Stage 3 EAD (₹ Cr) | B13: ₹ Cr | C13: 16640 | D13: 16290 | E13: 15750 | F13: 15390 | G13: 15120 | H13: 14820 | I13: 14550 | J13: 14250 | K13: 13940 | L13: 13940 | M13: 14250 | N13: 14250 | O13: ECL Engine | P13: Stage 3 Exposure at Default
A14: ECL Stage 3 Provisions (₹Cr) | B14: ₹ Cr | C14: 10234 | D14: 10027 | E14: 9945 | F14: 9752 | G14: 9645 | H14: 9408 | I14: 9249 | J14: 8992 | K14: 8808 | L14: 8808 | M14: 8992 | N14: 8992 | O14: ECL Engine | P14: Provisions held against Stage 3
A15: --- MARKET RISK --- | O15: P1_Market_Risk
A16: Trading Book VaR 1D (₹ Cr) | B16: ₹ Cr | C16: 720 | D16: 680 | E16: 660 | F16: 665 | G16: 630 | H16: 640 | I16: 640 | J16: 650 | K16: 650 | L16: 640 | M16: 640 | N16: 640 | O16: Treasury/Murex | P16: PERCENTILE(VaR_1D_Cr, 99%)
A17: VaR Limit (₹ Cr) | B17: ₹ Cr | C17: 1000 | D17: 1000 | E17: 1000 | F17: 1000 | G17: 1000 | H17: 1000 | I17: 1000 | J17: 1000 | K17: 1000 | L17: 1000 | M17: 1000 | N17: 1000 | O17: Treasury/Murex | P17: Board approved limit
A18: SVaR Total (₹ Cr) | B18: ₹ Cr | C18: 4250 | D18: 4300 | E18: 4280 | F18: 4210 | G18: 4150 | H18: 4100 | I18: 4080 | J18: 4060 | K18: 4050 | L18: 4050 | M18: 4050 | N18: 4050 | O18: Treasury/Murex | P18: SUM(SVaR_Cr)
A19: IRC Total (₹ Cr) | B19: ₹ Cr | C19: 1820 | D19: 1800 | E19: 1780 | F19: 1760 | G19: 1750 | H19: 1740 | I19: 1730 | J19: 1720 | K19: 1720 | L19: 1720 | M19: 1720 | N19: 1720 | O19: Treasury/Murex | P19: SUM(IRC_Cr)
A20: FX Open Position (₹ Cr) | B20: ₹ Cr | C20: 92 | D20: 94 | E20: 91 | F20: 88 | G20: 85 | H20: 87 | I20: 88 | J20: 89 | K20: 90 | L20: 88 | M20: 88 | N20: 88 | O20: SWIFT/Murex | P20: Net open FX position
A21: DV01 Total (₹ Lakhs) | B21: ₹ Lk | C21: 5420 | D21: 5380 | E21: 5350 | F21: 5320 | G21: 5290 | H21: 5260 | I21: 5240 | J21: 5220 | K21: 5200 | L21: 5200 | M21: 5200 | N21: 5200 | O21: Murex | P21: SUM(DV01_Lakhs)
A22: DV01 Limit (₹ Lakhs) | B22: ₹ Lk | C22: 9000 | D22: 9000 | E22: 9000 | F22: 9000 | G22: 9000 | H22: 9000 | I22: 9000 | J22: 9000 | K22: 9000 | L22: 9000 | M22: 9000 | N22: 9000 | O22: Murex | P22: Board approved limit
A23: --- OPERATIONAL RISK --- | O23: P1_Operational_Risk
A24: Op Loss Net (₹ Cr) | B24: ₹ Cr | C24: 0.14 | D24: 0.13 | E24: 0.13 | F24: 0.12 | G24: 0.13 | H24: 0.12 | I24: 0.12 | J24: 0.12 | K24: 0.12 | L24: 0.11 | M24: 0.12 | N24: 0.12 | O24: ORMS | P24: SUM Net_Loss_Lakhs per month
A25: NII (Net Interest Income ₹Cr) | B25: ₹ Cr | C25: 11667 | D25: 11667 | E25: 11667 | F25: 11667 | G25: 11667 | H25: 11667 | I25: 11667 | J25: 11667 | K25: 11667 | L25: 11667 | M25: 11667 | N25: 11667 | O25: P&L | P25: Monthly NII figure
A26: KCI Breach Count | B26: Count | C26: 3 | D26: 3 | E26: 3 | F26: 3 | G26: 3 | H26: 3 | I26: 3 | J26: 3 | K26: 3 | L26: 3 | M26: 3 | N26: 3 | O26: ORMS | P26: COUNTIF(KRI_Breach=Yes)
A27: Overdue Actions | B27: Count | C27: 20 | D27: 20 | E27: 19 | F27: 18 | G27: 18 | H27: 18 | I27: 18 | J27: 18 | K27: 18 | L27: 18 | M27: 18 | N27: 18 | O27: GRC Tool | P27: COUNTIF(Status=Overdue)
A28: --- CAPITAL ADEQUACY --- | O28: P1_Capital_Adequacy
A29: CET1 Capital (₹ Cr) | B29: ₹ Cr | C29: 356000 | D29: 358000 | E29: 360000 | F29: 362000 | G29: 364000 | H29: 366000 | I29: 366000 | J29: 366000 | K29: 359199 | L29: 362448 | M29: 366393 | N29: 372064 | O29: CAR Return | P29: From quarterly CAR return (interpolated monthly)
A30: Tier1 Capital (₹ Cr) | B30: ₹ Cr | C30: 374000 | D30: 376000 | E30: 378000 | F30: 380000 | G30: 382000 | H30: 384000 | I30: 384000 | J30: 384000 | K30: 379036 | L30: 382633 | M30: 386361 | N30: 392022 | O30: CAR Return
A31: Total Capital (₹ Cr) | B31: ₹ Cr | C31: 436000 | D31: 438000 | E31: 440000 | F31: 442000 | G31: 444000 | H31: 446000 | I31: 446000 | J31: 446000 | K31: 444897 | L31: 448727 | M31: 454008 | N31: 460108 | O31: CAR Return
A32: Total RWA (₹ Cr) | B32: ₹ Cr | C32: 2280000 | D32: 2285000 | E32: 2290000 | F32: 2295000 | G32: 2300000 | H32: 2305000 | I32: 2310000 | J32: 2315000 | K32: 2300775 | L32: 2323874 | M32: 2363920 | N32: 2381080 | O32: CAR Return
A33: Tier1 (Leverage Exposure₹Cr) | B33: ₹ Cr | C33: 24800000 | D33: 24900000 | E33: 25000000 | F33: 25100000 | G33: 25200000 | H33: 25300000 | I33: 25400000 | J33: 25500000 | K33: 25357612 | L33: 24654381 | M33: 26351120 | N33: 25265818 | O33: CAR Return | P33: Exposure measure for leverage ratio
A34: --- LIQUIDITY --- | O34: P2_Liquidity_Risk
A35: HQLA Total (₹ Cr) | B35: ₹ Cr | C35: 6800 | D35: 7100 | E35: 7200 | F35: 7500 | G35: 7600 | H35: 7800 | I35: 8000 | J35: 8200 | K35: 8400 | L35: 8500 | M35: 8200 | N35: 8200 | O35: ALM System | P35: AVERAGE(HQLA_Cr) for month
A36: Net Cash Outflow 30D (₹ Cr) | B36: ₹ Cr | C36: 5763 | D36: 5917 | E36: 5902 | F36: 6048 | G36: 6080 | H36: 6191 | I36: 6299 | J36: 6406 | K36: 6512 | L36: 6538 | M36: 6406 | N36: 6406 | O36: ALM System | P36: AVERAGE(Net_Cash_Outflow_30D_Cr)
A37: NSFR ASF (₹ Cr) | B37: ₹ Cr | C37: 130000 | D37: 131000 | E37: 132000 | F37: 133000 | G37: 134000 | H37: 135000 | I37: 136000 | J37: 137000 | K37: 138000 | L37: 139000 | M37: 137000 | N37: 137000 | O37: ALM System | P37: AVERAGE(NSFR_ASF_Cr)
A38: NSFR RSF (₹ Cr) | B38: ₹ Cr | C38: 120000 | D38: 120183 | E38: 120000 | F38: 119800 | G38: 120721 | H38: 120536 | I38: 121429 | J38: 121239 | K38: 123214 | L38: 123009 | M38: 121239 | N38: 121239 | O38: ALM System | P38: AVERAGE(NSFR_RSF_Cr)
A39: SLR (% NDTL) | B39: % | C39: 23.06 | D39: 21.85 | E39: 22.06 | F39: 22.82 | G39: 23.25 | H39: 22.62 | I39: 22.71 | J39: 22.6 | K39: 23.06 | L39: 22.6 | M39: 22.6 | N39: 22.6 | O39: CBS | P39: Fortnightly SLR filing
A40: CRR (% NDTL) | B40: % | C40: 4 | D40: 4.5 | E40: 4.5 | F40: 4.5 | G40: 4 | H40: 4.5 | I40: 4.5 | J40: 4.5 | K40: 4 | L40: 4.5 | M40: 4.5 | N40: 4.5 | O40: CBS | P40: Fortnightly CRR filing
A41: Cumulative Gap 1M (₹ Cr) | B41: ₹ Cr | C41: -3800 | D41: -3500 | E41: -3200 | F41: -2900 | G41: -2700 | H41: -2600 | I41: -2500 | J41: -2400 | K41: -2400 | L41: -2400 | M41: -2400 | N41: -2400 | O41: ALM System | P41: AVERAGE(cumulative gap for 1M bucket)
A42: --- IRRBB --- | O42: P2_IRRBB
A43: NII Sensitivity +200bps (%) | B43: % | C43: -4.2 | D43: -4 | E43: -3.8 | F43: -3.6 | G43: -3.5 | H43: -3.4 | I43: -3.3 | J43: -3.2 | K43: -3.2 | L43: -3.1 | M43: -3.2 | N43: -3.2 | O43: ALM System | P43: Avg NII_Impact_% for +200bps scenario
A44: EVE Sensitivity +200bps(%T1) | B44: % T1 | C44: -6.8 | D44: -6.7 | E44: -6.6 | F44: -6.5 | G44: -6.5 | H44: -6.4 | I44: -6.3 | J44: -6.2 | K44: -6.2 | L44: -6.1 | M44: -6.2 | N44: -6.2 | O44: ALM System | P44: Avg EVE_Impact_Pct_Tier1 for +200bps
A45: Duration Gap (Years) | B45: Yrs | C45: 1.4 | D45: 1.4 | E45: 1.3 | F45: 1.3 | G45: 1.2 | H45: 1.2 | I45: 1.2 | J45: 1.2 | K45: 1.2 | L45: 1.1 | M45: 1.2 | N45: 1.2 | O45: ALM System | P45: AVERAGE(Duration_Gap_Yrs)
A46: Repricing Gap 1Y (%) | B46: % | C46: -4.5 | D46: -4.3 | E46: -4.2 | F46: -4.2 | G46: -4.1 | H46: -4 | I46: -4 | J46: -4.1 | K46: -4.1 | L46: -4.1 | M46: -4.1 | N46: -4.1 | O46: ALM System | P46: AVERAGE(NII_Impact_%) all shocks
A47: --- CLIMATE RISK --- | O47: P2_Climate_Risk
A48: High Physical Risk Exp (₹Cr) | B48: ₹ Cr | C48: 5200 | D48: 5100 | E48: 5000 | F48: 4900 | G48: 4700 | H48: 4600 | I48: 4500 | J48: 4400 | K48: 4300 | L48: 4200 | M48: 4200 | N48: 4200 | O48: Climate Tool | P48: SUMIF(Physical_Risk_Score>7, Exposure_Cr)
A49: Total Advances (₹ Cr) | B49: ₹ Cr | C49: 286900 | D49: 285900 | E49: 286200 | F49: 285100 | G49: 285400 | H49: 284800 | I49: 285200 | J49: 285000 | K49: 284700 | L49: 284600 | M49: 285000 | N49: 285000 | O49: CBS | P49: Gross Advances
A50: Green Finance Advances (₹Cr) | B50: ₹ Cr | C50: 20657 | D50: 21443 | E50: 22284 | F50: 22808 | G50: 23728 | H50: 24208 | I50: 25068 | J50: 25650 | K50: 26192 | L50: 26753 | M50: 27075 | N50: 27360 | O50: DW | P50: SUMIF(Green_Finance=Yes, Exposure_Cr)
A51: --- CYBER RISK --- | O51: P2_Cyber_Risk
A52: Critical Vulns Unpatched | B52: Count | C52: 8 | D52: 7 | E52: 7 | F52: 6 | G52: 5 | H52: 5 | I52: 4 | J52: 4 | K52: 4 | L52: 4 | M52: 4 | N52: 4 | O52: SIEM | P52: COUNTIF(CVSS_Score>7, Patch_Status<>Patched)
A53: MTTD Avg (Hours) | B53: Hrs | C53: 5.2 | D53: 4.8 | E53: 4.5 | F53: 4.2 | G53: 4 | H53: 3.8 | I53: 3.5 | J53: 3.2 | K53: 3 | L53: 2.8 | M53: 2.8 | N53: 2.8 | O53: SOC | P53: AVERAGE(MTTD_Hrs)
A54: MTTR Avg (Hours) | B54: Hrs | C54: 44.8 | D54: 43.2 | E54: 42 | F54: 40.5 | G54: 39.1 | H54: 37.4 | I54: 36.1 | J54: 34.5 | K54: 33 | L54: 31.5 | M54: 31.5 | N54: 31.5 | O54: SOC | P54: AVERAGE(MTTR_Hrs)
A55: --- FRAUD RISK --- | O55: P2_Fraud_Risk
A56: Fraud Loss Net (₹ Cr) | B56: ₹ Cr | C56: 0.14 | D56: 0.128 | E56: 0.126 | F56: 0.117 | G56: 0.117 | H56: 0.105 | I56: 0.105 | J56: 0.094 | K56: 0.094 | L56: 0.094 | M56: 0.094 | N56: 0.094 | O56: FMS | P56: SUM(Net_Loss_Lakhs) per month
A57: Total Income (₹ Cr) | B57: ₹ Cr | C57: 14500 | D57: 14500 | E57: 14500 | F57: 14500 | G57: 14500 | H57: 14500 | I57: 14500 | J57: 14500 | K57: 14500 | L57: 14500 | M57: 14500 | N57: 14500 | O57: P&L | P57: Monthly Total Income
A58: Fraud Recovered (₹ Cr) | B58: ₹ Cr | C58: 0.162 | D58: 0.153 | E58: 0.152 | F58: 0.14 | G58: 0.142 | H58: 0.128 | I58: 0.13 | J58: 0.118 | K58: 0.118 | L58: 0.118 | M58: 0.118 | N58: 0.118 | O58: FMS | P58: SUM(Recovered_Lakhs) per month
A59: Fraud Amount (₹ Cr) | B59: ₹ Cr | C59: 0.249 | D59: 0.221 | E59: 0.219 | F59: 0.197 | G59: 0.202 | H59: 0.178 | I59: 0.179 | J59: 0.158 | K59: 0.158 | L59: 0.158 | M59: 0.158 | N59: 0.158 | O59: FMS | P59: SUM(Amount_Lakhs) per month
A60: --- THIRD PARTY RISK --- | O60: P2_Third_Party_Risk
A61: Critical Vendor SLA Breaches | B61: Count | C61: 5 | D61: 5 | E61: 4 | F61: 4 | G61: 3 | H61: 3 | I61: 2 | J61: 2 | K61: 2 | L61: 2 | M61: 2 | N61: 2 | O61: Vendor Mgmt | P61: COUNTIF(Criticality=Critical, SLA_Breach=Yes) monthly
A62: --- REPUTATIONAL RISK --- | O62: P2_Reputational_Risk
A63: Media Sentiment Score | B63: Score | C63: 58 | D63: 59 | E63: 60 | F63: 61 | G63: 62 | H63: 62 | I63: 63 | J63: 63 | K63: 62 | L63: 62 | M63: 62 | N63: 62 | O63: Media Analytics | P63: AVERAGE(Sentiment_Score) for month
A64: Total Complaints | B64: Count | C64: 3200 | D64: 3100 | E64: 3050 | F64: 2950 | G64: 2900 | H64: 2850 | I64: 2800 | J64: 2750 | K64: 2700 | L64: 2650 | M64: 2750 | N64: 2750 | O64: CRM | P64: COUNT(Customer_Complaints) monthly
A65: Complaints Resolved | B65: Count | C65: 2880 | D65: 2821 | E65: 2836 | F65: 2773 | G65: 2624 | H65: 2736 | I65: 2786 | J65: 2667 | K65: 2619 | L65: 2571 | M65: 2667 | N65: 2667 | O65: CRM | P65: COUNT(Complaints_Resolved) monthly
A66: --- CONCENTRATION RISK --- | O66: P2_Concentration_Risk
A67: Single Borrower Max Exp(₹Cr) | B67: ₹ Cr | C67: 59400 | D67: 60000 | E67: 62100 | F67: 63000 | G67: 63600 | H67: 64500 | I67: 64500 | J67: 65400 | K67: 64800 | L67: 64800 | M67: 65400 | N67: 65400 | O67: DW | P67: MAX single borrower exposure
A68: Capital Funds (₹ Cr) | B68: ₹ Cr | C68: 400000 | D68: 402000 | E68: 404000 | F68: 406000 | G68: 408000 | H68: 410000 | I68: 410000 | J68: 410000 | K68: 444897 | L68: 448727 | M68: 454008 | N68: 460108 | O68: CAR Return | P68: Tier1 + Tier2 capital

Sheet Table_of_Contents
A1: BANK – ENTERPRISE RISK MANAGEMENT DASHBOARD Table of Contents
A2: # | B2: Sheet Name | C2: Description | D2: Pillar | E2: Last Updated
A3: 1 | B3: KRI_Master_Summary | C3: Master KRI tracker – all risk types with RAG status | D3: All Pillars | E3: Apr-2026
A4: 2 | B4: KRI_Thresholds | C4: Threshold definitions & breach logic for every KRI | D4: All Pillars | E4: Apr-2026
A5: 3 | B5: P1_Credit_Risk | C5: Pillar 1 – Credit risk: NPA, ECL, PD, LGD, CRAR by segment | D5: Pillar 1 | E5: Apr-2026
A6: 4 | B6: P1_Market_Risk | C6: Pillar 1 – Market risk: VaR, SVaR, IRC, DV01, limits | D6: Pillar 1 | E6: Apr-2026
A7: 5 | B7: P1_Operational_Risk | C7: Pillar 1 – Op risk: loss events, RCSA, BIA capital | D7: Pillar 1 | E7: Apr-2026
A8: 6 | B8: P1_Capital_Adequacy | C8: Pillar 1 – CRAR, Tier-1, CET-1, RWA by risk type | D8: Pillar 1 | E8: Apr-2026
A9: 7 | B9: P2_Liquidity_Risk | C9: Pillar 2 – LCR, NSFR, SLR, CRR, gap analysis | D9: Pillar 2 | E9: Apr-2026
A10: 8 | B10: P2_IRRBB | C10: Pillar 2 – IRRBB: NII sensitivity, EVE shock, duration gap | D10: Pillar 2 | E10: Apr-2026
A11: 9 | B11: P2_Concentration_Risk | C11: Pillar 2 – Single-borrower, sector & geography concentration | D11: Pillar 2 | E11: Apr-2026
A12: 10 | B12: P2_Climate_Risk | C12: Pillar 2 – Physical & transition risk, TCFD, GHG, ESG | D12: Pillar 2 | E12: Apr-2026
A13: 11 | B13: P2_Cyber_Risk | C13: Pillar 2 – Cyber incidents, CVSS, MTTD, MTTR | D13: Pillar 2 | E13: Apr-2026
A14: 12 | B14: P2_Fraud_Risk | C14: Pillar 2 – Fraud detection, channel, recovery rate | D14: Pillar 2 | E14: Apr-2026
... A20: 18 | B20: Monthly_KRI_Trend | C20: 12-month KRI trend for executive dashboard | D20: All Pillars | E20: Apr-2026

Sheet KRI_Master_Summary
A1: KRI MASTER SUMMARY – ENTERPRISE RISK DASHBOARD | Reference: /RMD/CCRMD/2025-26/01 | Current Values & MoM: FORMULA-DRIVEN from Monthly_KRI_Trend → Monthly_Data
A2: # | B2: Risk Category | C2: KRI Name | D2: Current Value | E2: Threshold (Green) | F2: Threshold (Amber) | G2: Threshold (Red) | H2: Unit | I2: Frequency | J2: RAG Status | K2: MoM Change | L2: Data Source | M2: Regulatory Ref | N2: KRI_Score | O2: Breach_Flag
A3: 1 | B3: Pillar 1 – Credit Risk | C3: Gross NPA Ratio | D3: =IFERROR(Monthly_KRI_Trend!T4,"") -> 5 | E3: <5% | F3: 5-6% | G3: >6% | H3: Percent | I3: Monthly | J3: =IFERROR(IF(Monthly_KRI_Trend!D4="Lower Better",IF(Monthly_KRI_Trend!T4<Monthly_KRI_Trend!F4,"Green",IF(Monthly_KRI_Trend!T4<Monthly_KRI_Trend!E4,"Amber","Red")),IF(Monthly_KRI_Trend!T4>Monthly_KRI_Trend!F4,"Green",IF(Monthly_KRI_Trend!T4>Monthly_KRI_Trend!E4,"Amber","Red"))),"") -> Amber | K3: +1.02% | L3: =IFERROR(Monthly_KRI_Trend!V4,"") -> 0 | M3: IRAC Norms | N3: =IF(J3="Green",1,IF(J3="Amber",2,IF(J3="Red",3,""))) -> 2 | O3: =IF(J3="Red","YES",IF(J3="Amber","WATCH","OK")) -> WATCH
A4: 2 | B4: Pillar 1 – Credit Risk | C4: Net NPA Ratio | D4: =IFERROR(Monthly_KRI_Trend!T5,"") -> 2.1 | E4: <2% | F4: 2-3% | G4: >3% | H4: Percent | I4: Monthly | J4: =IFERROR(IF(Monthly_KRI_Trend!D5="Lower Better",IF(Monthly_KRI_Trend!T5<Monthly_KRI_Trend!F5,"Green",IF(Monthly_KRI_Trend!T5<Monthly_KRI_Trend!E5,"Amber","Red")),IF(Monthly_KRI_Trend!T5>Monthly_KRI_Trend!F5,"Green",IF(Monthly_KRI_Trend!T5>Monthly_KRI_Trend!E5,"Amber","Red"))),"") -> Amber | K4: -2.36% | L4: =IFERROR(Monthly_KRI_Trend!V5,"") -> 0 | M4: IRAC Norms | N4: =IF(J4="Green",1,IF(J4="Amber",2,IF(J4="Red",3,""))) -> 2 | O4: =IF(J4="Red","YES",IF(J4="Amber","WATCH","OK")) -> WATCH
A5: 3 | B5: Pillar 1 – Credit Risk | C5: Credit Cost (Provisioning Ratio) | D5: =IFERROR(IF(Monthly_Data!N5=0,"",ROUND((Monthly_Data!N11/Monthly_Data!N5)*100,2)),"") -> 4.33 | E5: <1.5% | F5: 1.5-2% | G5: >2% | H5: Percent | I5: Quarterly | J5: =IFERROR(IF(Monthly_KRI_Trend!D6="Lower Better",IF(Monthly_KRI_Trend!T6<Monthly_KRI_Trend!F6,"Green",IF(Monthly_KRI_Trend!T6<Monthly_KRI_Trend!E6,"Amber","Red")),IF(Monthly_KRI_Trend!T6>Monthly_KRI_Trend!F6,"Green",IF(Monthly_KRI_Trend!T6>Monthly_KRI_Trend!E6,"Amber","Red"))),"") -> Amber | K5: -0.99% | L5: =IFERROR(Monthly_KRI_Trend!V6,"") -> 0 | M5: RBI MAS | N5: =IF(J5="Green",1,IF(J5="Amber",2,IF(J5="Red",3,""))) -> 2 | O5: =IF(J5="Red","YES",IF(J5="Amber","WATCH","OK")) -> WATCH
A6: 4 | B6: Pillar 1 – Credit Risk | C6: SMA-0 Ratio | D6: =IFERROR(Monthly_KRI_Trend!T6,"") -> 3.2 | E6: <3% | F6: 3-5% | G6: >5% | H6: Percent | I6: Monthly | J6: =IFERROR(IF(Monthly_KRI_Trend!D7="Lower Better",IF(Monthly_KRI_Trend!T7<Monthly_KRI_Trend!F7,"Green",IF(Monthly_KRI_Trend!T7<Monthly_KRI_Trend!E7,"Amber","Red")),IF(Monthly_KRI_Trend!T7>Monthly_KRI_Trend!F7,"Green",IF(Monthly_KRI_Trend!T7>Monthly_KRI_Trend!E7,"Amber","Red"))),"") -> Amber | K6: -1.27% | L6: =IFERROR(Monthly_KRI_Trend!V7,"") -> 0 | M6: RBI Circular | N6: =IF(J6="Green",1,IF(J6="Amber",2,IF(J6="Red",3,""))) -> 2 | O6: =IF(J6="Red","YES",IF(J6="Amber","WATCH","OK")) -> WATCH
A7: 5 | B7: Pillar 1 – Credit Risk | C7: SMA-1 Ratio | D7: =IFERROR(Monthly_KRI_Trend!T7,"") -> 1.2 | E7: <1% | F7: 1-2% | G7: >2% | H7: Percent | I7: Monthly | J7: =IFERROR(IF(Monthly_KRI_Trend!D8="Lower Better",IF(Monthly_KRI_Trend!T8<Monthly_KRI_Trend!F8,"Green",IF(Monthly_KRI_Trend!T8<Monthly_KRI_Trend!E8,"Amber","Red")),IF(Monthly_KRI_Trend!T8>Monthly_KRI_Trend!F8,"Green",IF(Monthly_KRI_Trend!T8>Monthly_KRI_Trend!E8,"Amber","Red"))),"") -> Amber | K7: +1.55% | L7: =IFERROR(Monthly_KRI_Trend!V8,"") -> 0 | M7: RBI Circular | N7: =IF(J7="Green",1,IF(J7="Amber",2,IF(J7="Red",3,""))) -> 2 | O7: =IF(J7="Red","YES",IF(J7="Amber","WATCH","OK")) -> WATCH
A8: 6 | B8: Pillar 1 – Credit Risk | C8: SMA-2 Ratio | D8: =IFERROR(Monthly_KRI_Trend!T8,"") -> 0.7 | E8: <0.5% | F8: 0.5-1% | G8: >1% | H8: Percent | I8: Monthly | J8: =IFERROR(IF(Monthly_KRI_Trend!D9="Lower Better",IF(Monthly_KRI_Trend!T9<Monthly_KRI_Trend!F9,"Green",IF(Monthly_KRI_Trend!T9<Monthly_KRI_Trend!E9,"Amber","Red")),IF(Monthly_KRI_Trend!T9>Monthly_KRI_Trend!F9,"Green",IF(Monthly_KRI_Trend!T9>Monthly_KRI_Trend!E9,"Amber","Red"))),"") -> Green | K8: +1.22% | L8: =IFERROR(Monthly_KRI_Trend!V9,"") -> 0 | M8: RBI Circular | N8: =IF(J8="Green",1,IF(J8="Amber",2,IF(J8="Red",3,""))) -> 1 | O8: =IF(J8="Red","YES",IF(J8="Amber","WATCH","OK")) -> OK
A9: 8 | B9: Pillar 1 – Credit Risk | C9: PCR (Provision Coverage Ratio) | D9: =IFERROR(Monthly_KRI_Trend!T9,"") -> 76 | E9: >75% | F9: 65-75% | G9: <65% | H9: Percent | I9: Quarterly | J9: =IFERROR(IF(Monthly_KRI_Trend!D10="Lower Better",IF(Monthly_KRI_Trend!T10<Monthly_KRI_Trend!F10,"Green",IF(Monthly_KRI_Trend!T10<Monthly_KRI_Trend!E10,"Amber","Red")),IF(Monthly_KRI_Trend!T10>Monthly_KRI_Trend!F10,"Green",IF(Monthly_KRI_Trend!T10>Monthly_KRI_Trend!E10,"Amber","Red"))),"") -> Green | K9: -2.02% | L9: =IFERROR(Monthly_KRI_Trend!V10,"") -> 0 | M9: RBI | N9: =IF(J9="Green",1,IF(J9="Amber",2,IF(J9="Red",3,""))) -> 1 | O9: =IF(J9="Red","YES",IF(J9="Amber","WATCH","OK")) -> OK
A10: 9 | B10: Pillar 1 – Credit Risk | C10: ECL Stage 3 Coverage | D10: =IFERROR(Monthly_KRI_Trend!T10,"") -> 63.101754 | E10: >60% | F10: 50-60% | G10: <50% | H10: Percent | I10: Quarterly | J10: Green | K10: -0.18% | L10: =IFERROR(Monthly_KRI_Trend!#REF!,"") | M10: Ind AS 109 | N10: =IF(J10="Green",1,IF(J10="Amber",2,IF(J10="Red",3,""))) -> 1 | O10: =IF(J10="Red","YES",IF(J10="Amber","WATCH","OK")) -> OK
A11: 13 | B11: Pillar 1 – Market Risk | C11: IRC (Incremental Risk Charge) | D11: =IFERROR(Monthly_KRI_Trend!T14,"") -> 88 | E11: <1500 | F11: 1500-2000 | G11: >2000 | H11: ₹ Cr | I11: Weekly | J11: =IFERROR(IF(Monthly_KRI_Trend!D14="Lower Better",IF(Monthly_KRI_Trend!T14<Monthly_KRI_Trend!F14,"Green",IF(Monthly_KRI_Trend!T14<Monthly_KRI_Trend!E14,"Amber","Red")),IF(Monthly_KRI_Trend!T14>Monthly_KRI_Trend!F14,"Green",IF(Monthly_KRI_Trend!T14>Monthly_KRI_Trend!E14,"Amber","Red"))),"") -> Green | K11: -2.35% | L11: =IFERROR(Monthly_KRI_Trend!V14,"") -> 0 | M11: Basel III | N11: =IF(J11="Green",1,IF(J11="Amber",2,IF(J11="Red",3,""))) -> 1 | O11: =IF(J11="Red","YES",IF(J11="Amber","WATCH","OK")) -> OK
A12: 14 | B12: Pillar 1 – Market Risk | C12: Modified Duration (Investment) | D12: 3.8 | E12: <4 | F12: 4-5 | G12: >5 | H12: Years | I12: Monthly | J12: =IFERROR(IF(Monthly_KRI_Trend!D15="Lower Better",IF(Monthly_KRI_Trend!T15<Monthly_KRI_Trend!F15,"Green",IF(Monthly_KRI_Trend!T15<Monthly_KRI_Trend!E15,"Amber","Red")),IF(Monthly_KRI_Trend!T15>Monthly_KRI_Trend!F15,"Green",IF(Monthly_KRI_Trend!T15>Monthly_KRI_Trend!E15,"Amber","Red"))),"") -> Green | K12: -1.41% | L12: =IFERROR(Monthly_KRI_Trend!V15,"") -> 0 | M12: Internal | N12: =IF(J12="Green",1,IF(J12="Amber",2,IF(J12="Red",3,""))) -> 1 | O12: =IF(J12="Red","YES",IF(J12="Amber","WATCH","OK")) -> OK
A13: 15 | B13: Pillar 1 – Market Risk | C13: G-Sec Portfolio MTM Loss | D13: -45 | E13: >-500 | F13: (-500)-(-750) | G13: <-750 | H13: ₹ Cr | I13: Daily | J13: =IFERROR(IF(Monthly_KRI_Trend!D16="Lower Better",IF(Monthly_KRI_Trend!T16<Monthly_KRI_Trend!F16,"Green",IF(Monthly_KRI_Trend!T16<Monthly_KRI_Trend!E16,"Amber","Red")),IF(Monthly_KRI_Trend!T16>Monthly_KRI_Trend!F16,"Green",IF(Monthly_KRI_Trend!T16>Monthly_KRI_Trend!E16,"Amber","Red"))),"") -> Green | K13: +1.07% | L13: =IFERROR(Monthly_KRI_Trend!V16,"") -> 0 | M13: Internal | N13: =IF(J13="Green",1,IF(J13="Amber",2,IF(J13="Red",3,""))) -> 1 | O13: =IF(J13="Red","YES",IF(J13="Amber","WATCH","OK")) -> OK
A14: 16 | B14: Pillar 1 – Market Risk | C14: FX Open Position (USD equiv.) | D14: =IFERROR(Monthly_KRI_Trend!T14,"") -> 88 | E14: <100 | F14: 100-150 | G14: >150 | H14: ₹ Cr | I14: Daily | J14: Green | K14: +0.5% | L14: =IFERROR(Monthly_KRI_Trend!V17,"") -> 0 | M14: FEMA / RBI | N14: =IF(J14="Green",1,IF(J14="Amber",2,IF(J14="Red",3,""))) -> 1 | O14: =IF(J14="Red","YES",IF(J14="Amber","WATCH","OK")) -> OK
A15: 17 | B15: Pillar 1 – Market Risk | C15: DV01 Limit Utilisation | D15: =IFERROR(Monthly_KRI_Trend!T15,"") -> 57.777778 | E15: <60% | F15: 60-80% | G15: >80% | H15: Percent | I15: Daily | J15: Green | K15: -1.29% | L15: =IFERROR(Monthly_KRI_Trend!V18,"") -> 0 | M15: Internal | N15: =IF(J15="Green",1,IF(J15="Amber",2,IF(J15="Red",3,""))) -> 1 | O15: =IF(J15="Red","YES",IF(J15="Amber","WATCH","OK")) -> OK
A16: 18 | B16: Pillar 1 – Market Risk | C16: Equity VaR Limit Utilisation | D16: 19.3 | E16: <50% | F16: 50-70% | G16: >70% | H16: Percent | I16: Daily | J16: =IFERROR(IF(Monthly_KRI_Trend!D19="Lower Better",IF(Monthly_KRI_Trend!T19<Monthly_KRI_Trend!F19,"Green",IF(Monthly_KRI_Trend!T19<Monthly_KRI_Trend!E19,"Amber","Red")),IF(Monthly_KRI_Trend!T19>Monthly_KRI_Trend!F19,"Green",IF(Monthly_KRI_Trend!T19>Monthly_KRI_Trend!E19,"Amber","Red"))),"") -> Green | K16: +0.74% | L16: =IFERROR(Monthly_KRI_Trend!V19,"") -> 0.11777418 | M16: Internal | N16: =IF(J16="Green",1,IF(J16="Amber",2,IF(J16="Red",3,""))) -> 1 | O16: =IF(J16="Red","YES",IF(J16="Amber","WATCH","OK")) -> OK
A17: 20 | B17: Pillar 1 – Op Risk | C17: RCSA Average Score | D17: 2.1 | E17: <2.5 | F17: 2.5-3.5 | G17: >3.5 | H17: Score (1-5) | I17: Semi-Annual | J17: =IFERROR(IF(Monthly_KRI_Trend!D21="Lower Better",IF(Monthly_KRI_Trend!T21<Monthly_KRI_Trend!F21,"Green",IF(Monthly_KRI_Trend!T21<Monthly_KRI_Trend!E21,"Amber","Red")),IF(Monthly_KRI_Trend!T21>Monthly_KRI_Trend!F21,"Green",IF(Monthly_KRI_Trend!T21>Monthly_KRI_Trend!E21,"Amber","Red"))),"") -> Red | K17: -2.46% | L17: =IFERROR(Monthly_KRI_Trend!V21,"") -> 0.08538704 | M17: Internal | N17: =IF(J17="Green",1,IF(J17="Amber",2,IF(J17="Red",3,""))) -> 3 | O17: =IF(J17="Red","YES",IF(J17="Amber","WATCH","OK")) -> YES
A18: 21 | B18: Pillar 1 – Op Risk | C18: KCI Breach Count | D18: =IFERROR(Monthly_KRI_Trend!T17,"") -> 3 | E18: <3 | F18: 3-6 | G18: >6 | H18: Count | I18: Monthly | J18: =IFERROR(IF(Monthly_KRI_Trend!D22="Lower Better",IF(Monthly_KRI_Trend!T22<Monthly_KRI_Trend!F22,"Green",IF(Monthly_KRI_Trend!T22<Monthly_KRI_Trend!E22,"Amber","Red")),IF(Monthly_KRI_Trend!T22>Monthly_KRI_Trend!F22,"Green",IF(Monthly_KRI_Trend!T22>Monthly_KRI_Trend!E22,"Amber","Red"))),"") -> Green | K18: +1.93% | L18: =IFERROR(Monthly_KRI_Trend!V22,"") -> 0 | M18: Internal | N18: =IF(J18="Green",1,IF(J18="Amber",2,IF(J18="Red",3,""))) -> 1 | O18: =IF(J18="Red","YES",IF(J18="Amber","WATCH","OK")) -> OK
A19: 22 | B19: Pillar 1 – Op Risk | C19: Overdue Action Items | D19: =IFERROR(Monthly_KRI_Trend!T18,"") -> 18 | E19: <10 | F19: 10-20 | G19: >20 | H19: Count | I19: Monthly | J19: Amber | K19: +1.34% | L19: =IFERROR(Monthly_KRI_Trend!V23,"") -> 0 | M19: Internal | N19: =IF(J19="Green",1,IF(J19="Amber",2,IF(J19="Red",3,""))) -> 2 | O19: =IF(J19="Red","YES",IF(J19="Amber","WATCH","OK")) -> WATCH
A20: 23 | B20: Pillar 1 – Op Risk | C20: BCBS 239 Compliance Score | D20: 92 | E20: >85 | F20: 75-85 | G20: <75 | H20: Percent | I20: Quarterly | J20: =IFERROR(IF(Monthly_KRI_Trend!D24="Lower Better",IF(Monthly_KRI_Trend!T24<Monthly_KRI_Trend!F24,"Green",IF(Monthly_KRI_Trend!T24<Monthly_KRI_Trend!E24,"Amber","Red")),IF(Monthly_KRI_Trend!T24>Monthly_KRI_Trend!F24,"Green",IF(Monthly_KRI_Trend!T24>Monthly_KRI_Trend!E24,"Amber","Red"))),"") -> Green | K20: -0.63% | L20: =IFERROR(Monthly_KRI_Trend!V24,"") -> 0 | M20: BCBS 239 | N20: =IF(J20="Green",1,IF(J20="Amber",2,IF(J20="Red",3,""))) -> 1 | O20: =IF(J20="Red","YES",IF(J20="Amber","WATCH","OK")) -> OK
A21: 24 | B21: Pillar 1 – Capital | C21: CRAR (Total) | D21: =IFERROR(Monthly_KRI_Trend!T19,"") -> 19.3235 | E21: >11.5% | F21: 11.6-12% | G21: <11.5% | H21: Percent | I21: Quarterly | J21: =IFERROR(IF(Monthly_KRI_Trend!D19="Lower Better",IF(Monthly_KRI_Trend!T19<Monthly_KRI_Trend!F19,"Green",IF(Monthly_KRI_Trend!T19<Monthly_KRI_Trend!E19,"Amber","Red")),IF(Monthly_KRI_Trend!T19>Monthly_KRI_Trend!F19,"Green",IF(Monthly_KRI_Trend!T19>Monthly_KRI_Trend!E19,"Amber","Red"))),"") -> Green | K21: -1.64% | L21: =IFERROR(Monthly_KRI_Trend!V19,"") -> 0.11777418 | M21: Basel III RBI | N21: =IF(J21="Green",1,IF(J21="Amber",2,IF(J21="Red",3,""))) -> 1 | O21: =IF(J21="Red","YES",IF(J21="Amber","WATCH","OK")) -> OK
A22: 25 | B22: Pillar 1 – Capital | C22: CET-1 Ratio | D22: =IFERROR(Monthly_KRI_Trend!T20,"") -> 15.62585 | E22: >5.5% | F22: 5.6-6% | G22: <5.5% | H22: Percent | I22: Quarterly | J22: =IFERROR(IF(Monthly_KRI_Trend!D20="Lower Better",IF(Monthly_KRI_Trend!T20<Monthly_KRI_Trend!F20,"Green",IF(Monthly_KRI_Trend!T20<Monthly_KRI_Trend!E20,"Amber","Red")),IF(Monthly_KRI_Trend!T20>Monthly_KRI_Trend!F20,"Green",IF(Monthly_KRI_Trend!T20>Monthly_KRI_Trend!E20,"Amber","Red"))),"") -> Green | K22: +2.76% | L22: =IFERROR(Monthly_KRI_Trend!V20,"") -> 0.12646807 | M22: RBI | N22: =IF(J22="Green",1,IF(J22="Amber",2,IF(J22="Red",3,""))) -> 1 | O22: =IF(J22="Red","YES",IF(J22="Amber","WATCH","OK")) -> OK
A23: 26 | B23: Pillar 1 – Capital | C23: Tier-1 Capital Ratio | D23: =IFERROR(Monthly_Data!N30/Monthly_Data!N32*100,"") -> 16.464042 | E23: >12% | F23: 10-12% | G23: <10% | H23: Percent | I23: Quarterly | J23: =IFERROR(IF(D23>12,"Green",IF(D23>10,"Amber","Red")),"") -> Green | K23: -0.65% | L23: =IFERROR(D23-(Monthly_Data!M30/Monthly_Data!M32*100),"") -> 0.11996051 | M23: RBI | N23: =IF(J23="Green",1,IF(J23="Amber",2,IF(J23="Red",3,""))) -> 1 | O23: =IF(J23="Red","YES",IF(J23="Amber","WATCH","OK")) -> OK
A24: 27 | B24: Pillar 1 – Capital | C24: Capital Conservation Buffer | D24: 2.5 | E24: >2.5% | F24: 2-2.4% | G24: <2.5% | H24: Percent | I24: Quarterly | J24: =IF(D24>=2.5,"Green",IF(D24>=1.875,"Amber","Red")) -> Green | K24: -1.99% | L24: 0 | M24: Basel III | N24: =IF(J24="Green",1,IF(J24="Amber",2,IF(J24="Red",3,""))) -> 1 | O24: =IF(J24="Red","YES",IF(J24="Amber","WATCH","OK")) -> OK
A25: 29 | B25: Pillar 2 – Liquidity | C25: LCR (Liquidity Coverage Ratio) | D25: =IFERROR(Monthly_KRI_Trend!T22,"") -> 128.005 | E25: >120% | F25: 100-120% | G25: <100% | H25: Percent | I25: Daily | J25: =IFERROR(IF(Monthly_KRI_Trend!D22="Lower Better",IF(Monthly_KRI_Trend!T22<Monthly_KRI_Trend!F22,"Green",IF(Monthly_KRI_Trend!T22<Monthly_KRI_Trend!E22,"Amber","Red")),IF(Monthly_KRI_Trend!T22>Monthly_KRI_Trend!F22,"Green",IF(Monthly_KRI_Trend!T22>Monthly_KRI_Trend!E22,"Amber","Red"))),"") -> Green | K25: +2.16% | L25: =IFERROR(Monthly_KRI_Trend!V22,"") -> 0 | M25: RBI | N25: =IF(J25="Green",1,IF(J25="Amber",2,IF(J25="Red",3,""))) -> 1 | O25: =IF(J25="Red","YES",IF(J25="Amber","WATCH","OK")) -> OK
A26: 30 | B26: Pillar 2 – Liquidity | C26: NSFR (Net Stable Funding Ratio) | D26: =IFERROR(Monthly_KRI_Trend!T23,"") -> 112.99994 | E26: >100% | F26: 99-100% | G26: <100% | H26: Percent | I26: Monthly | J26: =IFERROR(IF(Monthly_KRI_Trend!D23="Lower Better",IF(Monthly_KRI_Trend!T23<Monthly_KRI_Trend!F23,"Green",IF(Monthly_KRI_Trend!T23<Monthly_KRI_Trend!E23,"Amber","Red")),IF(Monthly_KRI_Trend!T23>Monthly_KRI_Trend!F23,"Green",IF(Monthly_KRI_Trend!T23>Monthly_KRI_Trend!E23,"Amber","Red"))),"") -> Green | K26: +0.82% | L26: =IFERROR(Monthly_KRI_Trend!V23,"") -> 0 | M26: RBI | N26: =IF(J26="Green",1,IF(J26="Amber",2,IF(J26="Red",3,""))) -> 1 | O26: =IF(J26="Red","YES",IF(J26="Amber","WATCH","OK")) -> OK
A27: 31 | B27: Pillar 2 – Liquidity | C27: SLR (Statutory Liquidity Ratio) | D27: =IFERROR(Monthly_KRI_Trend!T24,"") -> 22.6 | E27: >18% | F27: 18-19% | G27: <18% | H27: Percent | I27: Fortnightly | J27: =IFERROR(IF(Monthly_KRI_Trend!D24="Lower Better",IF(Monthly_KRI_Trend!T24<Monthly_KRI_Trend!F24,"Green",IF(Monthly_KRI_Trend!T24<Monthly_KRI_Trend!E24,"Amber","Red")),IF(Monthly_KRI_Trend!T24>Monthly_KRI_Trend!F24,"Green",IF(Monthly_KRI_Trend!T24>Monthly_KRI_Trend!E24,"Amber","Red"))),"") -> Green | K27: +1.94% | L27: =IFERROR(Monthly_KRI_Trend!V24,"") -> 0 | M27: RBI | N27: =IF(J27="Green",1,IF(J27="Amber",2,IF(J27="Red",3,""))) -> 1 | O27: =IF(J27="Red","YES",IF(J27="Amber","WATCH","OK")) -> OK
A28: 32 | B28: Pillar 2 – Liquidity | C28: CRR (Cash Reserve Ratio) | D28: =IFERROR(Monthly_KRI_Trend!T33,"") -> 4 | E28: >3% | F28: 2.8-2.9% | G28: <3% | H28: Percent | I28: Fortnightly | J28: =IFERROR(IF(Monthly_KRI_Trend!D33="Lower Better",IF(Monthly_KRI_Trend!T33<Monthly_KRI_Trend!F33,"Green",IF(Monthly_KRI_Trend!T33<Monthly_KRI_Trend!E33,"Amber","Red")),IF(Monthly_KRI_Trend!T33>Monthly_KRI_Trend!F33,"Green",IF(Monthly_KRI_Trend!T33>Monthly_KRI_Trend!E33,"Amber","Red"))),"") -> Green | K28: +1.51% | L28: =IFERROR(Monthly_KRI_Trend!V33,"") -> 0 | M28: RBI | N28: =IF(J28="Green",1,IF(J28="Amber",2,IF(J28="Red",3,""))) -> 1 | O28: =IF(J28="Red","YES",IF(J28="Amber","WATCH","OK")) -> OK
A29: 40 | B29: Pillar 2 – Liquidity | C29: HQLA Buffer (₹ Cr) | D29: =IFERROR(Monthly_KRI_Trend!T35,"") -> 31.5 | E29: >60 | F29: 40-60 | G29: <40 | H29: ₹ Cr | I29: Daily | J29: =IFERROR(IF(Monthly_KRI_Trend!D35="Lower Better",IF(Monthly_KRI_Trend!T35<Monthly_KRI_Trend!F35,"Green",IF(Monthly_KRI_Trend!T35<Monthly_KRI_Trend!E35,"Amber","Red")),IF(Monthly_KRI_Trend!T35>Monthly_KRI_Trend!F35,"Green",IF(Monthly_KRI_Trend!T35>Monthly_KRI_Trend!E35,"Amber","Red"))),"") -> Red | K29: +2.85% | L29: =IFERROR(Monthly_KRI_Trend!V35,"") -> 0 | M29: RBI LCR | N29: =IF(J29="Green",1,IF(J29="Amber",2,IF(J29="Red",3,""))) -> 3 | O29: =IF(J29="Red","YES",IF(J29="Amber","WATCH","OK")) -> YES
A30: 36 | B30: Pillar 2 – IRRBB | C30: EVE Sensitivity (+200bps) | D30: =IFERROR(Monthly_KRI_Trend!T28,"") -> -6.2 | E30: >-8% | F30: -8 to -12% | G30: <-12% | H30: Percent of Tier-1 | I30: Quarterly | J30: =IFERROR(IF(Monthly_KRI_Trend!D28="Lower Better",IF(Monthly_KRI_Trend!T28<Monthly_KRI_Trend!F28,"Green",IF(Monthly_KRI_Trend!T28<Monthly_KRI_Trend!E28,"Amber","Red")),IF(Monthly_KRI_Trend!T28>Monthly_KRI_Trend!F28,"Green",IF(Monthly_KRI_Trend!T28>Monthly_KRI_Trend!E28,"Amber","Red"))),"") -> Green | K30: +0.54% | L30: =IFERROR(Monthly_KRI_Trend!V28,"") -> 0 | M30: Basel IRRBB | N30: =IF(J30="Green",1,IF(J30="Amber",2,IF(J30="Red",3,""))) -> 1 | O30: =IF(J30="Red","YES",IF(J30="Amber","WATCH","OK")) -> OK
A31: 37 | B31: Pillar 2 – IRRBB | C31: Duration Gap | D31: =IFERROR(Monthly_KRI_Trend!T38,"") -> 2 | E31: <1.5 | F31: 1.5-2 | G31: >2 | H31: Years | I31: Quarterly | J31: =IFERROR(IF(Monthly_KRI_Trend!D38="Lower Better",IF(Monthly_KRI_Trend!T38<Monthly_KRI_Trend!F38,"Green",IF(Monthly_KRI_Trend!T38<Monthly_KRI_Trend!E38,"Amber","Red")),IF(Monthly_KRI_Trend!T38>Monthly_KRI_Trend!F38,"Green",IF(Monthly_KRI_Trend!T38>Monthly_KRI_Trend!E38,"Amber","Red"))),"") -> Green | K31: +2.06% | L31: =IFERROR(Monthly_KRI_Trend!V38,"") -> 0 | M31: Internal | N31: =IF(J31="Green",1,IF(J31="Amber",2,IF(J31="Red",3,""))) -> 1 | O31: =IF(J31="Red","YES",IF(J31="Amber","WATCH","OK")) -> OK
A32: 39 | B32: Pillar 2 – IRRBB | C32: MCLR Reset Sensitivity | D32: 0.65 | E32: <1% | F32: 1-1.5% | G32: >1.5% | H32: Percent NII impact | I32: Quarterly | J32: =IF(D32<1,"Green",IF(D32<=1.5,"Amber","Red")) -> Green | K32: +2.24% | L32: 0 | M32: RBI | N32: =IF(J32="Green",1,IF(J32="Amber",2,IF(J32="Red",3,""))) -> 1 | O32: =IF(J32="Red","YES",IF(J32="Amber","WATCH","OK")) -> OK
A33: 40 | B33: Pillar 2 – Concentration | C33: Single Borrower Limit Util. | D33: =IFERROR(Monthly_KRI_Trend!T41,"") -> 94.760361 | E33: <80% | F33: 80-90% | G33: >90% | H33: Percent | I33: Monthly | J33: =IFERROR(IF(Monthly_KRI_Trend!D41="Lower Better",IF(Monthly_KRI_Trend!T41<Monthly_KRI_Trend!F41,"Green",IF(Monthly_KRI_Trend!T41<Monthly_KRI_Trend!E41,"Amber","Red")),IF(Monthly_KRI_Trend!T41>Monthly_KRI_Trend!F41,"Green",IF(Monthly_KRI_Trend!T41>Monthly_KRI_Trend!E41,"Amber","Red"))),"") -> Red | K33: +0.68% | L33: =IFERROR(Monthly_KRI_Trend!V41,"") -> -1.2731895 | M33: RBI LSBE | N33: =IF(J33="Green",1,IF(J33="Amber",2,IF(J33="Red",3,""))) -> 3 | O33: =IF(J33="Red","YES",IF(J33="Amber","WATCH","OK")) -> YES
A34: 41 | B34: Pillar 2 – Concentration | C34: Group Borrower Limit Util. | D34: 72 | E34: <70% | F34: 70-80% | G34: >80% | H34: Percent | I34: Monthly | J34: Amber | K34: +1.38% | L34: DW | M34: RBI LSBE | N34: =IF(J34="Green",1,IF(J34="Amber",2,IF(J34="Red",3,""))) -> 2 | O34: =IF(J34="Red","YES",IF(J34="Amber","WATCH","OK")) -> WATCH
A35: 42 | B35: Pillar 2 – Concentration | C35: Top-10 Sector Conc. | D35: 42 | E35: <40% | F35: 40-50% | G35: >50% | H35: Percent of Advances | I35: Quarterly | J35: Amber | K35: -2.25% | L35: DW | M35: Internal | N35: =IF(J35="Green",1,IF(J35="Amber",2,IF(J35="Red",3,""))) -> 2 | O35: =IF(J35="Red","YES",IF(J35="Amber","WATCH","OK")) -> WATCH
A36: 43 | B36: Pillar 2 – Concentration | C36: Geographic HHI Score | D36: 0.18 | E36: <0.20 | F36: 0.20-0.25 | G36: >0.25 | H36: HHI Index | I36: Quarterly | J36: Green | K36: -1.25% | L36: DW | M36: Internal | N36: =IF(J36="Green",1,IF(J36="Amber",2,IF(J36="Red",3,""))) -> 1 | O36: =IF(J36="Red","YES",IF(J36="Amber","WATCH","OK")) -> OK
A37: 44 | B37: Pillar 2 – Concentration | C37: Unsecured Loan Ratio | D37: 22 | E37: <20% | F37: 20-25% | G37: >25% | H37: Percent | I37: Monthly | J37: Amber | K37: -0.91% | L37: Finacle | M37: Internal | N37: =IF(J37="Green",1,IF(J37="Amber",2,IF(J37="Red",3,""))) -> 2 | O37: =IF(J37="Red","YES",IF(J37="Amber","WATCH","OK")) -> WATCH
A38: 45 | B38: Pillar 2 – Climate | C38: Physical Risk Exposure (High) ₹Cr | D38: 4200 | E38: <4000 | F38: 4000-6000 | G38: >6000 | H38: ₹ Cr | I38: Quarterly | J38: Amber | K38: -2.06% | L38: Climate Tool | M38: NGFS/RBI | N38: =IF(J38="Green",1,IF(J38="Amber",2,IF(J38="Red",3,""))) -> 2 | O38: =IF(J38="Red","YES",IF(J38="Amber","WATCH","OK")) -> WATCH
A39: 46 | B39: Pillar 2 – Climate | C39: Transition Risk Score (Portfolio) | D39: 6.2 | E39: <5 | F39: 5-7 | G39: >7 | H39: Score (1-10) | I39: Semi-Annual | J39: Amber | K39: -1.22% | L39: Internal | M39: TCFD | N39: =IF(J39="Green",1,IF(J39="Amber",2,IF(J39="Red",3,""))) -> 2 | O39: =IF(J39="Red","YES",IF(J39="Amber","WATCH","OK")) -> WATCH
A40: 47 | B40: Pillar 2 – Climate | C40: Green Finance Ratio | D40: 9.4 | E40: >10% | F40: 7-10% | G40: <7% | H40: Percent | I40: Quarterly | J40: Amber | K40: -1.94% | L40: DW | M40: RBI | N40: =IF(J40="Green",1,IF(J40="Amber",2,IF(J40="Red",3,""))) -> 2 | O40: =IF(J40="Red","YES",IF(J40="Amber","WATCH","OK")) -> WATCH
A41: 48 | B41: Pillar 2 – Climate | C41: Carbon Intensity (Portfolio avg.) | D41: 182 | E41: <150 | F41: 150-200 | G41: >200 | H41: tCO2/₹Cr | I41: Annual | J41: Amber | K41: -0.97% | L41: Internal | M41: TCFD | N41: =IF(J41="Green",1,IF(J41="Amber",2,IF(J41="Red",3,""))) -> 2 | O41: =IF(J41="Red","YES",IF(J41="Amber","WATCH","OK")) -> WATCH
A42: 49 | B42: Pillar 2 – Climate | C42: Flood-Exposed Advances | D42: 6800 | E42: <6000 | F42: 6000-9000 | G42: >9000 | H42: ₹ Cr | I42: Annual | J42: Amber | K42: +1.0% | L42: Climate Tool | M42: Internal | N42: =IF(J42="Green",1,IF(J42="Amber",2,IF(J42="Red",3,""))) -> 2 | O42: =IF(J42="Red","YES",IF(J42="Amber","WATCH","OK")) -> WATCH
A43: 50 | B43: Pillar 2 – Cyber | C43: Critical Vulnerabilities Unpatched | D43: 3 | E43: <5 | F43: 5-10 | G43: >10 | H43: Count | I43: Weekly | J43: Green | K43: -0.49% | L43: SIEM | M43: RBI IT | N43: =IF(J43="Green",1,IF(J43="Amber",2,IF(J43="Red",3,""))) -> 1 | O43: =IF(J43="Red","YES",IF(J43="Amber","WATCH","OK")) -> OK
A44: 51 | B44: Pillar 2 – Cyber | C44: Mean Time to Detect (MTTD hrs) | D44: 2.8 | E44: <4 | F44: 4-8 | G44: >8 | H44: Hours | I44: Monthly | J44: Green | K44: -0.46% | L44: SOC | M44: NIST | N44: =IF(J44="Green",1,IF(J44="Amber",2,IF(J44="Red",3,""))) -> 1 | O44: =IF(J44="Red","YES",IF(J44="Amber","WATCH","OK")) -> OK
A45: 52 | B45: Pillar 2 – Cyber | C45: Mean Time to Respond (MTTR hrs) | D45: 6.4 | E45: <8 | F45: 8-24 | G45: >24 | H45: Hours | I45: Monthly | J45: Green | K45: -1.35% | L45: SOC | M45: NIST | N45: =IF(J45="Green",1,IF(J45="Amber",2,IF(J45="Red",3,""))) -> 1 | O45: =IF(J45="Red","YES",IF(J45="Amber","WATCH","OK")) -> OK
... A61: 68 | B61: Pillar 3 – Disclosure | C61: Pillar 3 Report Timeliness | D61: 98 | E61: >95% | F61: 90-95% | G61: <90% | H61: Percent on-time | I61: Quarterly | J61: Green | K61: -2.32% | L61: Internal | M61: RBI | N61: =IF(J61="Green",1,IF(J61="Amber",2,IF(J61="Red",3,""))) -> 1 | O61: =IF(J61="Red","YES",IF(J61="Amber","WATCH","OK")) -> OK
A62: 69 | B62: Pillar 3 – Disclosure | C62: ICAAP Submission Date | D62: On-Time | E62: On-Time | F62: Within 7 days | G62: Overdue | H62: Text | I62: Annual | J62: Green | L62: Internal | M62: RBI | N62: =IF(J62="Green",1,IF(J62="Amber",2,IF(J62="Red",3,""))) -> 1 | O62: =IF(J62="Red","YES",IF(J62="Amber","WATCH","OK")) -> OK

Sheet P1_Credit_Risk
A1: PILLAR 1 | Credit Risk – Loan Book Details | Bank Risk Management Dashboard
A2: Loan_ID | B2: Borrower | C2: Segment | D2: Loan_Type | E2: Sanction_Amt_Cr | F2: Outstanding_Cr | G2: DPD_Days | H2: NPA_Category | I2: PD_% | J2: LGD_% | K2: EAD_Cr | L2: ECL_Cr | M2: CRAR_% | N2: Collateral | O2: Risk_Rating | P2: SMA_Flag | Q2: PCR_% | R2: Review_Date | S2: Sector | T2: Geography | U2: Status | V2: RAG
A3: LN20000 | B3: Borrower_001 | C3: Retail | D3: Home Loan | E3: 1796.72 | F3: 1026.49 | G3: 72 | H3: SMA-2 | I3: 19.38 | J3: 47.94 | K3: 1006.87 | L3: =ROUND(K3*(I3/100)*(J3/100),4) -> 93.546 | M3: 13.52 | N3: Stocks | O3: A- | P3: Yes | Q3: 76.2 | R3: 22-Oct-2024 | S3: Retail | T3: Gujarat | U3: Watch | V3: Amber
A4: LN20001 | B4: Borrower_002 | C4: Corporate | D4: Working Capital | E4: 1784.21 | F4: 606.69 | G4: 0 | H4: Standard | I4: 2.61 | J4: 21.77 | K4: 601.48 | L4: =ROUND(K4*(I4/100)*(J4/100),4) -> 3.4176 | M4: 17.52 | N4: Plant & Machinery | O4: A | P4: No | Q4: 52 | R4: 06-Oct-2025 | S4: Retail | T4: Andhra Pradesh | U4: Normal | V4: Green
A5: LN20002 | B5: Borrower_003 | C5: Retail | D5: MSME Loan | E5: 2028.37 | F5: 871.14 | G5: 0 | H5: Standard | I5: 1.22 | J5: 30.28 | K5: 912.73 | L5: =ROUND(K5*(I5/100)*(J5/100),4) -> 3.3718 | M5: 11.99 | N5: Guarantee | O5: A- | P5: No | Q5: 50.2 | R5: 17-Apr-2025 | S5: Shipping | T5: Rajasthan | U5: Normal | V5: Green
A6: LN20003 | B6: Borrower_004 | C6: SME | D6: Home Loan | E6: 519.4 | F6: 345.23 | G6: 0 | H6: Standard | I6: 1.02 | J6: 26.25 | K6: 363.56 | L6: =ROUND(K6*(I6/100)*(J6/100),4) -> 0.9734 | M6: 15.49 | N6: Clean | O6: BBB | P6: No | Q6: 74.2 | R6: 21-Apr-2024 | S6: Real Estate | T6: Telangana | U6: Normal | V6: Green
A7: LN20004 | B7: Borrower_005 | C7: Corporate | D7: Working Capital | E7: 2319.6 | F7: 2034.55 | G7: 0 | H7: Standard | I7: 1.57 | J7: 41.62 | K7: 2138.76 | L7: =ROUND(K7*(I7/100)*(J7/100),4) -> 13.9754 | M7: 12.98 | N7: Immovable Property | O7: A+ | P7: No | Q7: 59.1 | R7: 12-May-2026 | S7: Cement | T7: Andhra Pradesh | U7: Normal | V7: Green
A8: LN20005 | B8: Borrower_006 | C8: Agri | D8: Project Finance | E8: 1756.65 | F8: 1399.6 | G8: 175 | H8: Sub-Standard | I8: 42.96 | J8: 43.87 | K8: 1394.99 | L8: =ROUND(K8*(I8/100)*(J8/100),4) -> 262.9075 | M8: 20.22 | N8: FD | O8: BB | P8: Yes | Q8: 84.6 | R8: 28-Apr-2024 | S8: Infra | T8: Punjab | U8: High | V8: Red
A9: LN20006 | B9: Borrower_007 | C9: Government | D9: CC/OD | E9: 189.35 | F9: 122.19 | G9: 198 | H9: Doubtful-1 | I9: 57.85 | J9: 61.88 | K9: 121.11 | L9: =ROUND(K9*(I9/100)*(J9/100),4) -> 43.3544 | M9: 12.58 | N9: FD | O9: B | P9: Yes | Q9: 75.7 | R9: 10-Apr-2024 | S9: Retail | T9: UP | U9: High | V9: Red
A10: LN20007 | B10: Borrower_008 | C10: Personal | D10: Personal Loan | E10: 2340.03 | F10: 1027.03 | G10: 121 | H10: Sub-Standard | I10: 31.64 | J10: 43.27 | K10: 1055.88 | L10: =ROUND(K10*(I10/100)*(J10/100),4) -> 144.5566 | M10: 15.62 | N10: Clean | O10: BB | P10: Yes | Q10: 45.5 | R10: 27-Nov-2025 | S10: Retail | T10: UP | U10: High | V10: Red
A11: LN20008 | B11: Borrower_009 | C11: SME | D11: Home Loan | E11: 1289.42 | F11: 502.96 | G11: 0 | H11: Standard | I11: 2.67 | J11: 29.24 | K11: 495.01 | L11: =ROUND(K11*(I11/100)*(J11/100),4) -> 3.8646 | M11: 19 | N11: Guarantee | O11: AA | P11: No | Q11: 77.4 | R11: 05-Jun-2026 | S11: Real Estate | T11: Telangana | U11: Normal | V11: Green
A12: LN20009 | B12: Borrower_010 | C12: Corporate | D12: Auto Loan | E12: 2332.8 | F12: 864.16 | G12: 248 | H12: Doubtful-1 | I12: 43.46 | J12: 47.68 | K12: 881.26 | L12: =ROUND(K12*(I12/100)*(J12/100),4) -> 182.6123 | M12: 13.95 | N12: FD | O12: B | P12: Yes | Q12: 83 | R12: 25-Sep-2024 | S12: Real Estate | T12: Delhi | U12: High | V12: Red
A13: LN20010 | B13: Borrower_011 | C13: Agri | D13: MSME Loan | E13: 665.25 | F13: 610.4 | G13: 0 | H13: Standard | I13: 2.53 | J13: 21.1 | K13: 610.41 | L13: =ROUND(K13*(I13/100)*(J13/100),4) -> 3.2586 | M13: 12.68 | N13: Stocks | O13: AA+ | P13: No | Q13: 84.3 | R13: 16-Sep-2025 | S13: Shipping | T13: West Bengal | U13: Normal | V13: Green
A14: LN20011 | B14: Borrower_012 | C14: Corporate | D14: Working Capital | E14: 234.35 | F14: 211.04 | G14: 645 | H14: Doubtful-2 | I14: 60.9 | J14: 64.23 | K14: 215.2 | L14: =ROUND(K14*(I14/100)*(J14/100),4) -> 84.1778 | M14: 15.37 | N14: Immovable Property | O14: CCC | P14: Yes | Q14: 64.3 | R14: 25-May-2026 | S14: Coal | T14: Maharashtra | U14: High | V14: Red
... A202: LN20199 | B202: Borrower_200 | C202: Retail | D202: Home Loan | E202: 98.82 | F202: 61.77 | G202: 0 | H202: Standard | I202: 2.47 | J202: 28.52 | K202: 60.9 | L202: =ROUND(K202*(I202/100)*(J202/100),4) -> 0.429 | M202: 18.72 | N202: Clean | O202: AA | P202: No | Q202: 48.2 | R202: 30-Jul-2024 | S202: Retail | T202: MP | U202: Normal | V202: Green

Sheet P1_Market_Risk
A1: PILLAR 1 | Market Risk – Trading Book Positions | Bank Risk Management Dashboard
A2: Position_ID | B2: Trade_Date | C2: Desk | D2: Asset_Class | E2: Instrument | F2: Currency | G2: Face_Value_Cr | H2: MTM_Cr | I2: VaR_1D_Cr | J2: SVaR_Cr | K2: IRC_Cr | L2: ES_99_Cr | M2: Duration | N2: DV01_Lakhs | O2: Greeks_Delta | P2: Limit_Cr | Q2: Limit_Used_% | R2: Breach_Flag | S2: Rating | T2: Maturity_Date | U2: Status | V2: RAG
A3: POS00001 | B3: 24-Aug-2024 | C3: Commodity | D3: Corporate Bond | E3: Derivative | F3: JPY | G3: 606.65 | H3: 674.66 | I3: 21.0242 | J3: 57.4025 | K3: 15.0633 | L3: 26.9283 | M3: 4.74 | N3: 28.76 | O3: -0.727 | P3: 1383.91 | Q3: =ROUND(I3/P3*100,1) -> 1.5 | R3: No | S3: BBB | T3: 29-Mar-2036 | U3: Normal | V3: Green
A4: POS00002 | B4: 12-Aug-2025 | C4: Equity | D4: FX Forward | E4: Forward | F4: SGD | G4: 679.06 | H4: 718.93 | I4: 47.1535 | J4: 119.9769 | K4: 27.2825 | L4: 78.801 | M4: 2.88 | N4: 19.56 | O4: -0.386 | P4: 2810.83 | Q4: =ROUND(I4/P4*100,1) -> 1.7 | R4: No | S4: AA | T4: 31-Mar-2028 | U4: Normal | V4: Green
A5: POS00003 | B5: 02-Apr-2024 | C5: Equity | D5: Equity | E5: Derivative | F5: JPY | G5: 51.7 | H5: 53.79 | I5: 3.502 | J5: 9.6692 | K5: 2.0197 | L5: 5.7868 | M5: 14.07 | N5: 7.27 | O5: -0.719 | P5: 221.01 | Q5: =ROUND(I5/P5*100,1) -> 1.6 | R5: No | S5: A+ | T5: 31-Mar-2031 | U5: Normal | V5: Green
A6: POS00004 | B6: 22-Feb-2025 | C6: Corporate Bond | D6: Corporate Bond | E6: Derivative | F6: SGD | G6: 478.92 | H6: 510.46 | I6: 14.7097 | J6: 23.7367 | K6: 8.3514 | L6: 25.8088 | M6: 5.45 | N6: 26.1 | O6: 0.574 | P6: 2052.79 | Q6: =ROUND(I6/P6*100,1) -> 0.7 | R6: No | S6: AAA | T6: 30-Mar-2032 | U6: Normal | V6: Green
A7: POS00005 | B7: 23-Jun-2025 | C7: Equity | D7: Equity | E7: Forward | F7: GBP | G7: 360.36 | H7: 358.83 | I7: 15.0183 | J7: 25.8572 | K7: 11.7682 | L7: 28.4032 | M7: 9.87 | N7: 35.57 | O7: 0.374 | P7: 742.53 | Q7: =ROUND(I7/P7*100,1) -> 2 | R7: No | S7: AA+ | T7: 01-Apr-2026 | U7: Normal | V7: Green
A8: POS00006 | B8: 27-Jan-2025 | C8: G-Sec | D8: FX Forward | E8: Option | F8: INR | G8: 79.71 | H8: 76.05 | I8: 2.3787 | J8: 5.8953 | K8: 1.9925 | L8: 4.5635 | M8: 1.67 | N8: 1.33 | O8: 0.188 | P8: 277.41 | Q8: =ROUND(I8/P8*100,1) -> 0.9 | R8: No | S8: BB | T8: 29-Mar-2037 | U8: Normal | V8: Green
A9: POS00007 | B9: 02-May-2024 | C9: FX | D9: T-Bill | E9: Swap | F9: GBP | G9: 135.26 | H9: 127.18 | I9: 2.6382 | J9: 4.8226 | K9: 2.5268 | L9: 4.6897 | M9: 11.03 | N9: 14.92 | O9: -0.469 | P9: 316.08 | Q9: =ROUND(I9/P9*100,1) -> 0.8 | R9: No | S9: A+ | T9: 01-Apr-2027 | U9: Normal | V9: Green
A10: POS00008 | B10: 21-May-2024 | C10: FX | D10: Interest Rate Swap | E10: Derivative | F10: GBP | G10: 132.91 | H10: 131.87 | I10: 4.551 | J10: 8.8902 | K10: 4.2307 | L10: 7.6465 | M10: 3.24 | N10: 4.31 | O10: -0.949 | P10: 276.65 | Q10: =ROUND(I10/P10*100,1) -> 1.6 | R10: No | S10: A | T10: 01-Apr-2027 | U10: Normal | V10: Green
A11: POS00009 | B11: 29-Jul-2025 | C11: Commodity | D11: Corporate Bond | E11: Option | F11: GBP | G11: 345.53 | H11: 379.73 | I11: 9.2769 | J11: 21.9885 | K11: 6.5868 | L11: 13.8858 | M11: 5.91 | N11: 20.42 | O11: -0.627 | P11: 628.89 | Q11: =ROUND(I11/P11*100,1) -> 1.5 | R11: No | S11: BB | T11: 30-Mar-2033 | U11: Normal | V11: Green
A12: POS00010 | B12: 26-Dec-2024 | C12: Corporate Bond | D12: CD | E12: Swap | F12: INR | G12: 131.26 | H12: 139.04 | I12: 1.9459 | J12: 4.6736 | K12: 2.0365 | L12: 2.9795 | M12: 11.42 | N12: 14.99 | O12: -0.545 | P12: 238.24 | Q12: =ROUND(I12/P12*100,1) -> 0.8 | R12: No | S12: BBB | T12: 30-Mar-2034 | U12: Normal | V12: Green
A13: POS00011 | B13: 03-Jun-2025 | C13: Derivatives | D13: CDS | E13: Swap | F13: USD | G13: 349.1 | H13: 326.68 | I13: 20.8984 | J13: 51.3509 | K13: 16.7539 | L13: 40.1325 | M13: 12.07 | N13: 42.14 | O13: 0.355 | P13: 1199.23 | Q13: =ROUND(I13/P13*100,1) -> 1.7 | R13: No | S13: AA+ | T13: 30-Mar-2033 | U13: Normal | V13: Green
A14: POS00012 | B14: 25-Sep-2024 | C14: Corporate Bond | D14: CP | E14: Derivative | F14: USD | G14: 114.54 | H14: 115.08 | I14: 7.972 | J14: 16.9203 | K14: 9.549 | L14: 13.5666 | M14: 12.56 | N14: 14.39 | O14: -0.484 | P14: 539.47 | Q14: =ROUND(I14/P14*100,1) -> 1.5 | R14: No | S14: AA+ | T14: 01-Apr-2027 | U14: Normal | V14: Green
... A202: POS00200 | B202: 08-Jun-2024 | C202: Derivatives | D202: CP | E202: Forward | F202: EUR | G202: 189.88 | H202: 179 | I202: 6.7423 | J202: 18.3861 | K202: 5.826 | L202: 13.264 | M202: 3.38 | N202: 6.42 | O202: 0.49 | P202: 409.74 | Q202: =ROUND(I202/P202*100,1) -> 1.6 | R202: No | S202: A- | T202: 31-Mar-2030 | U202: Normal | V202: Green

Sheet P1_Operational_Risk
A1: PILLAR 1 | Operational Risk – Loss Event Register | Bank Risk Management Dashboard
A2: Incident_ID | B2: Date | C2: Business_Unit | D2: Risk_Category | E2: Event_Type | F2: Gross_Loss_Cr | G2: Net_Loss_Cr | H2: Recovery_Cr | I2: Frequency | J2: RCSA_Score | K2: KRI_Breach | L2: RCA_Done | M2: Control_Adequacy | N2: Residual_Risk | O2: BEL_Estimate_Cr | P2: Action_Owner | Q2: Target_Date | R2: Op_Capital_Cr | S2: Status | T2: RAG
A3: INC2024001 | B3: 30-May-2025 | C3: HR | D3: People Risk | E3: Fraud | F3: 0.427 | G3: =ROUND(F3-H3,2) -> 0.3 | H3: 0.1245 | I3: 16 | J3: 3 | K3: Yes | L3: No | M3: Weak | N3: Medium | O3: =ROUND(F3*I3*0.85,2) -> 5.81 | P3: Owner_40 | Q3: 07-Aug-2025 | R3: =ROUND(O3/100,2) -> 0.06 | S3: Open | T3: Amber
A4: INC2024002 | B4: 11-Jul-2024 | C4: Trade Finance | D4: Internal Fraud | E4: System Failure | F4: 2.3746 | G4: =ROUND(F4-H4,2) -> 1.96 | H4: 0.416 | I4: 3 | J4: 1.4 | K4: No | L4: Yes | M4: Adequate | N4: Medium | O4: =ROUND(F4*I4*0.85,2) -> 6.06 | P4: Owner_10 | Q4: 23-Apr-2026 | R4: =ROUND(O4/100,2) -> 0.06 | S4: Closed | T4: Amber
A5: INC2024003 | B5: 17-Jun-2025 | C5: Retail Banking | D5: People Risk | E5: Natural Disaster | F5: 5.819 | G5: =ROUND(F5-H5,2) -> 3.32 | H5: 2.4964 | I5: 5 | J5: 2.9 | K5: No | L5: No | M5: Strong | N5: Medium | O5: =ROUND(F5*I5*0.85,2) -> 24.73 | P5: Owner_13 | Q5: 04-Mar-2025 | R5: =ROUND(O5/100,2) -> 0.25 | S5: Open | T5: Amber
A6: INC2024004 | B6: 25-Aug-2024 | C6: Forex | D6: Technology Risk | E6: Natural Disaster | F6: 3.4933 | G6: =ROUND(F6-H6,2) -> 1.72 | H6: 1.7782 | I6: 11 | J6: 2.9 | K6: No | L6: No | M6: Weak | N6: High | O6: =ROUND(F6*I6*0.85,2) -> 32.66 | P6: Owner_9 | Q6: 05-May-2026 | R6: =ROUND(O6/100,2) -> 0.33 | S6: Overdue | T6: Amber
A7: INC2024005 | B7: 24-Jun-2024 | C7: Cards | D7: Process Risk | E7: Third Party Failure | F7: 2.2628 | G7: =ROUND(F7-H7,2) -> 1.69 | H7: 0.5696 | I7: 2 | J7: 1.6 | K7: No | L7: No | M7: Adequate | N7: High | O7: =ROUND(F7*I7*0.85,2) -> 3.85 | P7: Owner_11 | Q7: 30-Jan-2026 | R7: =ROUND(O7/100,2) -> 0.04 | S7: Overdue | T7: Amber
A8: INC2024006 | B8: 05-Jul-2024 | C8: ATM | D8: Cyber | E8: Process Error | F8: 1.4655 | G8: =ROUND(F8-H8,2) -> 1.35 | H8: 0.1155 | I8: 11 | J8: 3.3 | K8: No | L8: No | M8: Weak | N8: Low | O8: =ROUND(F8*I8*0.85,2) -> 13.7 | P8: Owner_14 | Q8: 14-Nov-2025 | R8: =ROUND(O8/100,2) -> 0.14 | S8: Open | T8: Amber
A9: INC2024007 | B9: 12-Nov-2025 | C9: IT | D9: Technology Risk | E9: Process Error | F9: 2.2688 | G9: =ROUND(F9-H9,2) -> 1.3 | H9: 0.9708 | I9: 6 | J9: 3.1 | K9: Yes | L9: Yes | M9: Inadequate | N9: Medium | O9: =ROUND(F9*I9*0.85,2) -> 11.57 | P9: Owner_50 | Q9: 15-Apr-2025 | R9: =ROUND(O9/100,2) -> 0.12 | S9: In Progress | T9: Amber
A10: INC2024008 | B10: 23-Nov-2024 | C10: ATM | D10: External Fraud | E10: Theft | F10: 5.8548 | G10: =ROUND(F10-H10,2) -> 4.2 | H10: 1.6504 | I10: 23 | J10: 2.2 | K10: No | L10: In Progress | M10: Adequate | N10: High | O10: =ROUND(F10*I10*0.85,2) -> 114.46 | P10: Owner_47 | Q10: 10-May-2026 | R10: =ROUND(O10/100,2) -> 1.14 | S10: In Progress | T10: Red
A11: INC2024009 | B11: 12-Dec-2024 | C11: Treasury | D11: Business Continuity | E11: Fraud | F11: 0.8796 | G11: =ROUND(F11-H11,2) -> 0.5 | H11: 0.3832 | I11: 10 | J11: 1.1 | K11: No | L11: No | M11: Weak | N11: Low | O11: =ROUND(F11*I11*0.85,2) -> 7.48 | P11: Owner_21 | Q11: 28-Feb-2025 | R11: =ROUND(O11/100,2) -> 0.07 | S11: Closed | T11: Green
A12: INC2024010 | B12: 20-Aug-2025 | C12: Forex | D12: Process Risk | E12: Regulatory Action | F12: 1.2145 | G12: =ROUND(F12-H12,2) -> 1.08 | H12: 0.1318 | I12: 15 | J12: 3.7 | K12: Yes | L12: In Progress | M12: Inadequate | N12: Low | O12: =ROUND(F12*I12*0.85,2) -> 15.48 | P12: Owner_32 | Q12: 12-Jul-2025 | R12: =ROUND(O12/100,2) -> 0.15 | S12: Open | T12: Red
A13: INC2024011 | B13: 13-Nov-2025 | C13: IT | D13: Legal/Compliance | E13: Process Error | F13: 4.31 | G13: =ROUND(F13-H13,2) -> 2.8 | H13: 1.5057 | I13: 13 | J13: 2.5 | K13: No | L13: No | M13: Weak | N13: Medium | O13: =ROUND(F13*I13*0.85,2) -> 47.63 | P13: Owner_29 | Q13: 23-Apr-2026 | R13: =ROUND(O13/100,2) -> 0.48 | S13: Open | T13: Amber
A14: INC2024012 | B14: 08-Aug-2024 | C14: Trade Finance | D14: Legal/Compliance | E14: Third Party Failure | F14: 1.7674 | G14: =ROUND(F14-H14,2) -> 0.68 | H14: 1.0851 | I14: 14 | J14: 3.9 | K14: No | L14: Yes | M14: Strong | N14: Low | O14: =ROUND(F14*I14*0.85,2) -> 21.03 | P14: Owner_14 | Q14: 05-Jul-2025 | R14: =ROUND(O14/100,2) -> 0.21 | S14: In Progress | T14: Red
... A202: INC2024200 | B202: 11-Jan-2025 | C202: Retail Banking | D202: Internal Fraud | E202: System Failure | F202: 0.5417 | G202: =ROUND(F202-H202,2) -> 0.33 | H202: 0.2126 | I202: 22 | J202: 4.6 | K202: No | L202: Yes | M202: Inadequate | N202: Medium | O202: =ROUND(F202*I202*0.85,2) -> 10.13 | P202: Owner_45 | Q202: 16-Feb-2026 | R202: =ROUND(O202/100,2) -> 0.1 | S202: Open | T202: Red

Sheet P1_Capital_Adequacy
A1: PILLAR 1 | Capital Adequacy – CRAR & RWA Trend | Bank Risk Management Dashboard
A2: Quarter | B2: CET1_Cr | C2: Tier1_Cr | D2: Tier2_Cr | E2: Total_Capital_Cr | F2: Credit_RWA_Cr | G2: Market_RWA_Cr | H2: Op_RWA_Cr | I2: Total_RWA_Cr | J2: CET1_% | K2: Tier1_% | L2: CRAR_% | M2: CCB_% | N2: D-SIB_Buffer_% | O2: Leverage_Ratio_% | P2: Capital_Buffer_Cr | Q2: ICAAP_Headroom_Cr | R2: RAG
A3: Q1-FY24 | B3: 321319 | C3: 338640 | D3: 59981 | E3: 398621 | F3: 1602419 | G3: 200602 | H3: 250179 | I3: 2053200 | J3: =ROUND(B3/I3*100,2) -> 15.65 | K3: =ROUND(C3/I3*100,2) -> 16.49 | L3: =ROUND(E3/I3*100,2) -> 19.41 | M3: 2.5 | N3: 0.6 | O3: =ROUND(C3/(I3*11)*100,2) -> 1.5 | P3: =ROUND(E3-I3*0.13,0) -> 131705 | Q3: =ROUND(E3-I3*0.15,0) -> 90641 | R3: Green
A4: Q2-FY24 | B4: 322979 | C4: 340199 | D4: 61217 | E4: 401416 | F4: 1628168 | G4: 202693 | H4: 253792 | I4: 2084653 | J4: =ROUND(B4/I4*100,2) -> 15.49 | K4: =ROUND(C4/I4*100,2) -> 16.32 | L4: =ROUND(E4/I4*100,2) -> 19.26 | M4: 2.5 | N4: 0.6 | O4: =ROUND(C4/(I4*11)*100,2) -> 1.48 | P4: =ROUND(E4-I4*0.13,0) -> 130411 | Q4: =ROUND(E4-I4*0.15,0) -> 88718 | R4: Green
A5: Q3-FY24 | B5: 327384 | C5: 345646 | D5: 61485 | E5: 407131 | F5: 1652425 | G5: 208165 | H5: 256048 | I5: 2116638 | J5: =ROUND(B5/I5*100,2) -> 15.47 | K5: =ROUND(C5/I5*100,2) -> 16.33 | L5: =ROUND(E5/I5*100,2) -> 19.23 | M5: 2.5 | N5: 0.6 | O5: =ROUND(C5/(I5*11)*100,2) -> 1.48 | P5: =ROUND(E5-I5*0.13,0) -> 131968 | Q5: =ROUND(E5-I5*0.15,0) -> 89635 | R5: Green
A6: Q4-FY24 | B6: 334797 | C6: 353736 | D6: 62521 | E6: 416257 | F6: 1668436 | G6: 213454 | H6: 260206 | I6: 2142096 | J6: =ROUND(B6/I6*100,2) -> 15.63 | K6: =ROUND(C6/I6*100,2) -> 16.51 | L6: =ROUND(E6/I6*100,2) -> 19.43 | M6: 2.5 | N6: 0.6 | O6: =ROUND(C6/(I6*11)*100,2) -> 1.5 | P6: =ROUND(E6-I6*0.13,0) -> 137785 | Q6: =ROUND(E6-I6*0.15,0) -> 94943 | R6: Green
A7: Q1-FY25 | B7: 341088 | C7: 359474 | D7: 63005 | E7: 422479 | F7: 1693048 | G7: 215824 | H7: 262787 | I7: 2171659 | J7: =ROUND(B7/I7*100,2) -> 15.71 | K7: =ROUND(C7/I7*100,2) -> 16.55 | L7: =ROUND(E7/I7*100,2) -> 19.45 | M7: 2.5 | N7: 0.6 | O7: =ROUND(C7/(I7*11)*100,2) -> 1.5 | P7: =ROUND(E7-I7*0.13,0) -> 140163 | Q7: =ROUND(E7-I7*0.15,0) -> 96730 | R7: Green
A8: Q2-FY25 | B8: 342185 | C8: 360541 | D8: 63226 | E8: 423767 | F8: 1716781 | G8: 219499 | H8: 265931 | I8: 2202211 | J8: =ROUND(B8/I8*100,2) -> 15.54 | K8: =ROUND(C8/I8*100,2) -> 16.37 | L8: =ROUND(E8/I8*100,2) -> 19.24 | M8: 2.5 | N8: 0.6 | O8: =ROUND(C8/(I8*11)*100,2) -> 1.49 | P8: =ROUND(E8-I8*0.13,0) -> 137480 | Q8: =ROUND(E8-I8*0.15,0) -> 93435 | R8: Green
A9: Q3-FY25 | B9: 346529 | C9: 366593 | D9: 64328 | E9: 430921 | F9: 1743206 | G9: 223003 | H9: 267794 | I9: 2234003 | J9: =ROUND(B9/I9*100,2) -> 15.51 | K9: =ROUND(C9/I9*100,2) -> 16.41 | L9: =ROUND(E9/I9*100,2) -> 19.29 | M9: 2.5 | N9: 0.6 | O9: =ROUND(C9/(I9*11)*100,2) -> 1.49 | P9: =ROUND(E9-I9*0.13,0) -> 140501 | Q9: =ROUND(E9-I9*0.15,0) -> 95821 | R9: Green
A10: Q4-FY25 | B10: 355804 | C10: 374662 | D10: 64781 | E10: 439443 | F10: 1774406 | G10: 226457 | H10: 271766 | I10: 2272629 | J10: =ROUND(B10/I10*100,2) -> 15.66 | K10: =ROUND(C10/I10*100,2) -> 16.49 | L10: =ROUND(E10/I10*100,2) -> 19.34 | M10: 2.5 | N10: 0.6 | O10: =ROUND(C10/(I10*11)*100,2) -> 1.5 | P10: =ROUND(E10-I10*0.13,0) -> 144001 | Q10: =ROUND(E10-I10*0.15,0) -> 98549 | R10: Green
A11: Q1-FY26 | B11: 359199 | C11: 379036 | D11: 65861 | E11: 444897 | F11: 1795343 | G11: 230100 | H11: 275332 | I11: 2300775 | J11: =ROUND(B11/I11*100,2) -> 15.61 | K11: =ROUND(C11/I11*100,2) -> 16.47 | L11: =ROUND(E11/I11*100,2) -> 19.34 | M11: 2.5 | N11: 0.6 | O11: =ROUND(C11/(I11*11)*100,2) -> 1.5 | P11: =ROUND(E11-I11*0.13,0) -> 145796 | Q11: =ROUND(E11-I11*0.15,0) -> 99781 | R11: Green
A12: Q2-FY26 | B12: 362448 | C12: 382633 | D12: 66094 | E12: 448727 | F12: 1811811 | G12: 235791 | H12: 276272 | I12: 2323874 | J12: =ROUND(B12/I12*100,2) -> 15.6 | K12: =ROUND(C12/I12*100,2) -> 16.47 | L12: =ROUND(E12/I12*100,2) -> 19.31 | M12: 2.5 | N12: 0.6 | O12: =ROUND(C12/(I12*11)*100,2) -> 1.5 | P12: =ROUND(E12-I12*0.13,0) -> 146623 | Q12: =ROUND(E12-I12*0.15,0) -> 100146 | R12: Green
A13: Q3-FY26 | B13: 366393 | C13: 386361 | D13: 67647 | E13: 454008 | F13: 1846812 | G13: 237903 | H13: 279205 | I13: 2363920 | J13: =ROUND(B13/I13*100,2) -> 15.5 | K13: =ROUND(C13/I13*100,2) -> 16.34 | L13: =ROUND(E13/I13*100,2) -> 19.21 | M13: 2.5 | N13: 0.6 | O13: =ROUND(C13/(I13*11)*100,2) -> 1.49 | P13: =ROUND(E13-I13*0.13,0) -> 146698 | Q13: =ROUND(E13-I13*0.15,0) -> 99420 | R13: Green
A14: Q4-FY26 | B14: 372064 | C14: 392022 | D14: 68086 | E14: 460108 | F14: 1859378 | G14: 239037 | H14: 282665 | I14: 2381080 | J14: =ROUND(B14/I14*100,2) -> 15.63 | K14: =ROUND(C14/I14*100,2) -> 16.46 | L14: =ROUND(E14/I14*100,2) -> 19.32 | M14: 2.5 | N14: 0.6 | O14: =ROUND(C14/(I14*11)*100,2) -> 1.5 | P14: =ROUND(E14-I14*0.13,0) -> 150568 | Q14: =ROUND(E14-I14*0.15,0) -> 102946 | R14: Green

Sheet P2_Liquidity_Risk
A1: PILLAR 2 | Liquidity Risk – LCR/NSFR/Gap Analysis | Bank Risk Management Dashboard
A2: Record_ID | B2: Date | C2: Time_Bucket | D2: Inflow_Cr | E2: Outflow_Cr | F2: Net_Gap_Cr | G2: Cumul_Gap_Cr | H2: LCR_% | I2: NSFR_% | J2: SLR_% | K2: CRR_% | L2: HQLA_Cr | M2: HQLA_L1_Cr | N2: HQLA_L2_Cr | O2: Net_Cash_Outflow_30D_Cr | P2: Stress_Scenario | Q2: NSFR_RSF_Cr | R2: NSFR_ASF_Cr | S2: Status | T2: RAG
A3: LIQ00001 | B3: 07-Jul-2025 | C3: 8-14 Days | D3: 2460.35 | E3: 591.2 | F3: =ROUND(D3-E3,2) -> 1869.15 | G3: =ROUND(F3,2) -> 1869.15 | H3: =ROUND(L3/O3*100,2) -> 141.67 | I3: =ROUND(R3/Q3*100,2) -> 122.87 | J3: 23.06 | K3: 3.64 | L3: 3616.8 | M3: 2928.42 | N3: 688.38 | O3: 2552.96 | P3: Moderate Stress | Q3: 17944.31 | R3: 22048.55 | S3: Normal | T3: Green
A4: LIQ00002 | B4: 08-Jul-2024 | C4: 2-3 Months | D4: 3425.49 | E4: 3921.85 | F4: =ROUND(D4-E4,2) -> -496.36 | G4: =ROUND(G3+F4,2) -> 1372.79 | H4: =ROUND(L4/O4*100,2) -> 149.29 | I4: =ROUND(R4/Q4*100,2) -> 119.14 | J4: 21.19 | K4: 5.08 | L4: 5532.84 | M4: 4677.71 | N4: 855.13 | O4: 3706 | P4: Severe Stress | Q4: 6310.92 | R4: 7519.1 | S4: Normal | T4: Green
A5: LIQ00003 | B5: 10-May-2024 | C5: 1-2 Months | D5: 835.27 | E5: 748.94 | F5: =ROUND(D5-E5,2) -> 86.33 | G5: =ROUND(G4+F5,2) -> 1459.12 | H5: =ROUND(L5/O5*100,2) -> 138.41 | I5: =ROUND(R5/Q5*100,2) -> 126.92 | J5: 21.58 | K5: 4.17 | L5: 5733.27 | M5: 4928.91 | N5: 804.36 | O5: 4142.22 | P5: Moderate Stress | Q5: 7755.96 | R5: 9844.17 | S5: Normal | T5: Green
A6: LIQ00004 | B6: 19-Aug-2024 | C6: Overnight | D6: 677.89 | E6: 5878.96 | F6: =ROUND(D6-E6,2) -> -5201.07 | G6: =ROUND(G5+F6,2) -> -3741.95 | H6: =ROUND(L6/O6*100,2) -> 146.96 | I6: =ROUND(R6/Q6*100,2) -> 127.27 | J6: 19.55 | K6: 4.55 | L6: 3633.88 | M6: 2711.13 | N6: 922.75 | O6: 2472.63 | P6: Moderate Stress | Q6: 13065.92 | R6: 16629.25 | S6: Normal | T6: Green
A7: LIQ00005 | B7: 19-May-2024 | C7: 1-3Y | D7: 2158.51 | E7: 3475.73 | F7: =ROUND(D7-E7,2) -> -1317.22 | G7: =ROUND(G6+F7,2) -> -5059.17 | H7: =ROUND(L7/O7*100,2) -> 105.94 | I7: =ROUND(R7/Q7*100,2) -> 127.24 | J7: 18.91 | K7: 4.14 | L7: 3754.22 | M7: 3117.58 | N7: 636.64 | O7: 3543.59 | P7: Severe Stress | Q7: 8168.07 | R7: 10393.33 | S7: Watch | T7: Amber
A8: LIQ00006 | B8: 14-Mar-2025 | C8: 1-3Y | D8: 3354.86 | E8: 5303.92 | F8: =ROUND(D8-E8,2) -> -1949.06 | G8: =ROUND(G7+F8,2) -> -7008.23 | H8: =ROUND(L8/O8*100,2) -> 115.54 | I8: =ROUND(R8/Q8*100,2) -> 117.7 | J8: 24.34 | K8: 4.93 | L8: 4995.24 | M8: 3938.03 | N8: 1057.21 | O8: 4323.25 | P8: Mild Stress | Q8: 7712.04 | R8: 9077.26 | S8: Watch | T8: Amber
A9: LIQ00007 | B9: 15-Aug-2024 | C9: Overnight | D9: 5518.81 | E9: 3871.24 | F9: =ROUND(D9-E9,2) -> 1647.57 | G9: =ROUND(G8+F9,2) -> -5360.66 | H9: =ROUND(L9/O9*100,2) -> 140.69 | I9: =ROUND(R9/Q9*100,2) -> 126.94 | J9: 22.06 | K9: 4.42 | L9: 4852.59 | M9: 3717.02 | N9: 1135.57 | O9: 3449.06 | P9: Severe Stress | Q9: 17834.96 | R9: 22639.48 | S9: Normal | T9: Green
A10: LIQ00008 | B10: 14-Dec-2024 | C10: 1-2 Months | D10: 1727.36 | E10: 2623.81 | F10: =ROUND(D10-E10,2) -> -896.45 | G10: =ROUND(G9+F10,2) -> -6257.11 | H10: =ROUND(L10/O10*100,2) -> 148.84 | I10: =ROUND(R10/Q10*100,2) -> 107.51 | J10: 21.09 | K10: 5.22 | L10: 10084.22 | M10: 7603.4 | N10: 2480.82 | O10: 6775.14 | P10: Moderate Stress | Q10: 10878.18 | R10: 11695.07 | S10: Watch | T10: Amber
A11: LIQ00009 | B11: 17-May-2024 | C11: 5+ Years | D11: 568.9 | E11: 4406.72 | F11: =ROUND(D11-E11,2) -> -3837.82 | G11: =ROUND(G10+F11,2) -> -10094.93 | H11: =ROUND(L11/O11*100,2) -> 103.44 | I11: =ROUND(R11/Q11*100,2) -> 95.43 | J11: 24.82 | K11: 4.61 | L11: 9020.67 | M11: 7625.1 | N11: 1395.57 | O11: 8720.28 | P11: Severe Stress | Q11: 15700.16 | R11: 14982.32 | S11: High | T11: Red
A12: LIQ00010 | B12: 30-Jul-2025 | C12: 3-6 Months | D12: 4094.5 | E12: 5601.4 | F12: =ROUND(D12-E12,2) -> -1506.9 | G12: =ROUND(G11+F12,2) -> -11601.83 | H12: =ROUND(L12/O12*100,2) -> 141.11 | I12: =ROUND(R12/Q12*100,2) -> 119.65 | J12: 24.25 | K12: 4.56 | L12: 2658.7 | M12: 2127.71 | N12: 530.99 | O12: 1884.17 | P12: Base | Q12: 10865.66 | R12: 13000.92 | S12: Normal | T12: Green
A13: LIQ00011 | B13: 11-Jul-2025 | C13: Overnight | D13: 4313.54 | E13: 4245.29 | F13: =ROUND(D13-E13,2) -> 68.25 | G13: =ROUND(G12+F13,2) -> -11533.58 | H13: =ROUND(L13/O13*100,2) -> 144.34 | I13: =ROUND(R13/Q13*100,2) -> 133.59 | J13: 26.58 | K13: 5.15 | L13: 7550.02 | M13: 6297.74 | N13: 1252.28 | O13: 5230.76 | P13: Base | Q13: 13288.48 | R13: 17751.53 | S13: Normal | T13: Green
A14: LIQ00012 | B14: 12-Mar-2025 | C14: 1-3Y | D14: 5432.41 | E14: 1131.4 | F14: =ROUND(D14-E14,2) -> 4301.01 | G14: =ROUND(G13+F14,2) -> -7232.57 | H14: =ROUND(L14/O14*100,2) -> 121.2 | I14: =ROUND(R14/Q14*100,2) -> 99.53 | J14: 18.93 | K14: 4.49 | L14: 4348.89 | M14: 3695.95 | N14: 652.94 | O14: 3588.27 | P14: Mild Stress | Q14: 10479.4 | R14: 10430.08 | S14: High | T14: Red
A15: LIQ00013 | B15: 12-Jul-2025 | C15: 5+ Years | D15: 1573.61 | E15: 3280.81 | F15: =ROUND(D15-E15,2) -> -1707.2 | G15: =ROUND(G14+F15,2) -> -8939.77 | H15: =ROUND(L15/O15*100,2) -> 117.95 | I15: =ROUND(R15/Q15*100,2) -> 107.19 | J15: 21 | K15: 3.93 | L15: 7524.49 | M15: 6411.61 | N15: 1112.88 | O15: 6379.35 | P15: Severe Stress | Q15: 8609.56 | R15: 9228.83 | S15: Watch | T15: Amber
... A202: LIQ00200 | B202: 17-Aug-2024 | C202: 2-7 Days | D202: 551.51 | E202: 3076.61 | F202: =ROUND(D202-E202,2) -> -2525.1 | G202: =ROUND(G201+F202,2) -> -22226.3 | H202: =ROUND(L202/O202*100,2) -> 101.21 | I202: =ROUND(R202/Q202*100,2) -> 118.53 | J202: 24.81 | K202: 4.58 | L202: 7758.07 | M202: 5983.73 | N202: 1774.34 | O202: 7665.38 | P202: Mild Stress | Q202: 7146.68 | R202: 8470.8 | S202: Watch | T202: Amber

Sheet P2_IRRBB
A1: PILLAR 2 | IRRBB – Interest Rate Risk in Banking Book | Bank Risk Management Dashboard
A2: Record_ID | B2: Date | C2: Rate_Shock_bps | D2: Asset_Repricing_Cr | E2: Liability_Repricing_Cr | F2: Repricing_Gap_Cr | G2: NII_Impact_Cr | H2: NII_Impact_% | I2: EVE_Impact_Cr | J2: EVE_Impact_Pct_Tier1 | K2: Duration_Assets_Yrs | L2: Duration_Liab_Yrs | M2: Duration_Gap_Yrs | N2: MCLR_1Y_% | O2: Base_Rate_% | P2: Deposit_Rate_% | Q2: Yield_Portfolio_% | R2: Delta_NII_Parallel_Up | S2: Delta_NII_Parallel_Down | T2: Delta_NII_Steepener | U2: Scenario | V2: Status | W2: RAG
A3: IRR0001 | B3: 04-Feb-2025 | C3: 100 | D3: 179776.61 | E3: 164523.34 | F3: =ROUND(D3-E3,2) -> 15253.27 | G3: =ROUND(F3*C3/10000,2) -> 152.53 | H3: =ROUND(G3/320000*100,2) -> 0.05 | I3: =ROUND(F3*M3*C3/10000,2) -> 655.89 | J3: =ROUND(I3/380000*100,2) -> 0.17 | K3: 7.21 | L3: 2.91 | M3: =ROUND(K3-L3,2) -> 4.3 | N3: 9.76 | O3: 9.26 | P3: 5.91 | Q3: 9.07 | R3: 290.68 | S3: -314.59 | T3: 89.77 | U3: +200bps | V3: Normal | W3: Green
A4: IRR0002 | B4: 15-Mar-2025 | C4: -100 | D4: 106670.35 | E4: 114696.38 | F4: =ROUND(D4-E4,2) -> -8026.03 | G4: =ROUND(F4*C4/10000,2) -> 80.26 | H4: =ROUND(G4/320000*100,2) -> 0.03 | I4: =ROUND(F4*M4*C4/10000,2) -> 151.69 | J4: =ROUND(I4/380000*100,2) -> 0.04 | K4: 4.17 | L4: 2.28 | M4: =ROUND(K4-L4,2) -> 1.89 | N4: 9.69 | O4: 9.19 | P4: 6.52 | Q4: 8.72 | R4: -167.83 | S4: 175.01 | T4: 56.59 | U4: Bull Flat | V4: Normal | W4: Green
A5: IRR0003 | B5: 08-Apr-2025 | C5: 100 | D5: 149345.54 | E5: 72738.11 | F5: =ROUND(D5-E5,2) -> 76607.43 | G5: =ROUND(F5*C5/10000,2) -> 766.07 | H5: =ROUND(G5/320000*100,2) -> 0.24 | I5: =ROUND(F5*M5*C5/10000,2) -> 3156.23 | J5: =ROUND(I5/380000*100,2) -> 0.83 | K5: 7.13 | L5: 3.01 | M5: =ROUND(K5-L5,2) -> 4.12 | N5: 9.31 | O5: 8.81 | P5: 5.33 | Q5: 8.4 | R5: 1627.04 | S5: -1677.95 | T5: -335.66 | U5: +300bps | V5: Normal | W5: Green
A6: IRR0004 | B6: 31-Jul-2024 | C6: 300 | D6: 151209.14 | E6: 79227.77 | F6: =ROUND(D6-E6,2) -> 71981.37 | G6: =ROUND(F6*C6/10000,2) -> 2159.44 | H6: =ROUND(G6/320000*100,2) -> 0.67 | I6: =ROUND(F6*M6*C6/10000,2) -> 323.92 | J6: =ROUND(I6/380000*100,2) -> 0.09 | K6: 4.92 | L6: 4.77 | M6: =ROUND(K6-L6,2) -> 0.15 | N6: 9.39 | O6: 8.89 | P6: 7.52 | Q6: 10.42 | R6: 1516.62 | S6: -1368.23 | T6: 377.6 | U6: +100bps | V6: Normal | W6: Green
A7: IRR0005 | B7: 03-Jun-2024 | C7: -200 | D7: 118573.16 | E7: 132184.36 | F7: =ROUND(D7-E7,2) -> -13611.2 | G7: =ROUND(F7*C7/10000,2) -> 272.22 | H7: =ROUND(G7/320000*100,2) -> 0.09 | I7: =ROUND(F7*M7*C7/10000,2) -> 1064.4 | J7: =ROUND(I7/380000*100,2) -> 0.28 | K7: 4.94 | L7: 1.03 | M7: =ROUND(K7-L7,2) -> 3.91 | N7: 9.67 | O7: 9.17 | P7: 7.27 | Q7: 10.58 | R7: -272.21 | S7: 297.24 | T7: -67.28 | U7: Bear Steep | V7: Normal | W7: Green
A8: IRR0006 | B8: 09-May-2025 | C8: 300 | D8: 146576.87 | E8: 151365.35 | F8: =ROUND(D8-E8,2) -> -4788.48 | G8: =ROUND(F8*C8/10000,2) -> -143.65 | H8: =ROUND(G8/320000*100,2) -> -0.04 | I8: =ROUND(F8*M8*C8/10000,2) -> -251.4 | J8: =ROUND(I8/380000*100,2) -> -0.07 | K8: 6.9 | L8: 5.15 | M8: =ROUND(K8-L8,2) -> 1.75 | N8: 9.22 | O8: 8.72 | P8: 5.23 | Q8: 7.57 | R8: -89.3 | S8: 100.52 | T8: -22.34 | U8: +100bps | V8: Normal | W8: Green
A9: IRR0007 | B9: 26-Apr-2024 | C9: -200 | D9: 186260.34 | E9: 124470.3 | F9: =ROUND(D9-E9,2) -> 61790.04 | G9: =ROUND(F9*C9/10000,2) -> -1235.8 | H9: =ROUND(G9/320000*100,2) -> -0.39 | I9: =ROUND(F9*M9*C9/10000,2) -> -3583.82 | J9: =ROUND(I9/380000*100,2) -> -0.94 | K9: 6.26 | L9: 3.36 | M9: =ROUND(K9-L9,2) -> 2.9 | N9: 8.74 | O9: 8.24 | P9: 7.62 | Q9: 8.88 | R9: 1185.57 | S9: -1219.85 | T9: 319.88 | U9: +100bps | V9: Normal | W9: Green
A10: IRR0008 | B10: 19-Jun-2025 | C10: 200 | D10: 153812.06 | E10: 110879.5 | F10: =ROUND(D10-E10,2) -> 42932.56 | G10: =ROUND(F10*C10/10000,2) -> 858.65 | H10: =ROUND(G10/320000*100,2) -> 0.27 | I10: =ROUND(F10*M10*C10/10000,2) -> 4087.18 | J10: =ROUND(I10/380000*100,2) -> 1.08 | K10: 6.4 | L10: 1.64 | M10: =ROUND(K10-L10,2) -> 4.76 | N10: 9.39 | O10: 8.89 | P10: 5.61 | Q10: 9.76 | R10: 861.98 | S10: -815.93 | T10: 251.22 | U10: Flattener | V10: Normal | W10: Green
A11: IRR0009 | B11: 18-May-2024 | C11: -100 | D11: 142925.41 | E11: 161234.88 | F11: =ROUND(D11-E11,2) -> -18309.47 | G11: =ROUND(F11*C11/10000,2) -> 183.09 | H11: =ROUND(G11/320000*100,2) -> 0.06 | I11: =ROUND(F11*M11*C11/10000,2) -> -56.76 | J11: =ROUND(I11/380000*100,2) -> -0.01 | K11: 2.56 | L11: 2.87 | M11: =ROUND(K11-L11,2) -> -0.31 | N11: 8.76 | O11: 8.26 | P11: 5.2 | Q11: 11.4 | R11: -380.94 | S11: 344.16 | T11: -80.11 | U11: -200bps | V11: Normal | W11: Green
A12: IRR0010 | B12: 04-Dec-2024 | C12: -100 | D12: 87332.93 | E12: 121556.35 | F12: =ROUND(D12-E12,2) -> -34223.42 | G12: =ROUND(F12*C12/10000,2) -> 342.23 | H12: =ROUND(G12/320000*100,2) -> 0.11 | I12: =ROUND(F12*M12*C12/10000,2) -> 294.32 | J12: =ROUND(I12/380000*100,2) -> 0.08 | K12: 3.44 | L12: 2.58 | M12: =ROUND(K12-L12,2) -> 0.86 | N12: 9.45 | O12: 8.95 | P12: 5.68 | Q12: 9.83 | R12: -653.61 | S12: 728.38 | T12: -255.73 | U12: -100bps | V12: Normal | W12: Green
A13: IRR0011 | B13: 11-Jan-2025 | C13: 200 | D13: 192116.95 | E13: 131722.35 | F13: =ROUND(D13-E13,2) -> 60394.6 | G13: =ROUND(F13*C13/10000,2) -> 1207.89 | H13: =ROUND(G13/320000*100,2) -> 0.38 | I13: =ROUND(F13*M13*C13/10000,2) -> 5363.04 | J13: =ROUND(I13/380000*100,2) -> 1.41 | K13: 6.35 | L13: 1.91 | M13: =ROUND(K13-L13,2) -> 4.44 | N13: 9.51 | O13: 9.01 | P13: 5.31 | Q13: 7.97 | R13: 1150.62 | S13: -1111.82 | T13: 434.09 | U13: +300bps | V13: Normal | W13: Green
A14: IRR0012 | B14: 04-Dec-2024 | C14: 100 | D14: 195999.07 | E14: 151099.21 | F14: =ROUND(D14-E14,2) -> 44899.86 | G14: =ROUND(F14*C14/10000,2) -> 449 | H14: =ROUND(G14/320000*100,2) -> 0.14 | I14: =ROUND(F14*M14*C14/10000,2) -> 498.39 | J14: =ROUND(I14/380000*100,2) -> 0.13 | K14: 6.2 | L14: 5.09 | M14: =ROUND(K14-L14,2) -> 1.11 | N14: 8.86 | O14: 8.36 | P14: 5.01 | Q14: 8.04 | R14: 824.6 | S14: -952.48 | T14: -205.91 | U14: -100bps | V14: Normal | W14: Green
... A202: IRR0200 | B202: 09-Feb-2024 | C202: 300 | D202: 171085.94 | E202: 79551.15 | F202: =ROUND(D202-E202,2) -> 91534.79 | G202: =ROUND(F202*C202/10000,2) -> 2746.04 | H202: =ROUND(G202/320000*100,2) -> 0.86 | I202: =ROUND(F202*M202*C202/10000,2) -> 7139.71 | J202: =ROUND(I202/380000*100,2) -> 1.88 | K202: 4.01 | L202: 1.41 | M202: =ROUND(K202-L202,2) -> 2.6 | N202: 8.92 | O202: 8.42 | P202: 7.49 | Q202: 9.84 | R202: 1814.1 | S202: -1921.88 | T202: 454.52 | U202: +200bps | V202: Normal | W202: Green

Sheet P2_Concentration_Risk
A1: PILLAR 2 | Concentration Risk – Sector/Geo/Borrower Analysis | Bank Risk Management Dashboard
A2: Record_ID | B2: Date | C2: Dimension | D2: Category | E2: Exposure_Cr | F2: Total_Advances_Cr | G2: Conc_% | H2: Regulatory_Limit_% | I2: Utilisation_% | J2: HHI_Index | K2: Top5_Exposure_Cr | L2: Top10_Exposure_Cr | M2: Single_Borrower_Cap_% | N2: Group_Borrower_Cap_% | O2: Breach_Flag | P2: Action_Required | Q2: Status | R2: RAG
A3: CON0001 | B3: 05-Feb-2024 | C3: Maturity | D3: 3-5Y | E3: 195655.89 | F3: 3200000 | G3: =ROUND(E3/F3*100,2) -> 6.11 | H3: 40 | I3: =ROUND(G3/H3*100,2) -> 15.28 | J3: 0.3105 | K3: 861355.09 | L3: 1695345.2 | M3: 15 | N3: 25 | O3: No | P3: No Action | Q3: Low | R3: Green
A4: CON0002 | B4: 07-Apr-2024 | C4: Sector | D4: Steel | E4: 209733.03 | F4: 3200000 | G4: =ROUND(E4/F4*100,2) -> 6.55 | H4: 40 | I4: =ROUND(G4/H4*100,2) -> 16.38 | J4: 0.2998 | K4: 745909.54 | L4: 1420045.2 | M4: 15 | N4: 25 | O4: No | P4: No Action | Q4: Low | R4: Green
A5: CON0003 | B5: 11-Mar-2024 | C5: Product | D5: Term Loan | E5: 99785.7 | F5: 3200000 | G5: =ROUND(E5/F5*100,2) -> 3.12 | H5: 40 | I5: =ROUND(G5/H5*100,2) -> 7.8 | J5: 0.2591 | K5: 509168.05 | L5: 978314.35 | M5: 15 | N5: 25 | O5: No | P5: No Action | Q5: Low | R5: Green
A6: CON0004 | B6: 19-Feb-2024 | C6: Rating Band | D6: NR | E6: 45595.66 | F6: 3200000 | G6: =ROUND(E6/F6*100,2) -> 1.42 | H6: 40 | I6: =ROUND(G6/H6*100,2) -> 3.55 | J6: 0.2412 | K6: 175444.68 | L6: 328263.23 | M6: 15 | N6: 25 | O6: No | P6: No Action | Q6: Low | R6: Green
A7: CON0005 | B7: 15-Jun-2024 | C7: Sector | D7: IT | E7: 212386.52 | F7: 3200000 | G7: =ROUND(E7/F7*100,2) -> 6.64 | H7: 40 | I7: =ROUND(G7/H7*100,2) -> 16.6 | J7: 0.2079 | K7: 1035090.1 | L7: 2257675.2 | M7: 15 | N7: 25 | O7: No | P7: No Action | Q7: Low | R7: Green
A8: CON0006 | B8: 19-Mar-2024 | C8: Borrower Group | D8: Agri | E8: 172755.37 | F8: 3200000 | G8: =ROUND(E8/F8*100,2) -> 5.4 | H8: 25 | I8: =ROUND(G8/H8*100,2) -> 21.6 | J8: 0.0521 | K8: 872670.34 | L8: 1818716.2 | M8: 15 | N8: 25 | O8: No | P8: No Action | Q8: Low | R8: Green
A9: CON0007 | B9: 29-Jun-2024 | C9: Currency | D9: INR | E9: 109285.44 | F9: 3200000 | G9: =ROUND(E9/F9*100,2) -> 3.42 | H9: 40 | I9: =ROUND(G9/H9*100,2) -> 8.55 | J9: 0.1327 | K9: 571686.47 | L9: 1114869.7 | M9: 15 | N9: 25 | O9: No | P9: No Action | Q9: Low | R9: Green
A10: CON0008 | B10: 20-May-2025 | C10: Borrower Group | D10: Housing | E10: 158409.91 | F10: 3200000 | G10: =ROUND(E10/F10*100,2) -> 4.95 | H10: 25 | I10: =ROUND(G10/H10*100,2) -> 19.8 | J10: 0.3093 | K10: 843265.12 | L10: 1400598.1 | M10: 15 | N10: 25 | O10: No | P10: No Action | Q10: Low | R10: Green
A11: CON0009 | B11: 22-May-2024 | C11: Product | D11: MSME Loan | E11: 342684.94 | F11: 3200000 | G11: =ROUND(E11/F11*100,2) -> 10.71 | H11: 40 | I11: =ROUND(G11/H11*100,2) -> 26.78 | J11: 0.2739 | K11: 1215625.6 | L11: 2306877.4 | M11: 15 | N11: 25 | O11: No | P11: No Action | Q11: Low | R11: Green
A12: CON0010 | B12: 16-Mar-2025 | C12: Sector | D12: Cement | E12: 314702.87 | F12: 3200000 | G12: =ROUND(E12/F12*100,2) -> 9.83 | H12: 40 | I12: =ROUND(G12/H12*100,2) -> 24.58 | J12: 0.1863 | K12: 1443532.4 | L12: 2672230.7 | M12: 15 | N12: 25 | O12: No | P12: No Action | Q12: Low | R12: Green
A13: CON0011 | B13: 04-Feb-2024 | C13: Rating Band | D13: BB & Below | E13: 197262.14 | F13: 3200000 | G13: =ROUND(E13/F13*100,2) -> 6.16 | H13: 40 | I13: =ROUND(G13/H13*100,2) -> 15.4 | J13: 0.2062 | K13: 716130.74 | L13: 1258718.2 | M13: 15 | N13: 25 | O13: No | P13: No Action | Q13: Low | R13: Green
A14: CON0012 | B14: 11-Nov-2025 | C14: Maturity | D14: 5+ Years | E14: 143457.81 | F14: 3200000 | G14: =ROUND(E14/F14*100,2) -> 4.48 | H14: 40 | I14: =ROUND(G14/H14*100,2) -> 11.2 | J14: 0.3901 | K14: 762224.7 | L14: 1619971.2 | M14: 15 | N14: 25 | O14: No | P14: No Action | Q14: Low | R14: Green
... A202: CON0200 | B202: 24-Sep-2024 | C202: Maturity | D202: 1-3Y | E202: 290697.99 | F202: 3200000 | G202: =ROUND(E202/F202*100,2) -> 9.08 | H202: 40 | I202: =ROUND(G202/H202*100,2) -> 22.7 | J202: 0.0663 | K202: 1302622.6 | L202: 2739077.7 | M202: 15 | N202: 25 | O202: No | P202: No Action | Q202: Low | R202: Green

Sheet P2_Climate_Risk
A1: PILLAR 2 | Climate Risk – Physical & Transition Risk Portfolio | Bank Risk Management Dashboard
A2: Asset_ID | B2: Borrower | C2: Sector | D2: State | E2: Exposure_Cr | F2: Physical_Risk_Score | G2: Transition_Risk_Score | H2: Overall_Climate_Score | I2: Flood_Prob_% | J2: Drought_Prob_% | K2: Cyclone_Prob_% | L2: Heat_Stress_Score | M2: Carbon_Intensity_tCO2/Cr | N2: GHG_Scope1_tCO2 | O2: GHG_Scope2_tCO2 | P2: GHG_Scope3_tCO2 | Q2: TCFD_Category | R2: Net_Zero_Aligned | S2: ESG_Rating | T2: Green_Finance | U2: Climate_VaR_Cr | V2: Stranded_Asset_Risk | W2: Status | X2: RAG
A3: CLM00001 | B3: Entity_1 | C3: Cement | D3: Bihar | E3: 563.52 | F3: 7.3 | G3: 1.8 | H3: =ROUND((F3+G3)/2,1) -> 4.6 | I3: 16.8 | J3: 36 | K3: 29.2 | L3: 6.7 | M3: 186.1 | N3: 3136 | O3: 2087 | P3: 3697 | Q3: Liability | R3: No | S3: BBB | T3: Yes | U3: =ROUND(E3*H3/100*0.5,2) -> 12.96 | V3: Low | W3: Low | X3: Green
A4: CLM00002 | B4: Entity_2 | C4: Agri | D4: Maharashtra | E4: 557.03 | F4: 8 | G4: 7.2 | H4: =ROUND((F4+G4)/2,1) -> 7.6 | I4: 74 | J4: 55.6 | K4: 8.2 | L4: 2.5 | M4: 116.5 | N4: 702 | O4: 349 | P4: 432 | Q4: Physical-Acute | R4: Partial | S4: A | T4: No | U4: =ROUND(E4*H4/100*0.5,2) -> 21.17 | V4: Low | W4: High | X4: Red
A5: CLM00003 | B5: Entity_3 | C5: Shipping | D5: Bihar | E5: 631.29 | F5: 6.8 | G5: 1.5 | H5: =ROUND((F5+G5)/2,1) -> 4.2 | I5: 55.5 | J5: 72.8 | K5: 4.6 | L5: 2.3 | M5: 309 | N5: 3605 | O5: 671 | P5: 14020 | Q5: Transition-Technology | R5: Partial | S5: A- | T5: No | U5: =ROUND(E5*H5/100*0.5,2) -> 13.26 | V5: Medium | W5: Low | X5: Green
A6: CLM00004 | B6: Entity_4 | C6: Cement | D6: Gujarat | E6: 404.75 | F6: 2.3 | G6: 7 | H6: =ROUND((F6+G6)/2,1) -> 4.7 | I6: 48.2 | J6: 25.1 | K6: 35.4 | L6: 7.9 | M6: 217.8 | N6: 2867 | O6: 2253 | P6: 11185 | Q6: Physical-Acute | R6: No | S6: BB | T6: No | U6: =ROUND(E6*H6/100*0.5,2) -> 9.51 | V6: Low | W6: Low | X6: Green
A7: CLM00005 | B7: Entity_5 | C7: IT | D7: West Bengal | E7: 353.75 | F7: 1.4 | G7: 1.4 | H7: =ROUND((F7+G7)/2,1) -> 1.4 | I7: 58 | J7: 67 | K7: 26.4 | L7: 6.7 | M7: 31.5 | N7: 791 | O7: 314 | P7: 1226 | Q7: Transition-Technology | R7: Yes | S7: BB | T7: No | U7: =ROUND(E7*H7/100*0.5,2) -> 2.48 | V7: High | W7: Low | X7: Green
A8: CLM00006 | B8: Entity_6 | C8: Steel | D8: Karnataka | E8: 318.43 | F8: 8.2 | G8: 5.6 | H8: =ROUND((F8+G8)/2,1) -> 6.9 | I8: 84.3 | J8: 30.9 | K8: 6 | L8: 3.8 | M8: 226.6 | N8: 5225 | O8: 1737 | P8: 12953 | Q8: Physical-Acute | R8: Partial | S8: D | T8: Yes | U8: =ROUND(E8*H8/100*0.5,2) -> 10.99 | V8: High | W8: Medium | X8: Amber
A9: CLM00007 | B9: Entity_7 | C9: Shipping | D9: Maharashtra | E9: 314.38 | F9: 3.2 | G9: 6.4 | H9: =ROUND((F9+G9)/2,1) -> 4.8 | I9: 54.1 | J9: 37.2 | K9: 25 | L9: 10 | M9: 497.6 | N9: 5712 | O9: 2353 | P9: 4027 | Q9: Physical-Chronic | R9: Yes | S9: AAA | T9: No | U9: =ROUND(E9*H9/100*0.5,2) -> 7.55 | V9: Low | W9: Low | X9: Green
A10: CLM00008 | B10: Entity_8 | C10: FMCG | D10: Gujarat | E10: 612.41 | F10: 3.3 | G10: 5.8 | H10: =ROUND((F10+G10)/2,1) -> 4.6 | I10: 76.2 | J10: 69.1 | K10: 48.8 | L10: 3.4 | M10: 115.3 | N10: 927 | O10: 379 | P10: 826 | Q10: Transition-Technology | R10: No | S10: B+ | T10: Yes | U10: =ROUND(E10*H10/100*0.5,2) -> 14.09 | V10: High | W10: Low | X10: Green
A11: CLM00009 | B11: Entity_9 | C11: Oil & Gas | D11: West Bengal | E11: 516.82 | F11: 2.7 | G11: 6.8 | H11: =ROUND((F11+G11)/2,1) -> 4.8 | I11: 37 | J11: 22 | K11: 44.7 | L11: 2.3 | M11: 330 | N11: 2917 | O11: 899 | P11: 9547 | Q11: Transition-Technology | R11: Partial | S11: CCC | T11: No | U11: =ROUND(E11*H11/100*0.5,2) -> 12.4 | V11: Medium | W11: Low | X11: Green
A12: CLM00010 | B12: Entity_10 | C12: Chemicals | D12: Tamil Nadu | E12: 63.46 | F12: 8.9 | G12: 7.8 | H12: =ROUND((F12+G12)/2,1) -> 8.4 | I12: 15.4 | J12: 55.6 | K12: 55.4 | L12: 4.9 | M12: 196.8 | N12: 2563 | O12: 536 | P12: 8568 | Q12: Physical-Acute | R12: No | S12: A- | T12: No | U12: =ROUND(E12*H12/100*0.5,2) -> 2.67 | V12: Low | W12: High | X12: Red
A13: CLM00011 | B13: Entity_11 | C13: Power | D13: Bihar | E13: 292.88 | F13: 3.6 | G13: 8.9 | H13: =ROUND((F13+G13)/2,1) -> 6.3 | I13: 19.9 | J13: 60.2 | K13: 47.7 | L13: 4.3 | M13: 394.6 | N13: 2031 | O13: 1403 | P13: 4140 | Q13: Liability | R13: Yes | S13: CCC | T13: Yes | U13: =ROUND(E13*H13/100*0.5,2) -> 9.23 | V13: Medium | W13: Medium | X13: Amber
A14: CLM00012 | B14: Entity_12 | C14: Aviation | D14: UP | E14: 317.27 | F14: 3.5 | G14: 3.6 | H14: =ROUND((F14+G14)/2,1) -> 3.6 | I14: 51.1 | J14: 62 | K14: 34.3 | L14: 9.3 | M14: 497.4 | N14: 1392 | O14: 1708 | P14: 4955 | Q14: Transition-Technology | R14: Partial | S14: B | T14: Yes | U14: =ROUND(E14*H14/100*0.5,2) -> 5.71 | V14: Medium | W14: Low | X14: Green
... A202: CLM00200 | B202: Entity_200 | C202: Power | D202: Telangana | E202: 387.44 | F202: 9.9 | G202: 1.3 | H202: =ROUND((F202+G202)/2,1) -> 5.6 | I202: 78.7 | J202: 38.9 | K202: 45.3 | L202: 7.6 | M202: 179.6 | N202: 2026 | O202: 1509 | P202: 8587 | Q202: Liability | R202: Yes | S202: AA | T202: No | U202: =ROUND(E202*H202/100*0.5,2) -> 10.85 | V202: Low | W202: Medium | X202: Amber

Sheet P2_Cyber_Risk
A1: PILLAR 2 | Cyber Risk – Incident Register & KRIs | Bank Risk Management Dashboard
A2: Incident_ID | B2: Date | C2: Severity | D2: Attack_Vector | E2: Asset_Affected | F2: System_Type | G2: Downtime_Hrs | H2: Data_Records_Compromised | I2: Financial_Impact_Cr | J2: CVE_ID | K2: CVSS_Score | L2: Patch_Status | M2: CERT_In_Reported | N2: Response_Time_Hrs | O2: Recovery_Time_Hrs | P2: MTTD_Hrs | Q2: MTTR_Hrs | R2: RCA_Done | S2: Threat_Actor | T2: Business_Impact | U2: Controls_Tested | V2: Vulnerability_Count | W2: Status | X2: RAG
A3: CYB2024001 | B3: 10-Sep-2025 | C3: Medium | D3: Ransomware | E3: ATM Network | F3: Third-Party | G3: 16.3 | H3: 46531 | I3: 1.6434 | J3: CVE-2022-3694 | K3: 9.2 | L3: In Progress | M3: Yes | N3: 10.3 | O3: 63 | P3: 8.8 | Q3: 14 | R3: No | S3: Organized Crime | T3: High | U3: Passed | V3: 38 | W3: Active | X3: Red
A4: CYB2024002 | B4: 12-Aug-2025 | C4: High | D4: SQL Injection | E4: ATM Network | F4: Hybrid | G4: 8.1 | H4: 323631 | I4: 2.3688 | J4: CVE-2021-4493 | K4: 9.2 | L4: In Progress | M4: Yes | N4: 8 | O4: 69.9 | P4: 19.6 | Q4: 19.7 | R4: In Progress | S4: Organized Crime | T4: High | U4: Partial | V4: 38 | W4: Active | X4: Red
A5: CYB2024003 | B5: 02-Jan-2024 | C5: Medium | D5: SQL Injection | E5: ATM Network | F5: Hybrid | G5: 7.5 | H5: 224777 | I5: 0.7213 | J5: CVE-2019-9311 | K5: 4.2 | L5: Patched | M5: No | N5: 20.2 | O5: 90.9 | P5: 13.5 | Q5: 37.8 | R5: In Progress | S5: Organized Crime | T5: Medium | U5: Partial | V5: 31 | W5: Closed | X5: Red
A6: CYB2024004 | B6: 01-Jun-2025 | C6: High | D6: Insider Threat | E6: HR System | F6: Cloud | G6: 6.7 | H6: 82773 | I6: 2.8638 | J6: CVE-2022-2634 | K6: 4.2 | L6: In Progress | M6: Yes | N6: 35.5 | O6: 96.4 | P6: 12.1 | Q6: 63.9 | R6: In Progress | S6: Hacktivist | T6: High | U6: Failed | V6: 34 | W6: Active | X6: Red
A7: CYB2024005 | B7: 16-Feb-2025 | C7: Medium | D7: Zero-Day | E7: CRM | F7: Hybrid | G7: 4.8 | H7: 114608 | I7: 0.6826 | J7: CVE-2024-3502 | K7: 2.3 | L7: In Progress | M7: Yes | N7: 31.9 | O7: 75.9 | P7: 7.4 | Q7: 79.8 | R7: No | S7: Script Kiddie | T7: High | U7: Partial | V7: 36 | W7: Active | X7: Red
A8: CYB2024006 | B8: 11-Nov-2025 | C8: Critical | D8: Phishing Email | E8: Mobile Banking | F8: Hybrid | G8: 35.4 | H8: 431468 | I8: 3.6966 | J8: CVE-2023-6530 | K8: 2.9 | L8: Patched | M8: No | N8: 12.5 | O8: 89.9 | P8: 19.1 | Q8: 39.3 | R8: Yes | S8: Nation State | T8: High | U8: Passed | V8: 34 | W8: Closed | X8: Red
A9: CYB2024007 | B9: 05-Oct-2024 | C9: Medium | D9: SQL Injection | E9: Payment Gateway | F9: Cloud | G9: 25 | H9: 351749 | I9: 0.2145 | J9: CVE-2021-4753 | K9: 8.7 | L9: Pending | M9: Yes | N9: 32.8 | O9: 33.7 | P9: 0.8 | Q9: 53.5 | R9: Yes | S9: Hacktivist | T9: Low | U9: Failed | V9: 42 | W9: Closed | X9: Red
A10: CYB2024008 | B10: 04-Jun-2025 | C10: High | D10: Man-in-Middle | E10: ATM Network | F10: Third-Party | G10: 33.5 | H10: 165537 | I10: 2.4217 | J10: CVE-2024-5535 | K10: 8.1 | L10: Patched | M10: No | N10: 16.3 | O10: 57.7 | P10: 19.3 | Q10: 75.1 | R10: In Progress | S10: Nation State | T10: Medium | U10: Passed | V10: 27 | W10: Active | X10: Red
A11: CYB2024009 | B11: 14-Mar-2024 | C11: Low | D11: Zero-Day | E11: Email Server | F11: Third-Party | G11: 5.8 | H11: 352548 | I11: 0.5911 | J11: CVE-2019-7159 | K11: 6.3 | L11: In Progress | M11: No | N11: 22.8 | O11: 50.7 | P11: 19.4 | Q11: 6.7 | R11: Yes | S11: Organized Crime | T11: Low | U11: Failed | V11: 10 | W11: Active | X11: Red
A12: CYB2024010 | B12: 11-Jun-2024 | C12: High | D12: Ransomware | E12: CRM | F12: Cloud | G12: 8.5 | H12: 79470 | I12: 3.5789 | J12: CVE-2021-2200 | K12: 9.5 | L12: In Progress | M12: No | N12: 45.3 | O12: 62.8 | P12: 11.4 | Q12: 46.2 | R12: No | S12: Hacktivist | T12: Low | U12: Partial | V12: 33 | W12: Active | X12: Red
A13: CYB2024011 | B13: 08-Aug-2024 | C13: Low | D13: Man-in-Middle | E13: CRM | F13: Third-Party | G13: 5 | H13: 404959 | I13: 0.808 | J13: CVE-2020-3160 | K13: 4.9 | L13: Not Applicable | M13: Yes | N13: 23.3 | O13: 35.2 | P13: 14.1 | Q13: 43.4 | R13: In Progress | S13: Hacktivist | T13: High | U13: Partial | V13: 26 | W13: Active | X13: Red
A14: CYB2024012 | B14: 30-Aug-2024 | C14: High | D14: Insider Threat | E14: Payment Gateway | F14: On-Premise | G14: 7.5 | H14: 404682 | I14: 1.1851 | J14: CVE-2022-6387 | K14: 3.8 | L14: Patched | M14: No | N14: 9.5 | O14: 14.2 | P14: 1.6 | Q14: 11.4 | R14: Yes | S14: Insider | T14: Low | U14: Failed | V14: 31 | W14: Active | X14: Amber
... A202: CYB2024200 | B202: 07-Jul-2024 | C202: High | D202: Man-in-Middle | E202: Mobile Banking | F202: On-Premise | G202: 25.7 | H202: 115475 | I202: 2.7632 | J202: CVE-2020-2235 | K202: 4.7 | L202: Patched | M202: No | N202: 20.4 | O202: 31.3 | P202: 11.7 | Q202: 74.2 | R202: No | S202: Nation State | T202: Low | U202: Partial | V202: 23 | W202: Closed | X202: Red

Sheet P2_Fraud_Risk
A1: PILLAR 2 | Fraud Risk – Case Register & Detection KRIs | Bank Risk Management Dashboard
A2: Case_ID | B2: Date_Detected | C2: Channel | D2: Fraud_Type | E2: Amount_Cr | F2: Recovered_Cr | G2: Net_Loss_Cr | H2: Recovery_Rate_% | I2: Customer_ID | J2: Account_Type | K2: Detection_Method | L2: Alert_Source | M2: Reported_RBI | N2: FIR_Filed | O2: Perpetrator | P2: State | Q2: Resolution_Days | R2: SuspAcc_Frozen | S2: AML_Flag | T2: Investigation_Status | U2: Status | V2: RAG
A3: FRD2024001 | B3: 31-Aug-2024 | C3: NEFT/RTGS | D3: Card Skimming | E3: 3.4171 | F3: 1.134 | G3: =ROUND(E3-F3,2) -> 2.28 | H3: =ROUND(F3/E3*100,1) -> 33.2 | I3: CUST91776 | J3: FD | K3: Inter-Bank Alert | L3: CBS | M3: No | N3: Yes | O3: Unknown | P3: Maharashtra | Q3: 332 | R3: No | S3: Pending | T3: Under Investigation | U3: Pending | V3: Red
A4: FRD2024002 | B4: 24-Feb-2024 | C4: Mobile Banking | D4: Cheque Fraud | E4: 2.7755 | F4: 1.8259 | G4: =ROUND(E4-F4,2) -> 0.95 | H4: =ROUND(F4/E4*100,1) -> 65.8 | I4: CUST66928 | J4: OD | K4: SOC Alert | L4: External | M4: Yes | N4: No | O4: Foreign Entity | P4: West Bengal | Q4: 75 | R4: No | S4: Pending | T4: Closed | U4: Active | V4: Green
A5: FRD2024003 | B5: 12-Jun-2024 | C5: ATM | D5: Card Skimming | E5: 2.5266 | F5: 1.0469 | G5: =ROUND(E5-F5,2) -> 1.48 | H5: =ROUND(F5/E5*100,1) -> 41.4 | I5: CUST76631 | J5: Loan | K5: SOC Alert | L5: Manual | M5: No | N5: No | O5: Unknown | P5: UP | Q5: 149 | R5: No | S5: No | T5: Under Investigation | U5: Pending | V5: Red
A6: FRD2024004 | B6: 12-May-2025 | C6: Cheque | D6: Identity Theft | E6: 1.1344 | F6: 1.0014 | G6: =ROUND(E6-F6,2) -> 0.13 | H6: =ROUND(F6/E6*100,1) -> 88.3 | I6: CUST86949 | J6: Loan | K6: RBI Report | L6: External | M6: No | N6: Yes | O6: Insider | P6: Kerala | Q6: 366 | R6: No | S6: Yes | T6: Pending | U6: Pending | V6: Green
A7: FRD2024005 | B7: 27-Sep-2025 | C7: UPI | D7: Loan Fraud | E7: 0.2406 | F7: 0.0731 | G7: =ROUND(E7-F7,2) -> 0.17 | H7: =ROUND(F7/E7*100,1) -> 30.4 | I7: CUST96748 | J7: CA | K7: Customer Complaint | L7: Manual | M7: No | N7: No | O7: Organized Group | P7: Karnataka | Q7: 72 | R7: Yes | S7: Pending | T7: Under Investigation | U7: Active | V7: Red
A8: FRD2024006 | B8: 13-Apr-2024 | C8: Mobile Banking | D8: Phishing | E8: 1.6538 | F8: 0.8984 | G8: =ROUND(E8-F8,2) -> 0.76 | H8: =ROUND(F8/E8*100,1) -> 54.3 | I8: CUST79948 | J8: Loan | K8: Rule-Based Alert | L8: FMS | M8: No | N8: No | O8: Syndicate | P8: Rajasthan | Q8: 121 | R8: No | S8: Yes | T8: Closed | U8: Pending | V8: Amber
A9: FRD2024007 | B9: 15-Mar-2024 | C9: Mobile Banking | D9: Cheque Fraud | E9: 4.4257 | F9: 3.0055 | G9: =ROUND(E9-F9,2) -> 1.42 | H9: =ROUND(F9/E9*100,1) -> 67.9 | I9: CUST31410 | J9: CA | K9: Branch Report | L9: External | M9: No | N9: No | O9: Insider | P9: Karnataka | Q9: 331 | R9: Yes | S9: No | T9: Referred to CBI | U9: Pending | V9: Green
A10: FRD2024008 | B10: 17-Apr-2025 | C10: Phone Banking | D10: Cheque Fraud | E10: 0.7357 | F10: 0.3767 | G10: =ROUND(E10-F10,2) -> 0.36 | H10: =ROUND(F10/E10*100,1) -> 51.2 | I10: CUST75691 | J10: FD | K10: Customer Complaint | L10: CBS | M10: Yes | N10: No | O10: Syndicate | P10: Odisha | Q10: 284 | R10: No | S10: Yes | T10: Under Investigation | U10: Pending | V10: Amber
A11: FRD2024009 | B11: 13-Jul-2025 | C11: Branch | D11: Phishing | E11: 3.9405 | F11: 0.3725 | G11: =ROUND(E11-F11,2) -> 3.57 | H11: =ROUND(F11/E11*100,1) -> 9.5 | I11: CUST20097 | J11: Loan | K11: Branch Report | L11: SOC | M11: No | N11: No | O11: Insider | P11: Punjab | Q11: 387 | R11: No | S11: No | T11: Closed | U11: Pending | V11: Red
A12: FRD2024010 | B12: 28-Nov-2024 | C12: Phone Banking | D12: Money Laundering | E12: 6.8983 | F12: 4.2161 | G12: =ROUND(E12-F12,2) -> 2.68 | H12: =ROUND(F12/E12*100,1) -> 61.1 | I12: CUST84366 | J12: OD | K12: Branch Report | L12: External | M12: Yes | N12: Yes | O12: Syndicate | P12: Punjab | Q12: 83 | R12: Yes | S12: No | T12: Closed | U12: Closed | V12: Amber
A13: FRD2024011 | B13: 10-Jul-2025 | C13: ATM | D13: Cyber Fraud | E13: 8.8126 | F13: 3.7494 | G13: =ROUND(E13-F13,2) -> 5.06 | H13: =ROUND(F13/E13*100,1) -> 42.5 | I13: CUST60356 | J13: OD | K13: Customer Complaint | L13: FMS | M13: Yes | N13: No | O13: Insider | P13: Rajasthan | Q13: 168 | R13: No | S13: Pending | T13: Pending | U13: Active | V13: Red
A14: FRD2024012 | B14: 11-Oct-2024 | C14: UPI | D14: Cheque Fraud | E14: 6.6885 | F14: 3.4811 | G14: =ROUND(E14-F14,2) -> 3.21 | H14: =ROUND(F14/E14*100,1) -> 52 | I14: CUST62244 | J14: CC | K14: SOC Alert | L14: SOC | M14: No | N14: No | O14: External Individual | P14: Karnataka | Q14: 135 | R14: No | S14: No | T14: Under Investigation | U14: Closed | V14: Amber
... A202: FRD2024200 | B202: 18-Jul-2025 | C202: Phone Banking | D202: Identity Theft | E202: 0.1296 | F202: 0.0389 | G202: =ROUND(E202-F202,2) -> 0.09 | H202: =ROUND(F202/E202*100,1) -> 30 | I202: CUST38821 | J202: OD | K202: Branch Report | L202: Manual | M202: Yes | N202: Yes | O202: Insider | P202: Kerala | Q202: 97 | R202: Yes | S202: Pending | T202: Pending | U202: Closed | V202: Red

Sheet P2_Third_Party_Risk
A1: PILLAR 2 | Third Party Risk – Vendor Risk Register | Bank Risk Management Dashboard
A2: Vendor_ID | B2: Vendor_Name | C2: Service_Category | D2: Criticality | E2: Contract_Value_Cr | F2: Contract_Start | G2: Contract_End | H2: SLA_Uptime_% | I2: Actual_Uptime_% | J2: SLA_Breach | K2: Vendor_Risk_Score | L2: Data_Access_Level | M2: TPRA_Score | N2: VAPT_Done | O2: IS_Audit_Done | P2: BCP_Tested | Q2: RBI_Regulated | R2: Sub_Vendors | S2: Incident_Count | T2: Action_Required | U2: Status | V2: RAG
A3: VND0001 | B3: Vendor_001 | C3: Regulatory Reporting | D3: High | E3: 292.12 | F3: 11-Jul-2018 | G3: 09-Jan-2023 | H3: 98.56 | I3: 98.41 | J3: =IF(I3<H3,"Yes","No") -> Yes | K3: 2.1 | L3: PII Access | M3: 73.1 | N3: No | O3: Yes | P3: Yes | Q3: N/A | R3: 14 | S3: 5 | T3: Scheduled Review | U3: High | V3: Red
A4: VND0002 | B4: Vendor_002 | C4: Cybersecurity | D4: High | E4: 172.06 | F4: 07-Sep-2018 | G4: 28-Nov-2020 | H4: 98.17 | I4: 97.77 | J4: =IF(I4<H4,"Yes","No") -> Yes | K4: 3.8 | L4: PII Access | M4: 65.4 | N4: Scheduled | O4: Scheduled | P4: In Progress | Q4: N/A | R4: 8 | S4: 18 | T4: Immediate Review | U4: High | V4: Red
A5: VND0003 | B5: Vendor_003 | C5: Recovery/BCP | D5: Medium | E5: 351.07 | F5: 20-Oct-2021 | G5: 08-Jun-2024 | H5: 98.63 | I5: 95.38 | J5: =IF(I5<H5,"Yes","No") -> Yes | K5: 1.5 | L5: PII Access | M5: 20.6 | N5: Overdue | O5: Overdue | P5: Partial | Q5: No | R5: 11 | S5: 16 | T5: No Action | U5: Medium | V5: Amber
A6: VND0004 | B6: Vendor_004 | C6: Payment Processing | D6: Critical | E6: 596.97 | F6: 03-Jul-2018 | G6: 09-Jan-2026 | H6: 98.42 | I6: 95.62 | J6: =IF(I6<H6,"Yes","No") -> Yes | K6: 4.4 | L6: None | M6: 36.6 | N6: No | O6: Yes | P6: In Progress | Q6: Yes | R6: 3 | S6: 5 | T6: Immediate Review | U6: High | V6: Red
A7: VND0005 | B7: Vendor_005 | C7: ATM Maintenance | D7: Low | E7: 588.74 | F7: 15-Jun-2020 | G7: 13-Jun-2024 | H7: 99.48 | I7: 96.84 | J7: =IF(I7<H7,"Yes","No") -> Yes | K7: 1.4 | L7: Confidential | M7: 35.9 | N7: Scheduled | O7: No | P7: In Progress | Q7: N/A | R7: 2 | S7: 2 | T7: No Action | U7: Medium | V7: Amber
A8: VND0006 | B8: Vendor_006 | C8: ATM Maintenance | D8: High | E8: 317.71 | F8: 19-Dec-2023 | G8: 25-Jul-2026 | H8: 98.78 | I8: 95.36 | J8: =IF(I8<H8,"Yes","No") -> Yes | K8: 1.7 | L8: Admin | M8: 19.7 | N8: No | O8: Yes | P8: In Progress | Q8: Yes | R8: 13 | S8: 15 | T8: Scheduled Review | U8: High | V8: Red
A9: VND0007 | B9: Vendor_007 | C9: HR Systems | D9: High | E9: 478.23 | F9: 04-Mar-2023 | G9: 13-Jul-2029 | H9: 98.44 | I9: 95 | J9: =IF(I9<H9,"Yes","No") -> Yes | K9: 1.8 | L9: Admin | M9: 78.2 | N9: No | O9: Yes | P9: In Progress | Q9: N/A | R9: 10 | S9: 8 | T9: Scheduled Review | U9: High | V9: Red
A10: VND0008 | B10: Vendor_008 | C10: ATM Maintenance | D10: Critical | E10: 453.82 | F10: 23-May-2018 | G10: 07-Jan-2021 | H10: 98.48 | I10: 96.13 | J10: =IF(I10<H10,"Yes","No") -> Yes | K10: 3.4 | L10: None | M10: 35.1 | N10: Overdue | O10: No | P10: Partial | Q10: N/A | R10: 13 | S10: 7 | T10: Immediate Review | U10: High | V10: Red
A11: VND0009 | B11: Vendor_009 | C11: Regulatory Reporting | D11: Critical | E11: 96.12 | F11: 24-May-2024 | G11: 01-Nov-2028 | H11: 99.2 | I11: 98.66 | J11: =IF(I11<H11,"Yes","No") -> Yes | K11: 4.6 | L11: Read-Only | M11: 19 | N11: Overdue | O11: Yes | P11: No | Q11: No | R11: 2 | S11: 20 | T11: Immediate Review | U11: High | V11: Red
A12: VND0010 | B12: Vendor_010 | C12: Cloud Infrastructure | D12: Low | E12: 521.25 | F12: 27-Feb-2019 | G12: 14-Mar-2023 | H12: 99.41 | I12: 97.99 | J12: =IF(I12<H12,"Yes","No") -> Yes | K12: 1.1 | L12: None | M12: 56.1 | N12: No | O12: Scheduled | P12: Partial | Q12: No | R12: 3 | S12: 6 | T12: No Action | U12: Medium | V12: Amber
A13: VND0011 | B13: Vendor_011 | C13: Printing & Stationery | D13: Medium | E13: 194.41 | F13: 13-Jun-2018 | G13: 20-Nov-2022 | H13: 99.54 | I13: 97.43 | J13: =IF(I13<H13,"Yes","No") -> Yes | K13: 1 | L13: PII Access | M13: 60.8 | N13: Overdue | O13: Yes | P13: In Progress | Q13: N/A | R13: 9 | S13: 11 | T13: No Action | U13: Medium | V13: Amber
A14: VND0012 | B14: Vendor_012 | C14: ATM Maintenance | D14: Low | E14: 85.69 | F14: 02-Dec-2020 | G14: 21-Nov-2024 | H14: 99.4 | I14: 97.79 | J14: =IF(I14<H14,"Yes","No") -> Yes | K14: 3.5 | L14: Read-Write | M14: 37.9 | N14: Yes | O14: Overdue | P14: In Progress | Q14: N/A | R14: 2 | S14: 2 | T14: Immediate Review | U14: Medium | V14: Amber
... A52: VND0050 | B52: Vendor_050 | C52: Cybersecurity | D52: Critical | E52: 415.04 | F52: 15-Oct-2020 | G52: 02-Jul-2025 | H52: 99.95 | I52: 96.99 | J52: =IF(I52<H52,"Yes","No") -> Yes | K52: 4.4 | L52: None | M52: 88.5 | N52: No | O52: Yes | P52: Partial | Q52: Yes | R52: 15 | S52: 6 | T52: Immediate Review | U52: High | V52: Red
A53: VND0051 | B53: Vendor_051 | C53: ATM Managed Services | D53: High | E53: 89.48 | F53: 12-Feb-2023 | G53: 28-Feb-2026 | H53: 99.76 | I53: 98.76 | J53: Yes | K53: 4.6 | L53: Confidential | M53: 79.2 | N53: Yes | O53: Yes | P53: No | Q53: No | R53: 1 | S53: 10 | T53: Immediate Review | U53: High | V53: Red
A54: VND0052 | B54: Vendor_052 | C54: Payment Processing | D54: Low | E54: 89.34 | F54: 20-Jul-2022 | G54: 03-Aug-2025 | H54: 98.49 | I54: 97.39 | J54: Yes | K54: 4.9 | L54: None | M54: 1.1 | N54: Yes | O54: Yes | P54: Yes | Q54: N/A | R54: 8 | S54: 5 | T54: Immediate Review | U54: High | V54: Red
A55: VND0053 | B55: Vendor_053 | C55: ATM Managed Services | D55: High | E55: 358.73 | F55: 08-Nov-2020 | G55: 23-Jul-2025 | H55: 99.34 | I55: 97.64 | J55: Yes | K55: 3.9 | L55: Read-Only | M55: 35.6 | N55: Yes | O55: No | P55: Partial | Q55: N/A | R55: 1 | S55: 15 | T55: Immediate Review | U55: Medium | V55: Amber
A56: VND0054 | B56: Vendor_054 | C56: Cybersecurity | D56: Critical | E56: 203.62 | F56: 14-Sep-2022 | G56: 07-Oct-2027 | H56: 98.77 | I56: 97.47 | J56: Yes | K56: 2.7 | L56: Confidential | M56: 72.6 | N56: Overdue | O56: Yes | P56: Yes | Q56: N/A | R56: 8 | S56: 3 | T56: Immediate Review | U56: Low | V56: Green
A57: VND0055 | B57: Vendor_055 | C57: HR Systems | D57: High | E57: 385.39 | F57: 26-Jun-2023 | G57: 18-Sep-2025 | H57: 98.93 | I57: 98.04 | J57: Yes | K57: 2.6 | L57: Admin | M57: 91.9 | N57: Overdue | O57: Yes | P57: No | Q57: N/A | R57: 6 | S57: 7 | T57: Immediate Review | U57: Low | V57: Green
A58: VND0056 | B58: Vendor_056 | C58: Recovery/BCP | D58: Medium | E58: 175.62 | F58: 15-Oct-2022 | G58: 31-Dec-2025 | H58: 99.46 | I58: 99.43 | J58: No | K58: 3.9 | L58: Confidential | M58: 15.9 | N58: No | O58: No | P58: No | Q58: N/A | R58: 6 | S58: 12 | T58: Scheduled Review | U58: Medium | V58: Amber
A59: VND0057 | B59: Vendor_057 | C59: Cloud Services | D59: Medium | E59: 287.8 | F59: 11-Jul-2020 | G59: 11-Oct-2025 | H59: 98.64 | I59: 98.23 | J59: No | K59: 3.5 | L59: PII Access | M59: 57 | N59: Yes | O59: No | P59: No | Q59: Yes | R59: 9 | S59: 8 | T59: Scheduled Review | U59: Medium | V59: Amber
A60: VND0058 | B60: Vendor_058 | C60: Data Analytics | D60: Critical | E60: 382.23 | F60: 02-Sep-2021 | G60: 07-Oct-2025 | H60: 99.15 | I60: 97.93 | J60: Yes | K60: 2.8 | L60: Confidential | M60: 48 | N60: Overdue | O60: No | P60: No | Q60: N/A | R60: 4 | S60: 2 | T60: Immediate Review | U60: Low | V60: Green
A61: VND0059 | B61: Vendor_059 | C61: Network | D61: Low | E61: 242.73 | F61: 25-Feb-2023 | G61: 08-Jan-2025 | H61: 99.1 | I61: 97.91 | J61: Yes | K61: 2.2 | L61: Confidential | M61: 50.3 | N61: Overdue | O61: No | P61: Partial | Q61: N/A | R61: 9 | S61: 9 | T61: Immediate Review | U61: Low | V61: Green
A62: VND0060 | B62: Vendor_060 | C62: Data Analytics | D62: Medium | E62: 38.56 | F62: 08-Nov-2022 | G62: 01-Feb-2026 | H62: 99.6 | I62: 98 | J62: Yes | K62: 4.4 | L62: None | M62: 41.7 | N62: Yes | O62: No | P62: No | Q62: N/A | R62: 10 | S62: 10 | T62: Immediate Review | U62: High | V62: Red
A63: VND0061 | B63: Vendor_061 | C63: ATM Managed Services | D63: Low | E63: 366.8 | F63: 03-Jan-2023 | G63: 29-Dec-2027 | H63: 98.21 | I63: 97.45 | J63: Yes | K63: 4.1 | L63: PII Access | M63: 3.8 | N63: No | O63: No | P63: Yes | Q63: N/A | R63: 2 | S63: 12 | T63: Immediate Review | U63: High | V63: Red
A64: VND0062 | B64: Vendor_062 | C64: Core Banking | D64: Medium | E64: 482.46 | F64: 30-Aug-2020 | G64: 06-Mar-2025 | H64: 98.33 | I64: 98.05 | J64: No | K64: 2.8 | L64: Admin | M64: 40.6 | N64: Overdue | O64: Scheduled | P64: Yes | Q64: Yes | R64: 8 | S64: 5 | T64: No Action | U64: Low | V64: Green
... A102: VND0100 | B102: Vendor_100 | C102: Printing & Stationery | D102: Low | E102: 287.99 | F102: 01-Apr-2020 | G102: 07-May-2027 | H102: 98.99 | I102: 98.47 | J102: Yes | K102: 4 | L102: Confidential | M102: 86.2 | N102: Overdue | O102: Scheduled | P102: Yes | Q102: N/A | R102: 2 | S102: 5 | T102: Immediate Review | U102: Medium | V102: Amber

Sheet P2_Reputational_Risk
A1: PILLAR 2 | Reputational Risk – Sentiment & Complaint Tracker | Bank Risk Management Dashboard
A2: Record_ID | B2: Date | C2: Category | D2: Sub_Category | E2: Sentiment_Score | F2: Media_Coverage_Count | G2: Social_Media_Mentions | H2: Negative_Mentions_% | I2: Customer_Complaints | J2: Complaints_Resolved_% | K2: Resolution_TAT_Days | L2: NPS_Score | M2: Brand_Trust_Index | N2: RBI_Observations | O2: Penalty_Amt_Cr | P2: Parliamentary_Questions | Q2: Litigation_Count | R2: Litigation_Amt_Cr | S2: Reputation_Index | T2: Status | U2: RAG
A3: REP0001 | B3: 29-Oct-2024 | C3: Technology Failure | D3: Digital Media | E3: 35.7 | F3: 107 | G3: 6275 | H3: 15.2 | I3: 886 | J3: 76.3 | K3: 22.8 | L3: 28.6 | M3: 85.9 | N3: 1 | O3: 3.85 | P3: 0 | Q3: 6 | R3: 5.89 | S3: =ROUND(0.3*E3+0.3*J3+0.2*(100-H3)+0.2*MIN(L3*1.2,100),1) -> 57.4 | T3: Medium | U3: Amber
A4: REP0002 | B4: 10-Nov-2024 | C4: Employee Relations | D4: Print Media | E4: 46.5 | F4: 141 | G4: 6263 | H4: 44.6 | I4: 1017 | J4: 95.4 | K4: 22 | L4: 62.7 | M4: 59.4 | N4: 8 | O4: 3.64 | P4: 12 | Q4: 10 | R4: 31.98 | S4: =ROUND(0.3*E4+0.3*J4+0.2*(100-H4)+0.2*MIN(L4*1.2,100),1) -> 68.7 | T4: Low | U4: Green
A5: REP0003 | B5: 20-Feb-2025 | C5: Media Relations | D5: Facebook | E5: 67.5 | F5: 83 | G5: 21834 | H5: 64.3 | I5: 2686 | J5: 69.1 | K5: 20 | L5: 68.3 | M5: 70.9 | N5: 1 | O5: 1.7 | P5: 9 | Q5: 19 | R5: 26.69 | S5: =ROUND(0.3*E5+0.3*J5+0.2*(100-H5)+0.2*MIN(L5*1.2,100),1) -> 64.5 | T5: Medium | U5: Amber
A6: REP0004 | B6: 05-Jun-2024 | C6: Customer Service | D6: Employee Grievance | E6: 36.5 | F6: 26 | G6: 41009 | H6: 59.9 | I6: 1043 | J6: 65.8 | K6: 34 | L6: 64.7 | M6: 79.9 | N6: 6 | O6: 8.28 | P6: 1 | Q6: 0 | R6: 5.89 | S6: =ROUND(0.3*E6+0.3*J6+0.2*(100-H6)+0.2*MIN(L6*1.2,100),1) -> 54.2 | T6: Medium | U6: Amber
A7: REP0005 | B7: 23-Jun-2025 | C7: Regulatory | D7: Instagram | E7: 61.5 | F7: 39 | G7: 49000 | H7: 10.7 | I7: 4587 | J7: 69.8 | K7: 29 | L7: 65.1 | M7: 44.1 | N7: 1 | O7: 7.59 | P7: 7 | Q7: 11 | R7: 92.79 | S7: =ROUND(0.3*E7+0.3*J7+0.2*(100-H7)+0.2*MIN(L7*1.2,100),1) -> 72.9 | T7: Low | U7: Green
A8: REP0006 | B8: 15-Feb-2025 | C8: Regulatory | D8: Employee Grievance | E8: 73.5 | F8: 150 | G8: 25499 | H8: 62.2 | I8: 449 | J8: 83 | K8: 22.5 | L8: 37.3 | M8: 83 | N8: 1 | O8: 8.95 | P8: 0 | Q8: 11 | R8: 56.87 | S8: =ROUND(0.3*E8+0.3*J8+0.2*(100-H8)+0.2*MIN(L8*1.2,100),1) -> 63.5 | T8: Medium | U8: Amber
A9: REP0007 | B9: 22-May-2024 | C9: Social Media | D9: Parliamentary | E9: 24.1 | F9: 38 | G9: 36627 | H9: 41.9 | I9: 602 | J9: 88.9 | K9: 6.4 | L9: 7 | M9: 92.6 | N9: 7 | O9: 10.95 | P9: 4 | Q9: 17 | R9: 33.96 | S9: =ROUND(0.3*E9+0.3*J9+0.2*(100-H9)+0.2*MIN(L9*1.2,100),1) -> 47.2 | T9: High | U9: Red
A10: REP0008 | B10: 20-May-2025 | C10: Regulatory | D10: Twitter | E10: 71.4 | F10: 147 | G10: 30848 | H10: 61.2 | I10: 1385 | J10: 85.7 | K10: 4 | L10: 26.8 | M10: 89.1 | N10: 0 | O10: 3.97 | P10: 8 | Q10: 20 | R10: 2.31 | S10: =ROUND(0.3*E10+0.3*J10+0.2*(100-H10)+0.2*MIN(L10*1.2,100),1) -> 61.3 | T10: Medium | U10: Amber
A11: REP0009 | B11: 30-May-2024 | C11: Political | D11: Employee Grievance | E11: 16.1 | F11: 102 | G11: 3378 | H11: 20.9 | I11: 434 | J11: 70.9 | K11: 32.8 | L11: 16.8 | M11: 35.8 | N11: 5 | O11: 10.17 | P11: 7 | Q11: 8 | R11: 45.12 | S11: =ROUND(0.3*E11+0.3*J11+0.2*(100-H11)+0.2*MIN(L11*1.2,100),1) -> 46 | T11: High | U11: Red
A12: REP0010 | B12: 12-Feb-2025 | C12: Product Quality | D12: Court Case | E12: 17.9 | F12: 153 | G12: 2026 | H12: 18.9 | I12: 883 | J12: 86.6 | K12: 34 | L12: 43 | M12: 54.8 | N12: 6 | O12: 11.56 | P12: 4 | Q12: 6 | R12: 3.53 | S12: =ROUND(0.3*E12+0.3*J12+0.2*(100-H12)+0.2*MIN(L12*1.2,100),1) -> 57.9 | T12: Medium | U12: Amber
A13: REP0011 | B13: 02-Feb-2025 | C13: Social Media | D13: Court Case | E13: 45.2 | F13: 39 | G13: 14954 | H13: 34.9 | I13: 4231 | J13: 83 | K13: 32.5 | L13: 33.8 | M13: 87.8 | N13: 5 | O13: 5.11 | P13: 9 | Q13: 19 | R13: 82.96 | S13: =ROUND(0.3*E13+0.3*J13+0.2*(100-H13)+0.2*MIN(L13*1.2,100),1) -> 59.6 | T13: Medium | U13: Amber
A14: REP0012 | B14: 16-Mar-2024 | C14: Legal | D14: Employee Grievance | E14: 61.1 | F14: 18 | G14: 27808 | H14: 43.1 | I14: 1330 | J14: 93.7 | K14: 1.8 | L14: 10.7 | M14: 40.9 | N14: 3 | O14: 6.67 | P14: 0 | Q14: 8 | R14: 48.2 | S14: =ROUND(0.3*E14+0.3*J14+0.2*(100-H14)+0.2*MIN(L14*1.2,100),1) -> 60.4 | T14: Medium | U14: Amber
... A102: REP0100 | B102: 30-Nov-2024 | C102: Technology Failure | D102: Print Media | E102: 49.1 | F102: 27 | G102: 24462 | H102: 61.7 | I102: 2856 | J102: 83.2 | K102: 18 | L102: 57.3 | M102: 92.4 | N102: 4 | O102: 7.61 | P102: 11 | Q102: 1 | R102: 27.34 | S102: =ROUND(0.3*E102+0.3*J102+0.2*(100-H102)+0.2*MIN(L102*1.2,100),1) -> 61.1 | T102: Medium | U102: Amber
A103: REP0101 | B103: 31-Mar-2025 | C103: Social Media | D103: Investor Relations | E103: 58.5 | F103: 6 | G103: 5771 | H103: 51 | I103: 4060 | J103: 88 | K103: 17.4 | L103: 20.3 | M103: 74.9 | N103: 0 | O103: 0 | P103: 2 | Q103: 9 | R103: 56.04 | S103: 64.5 | T103: Medium | U103: Amber
A104: REP0102 | B104: 12-Jan-2024 | C104: Legal | D104: Instagram | E104: 74 | F104: 20 | G104: 32619 | H104: 14.3 | I104: 2210 | J104: 80 | K104: 23.6 | L104: 57.8 | M104: 65 | N104: 3 | O104: 5.73 | P104: 7 | Q104: 18 | R104: 76.09 | S104: 79.3 | T104: Low | U104: Green
A105: REP0103 | B105: 24-Dec-2025 | C105: Customer Service | D105: RBI Circular | E105: 81.2 | F105: 198 | G105: 35231 | H105: 25.3 | I105: 1856 | J105: 81 | K105: 23.1 | L105: 35.1 | M105: 68.4 | N105: 2 | O105: 6.88 | P105: 2 | Q105: 6 | R105: 51.57 | S105: 79.2 | T105: Low | U105: Green
A106: REP0104 | B106: 27-Aug-2025 | C106: Legal | D106: Digital Media | E106: 65.7 | F106: 1 | G106: 39134 | H106: 23.6 | I106: 4113 | J106: 95.4 | K106: 19.1 | L106: 28.8 | M106: 77.1 | N106: 2 | O106: 1.74 | P106: 6 | Q106: 8 | R106: 23.45 | S106: 77.8 | T106: Low | U106: Green
A107: REP0105 | B107: 01-Jun-2025 | C107: Employee Relations | D107: Print Media | E107: 78.5 | F107: 9 | G107: 38212 | H107: 48 | I107: 3917 | J107: 85.5 | K107: 8.6 | L107: 35.6 | M107: 55.2 | N107: 5 | O107: 6.35 | P107: 1 | Q107: 9 | R107: 22.21 | S107: 72.7 | T107: Low | U107: Green
A108: REP0106 | B108: 14-May-2024 | C108: Technology Failure | D108: Instagram | E108: 39.3 | F108: 118 | G108: 3457 | H108: 26.8 | I108: 3083 | J108: 72.4 | K108: 22.8 | L108: 60.6 | M108: 88.2 | N108: 2 | O108: 8.78 | P108: 4 | Q108: 13 | R108: 84.91 | S108: 59.4 | T108: Medium | U108: Amber
A109: REP0107 | B109: 13-Dec-2025 | C109: ESG/Sustainability | D109: Facebook | E109: 48.3 | F109: 18 | G109: 24200 | H109: 41.3 | I109: 723 | J109: 85.1 | K109: 24.7 | L109: 54.8 | M109: 68.6 | N109: 0 | O109: 0 | P109: 2 | Q109: 14 | R109: 47.54 | S109: 62.5 | T109: Medium | U109: Amber
A110: REP0108 | B110: 14-Mar-2025 | C110: Customer Service | D110: Employee Grievance | E110: 79 | F110: 3 | G110: 33983 | H110: 21.9 | I110: 345 | J110: 90.2 | K110: 19.8 | L110: 60.3 | M110: 59.3 | N110: 2 | O110: 9.76 | P110: 5 | Q110: 13 | R110: 75.29 | S110: 82.1 | T110: Low | U110: Green
A111: REP0109 | B111: 18-Feb-2025 | C111: Media Relations | D111: RBI Circular | E111: 83 | F111: 59 | G111: 46361 | H111: 18.6 | I111: 2197 | J111: 96.5 | K111: 18.2 | L111: 24.7 | M111: 41.4 | N111: 3 | O111: 6.45 | P111: 10 | Q111: 6 | R111: 2.23 | S111: 86.6 | T111: Low | U111: Green
A112: REP0110 | B112: 07-Apr-2025 | C112: Product Quality | D112: Digital Media | E112: 58.4 | F112: 35 | G112: 12095 | H112: 45.4 | I112: 3455 | J112: 81.9 | K112: 25.9 | L112: 64.7 | M112: 72.1 | N112: 0 | O112: 0 | P112: 9 | Q112: 0 | R112: 77.11 | S112: 64.3 | T112: Medium | U112: Amber
A113: REP0111 | B113: 11-Dec-2025 | C113: Technology Failure | D113: Investor Relations | E113: 50.2 | F113: 56 | G113: 33024 | H113: 46.8 | I113: 4907 | J113: 93.4 | K113: 2.4 | L113: 38.2 | M113: 50.3 | N113: 3 | O113: 2.04 | P113: 10 | Q113: 5 | R113: 69.64 | S113: 64.1 | T113: Medium | U113: Amber
A114: REP0112 | B114: 12-Dec-2025 | C114: Employee Relations | D114: Investor Relations | E114: 72.9 | F114: 103 | G114: 1677 | H114: 45.8 | I114: 2589 | J114: 93.2 | K114: 19.5 | L114: 60.9 | M114: 82.2 | N114: 5 | O114: 3.03 | P114: 2 | Q114: 4 | R114: 82.84 | S114: 73.4 | T114: Low | U114: Green
... A122: REP0120 | B122: 06-Jul-2025 | C122: Regulatory | D122: Parliamentary | E122: 74.2 | F122: 30 | G122: 31292 | H122: 8 | I122: 4917 | J122: 98.3 | K122: 13 | L122: 27.9 | M122: 62.3 | N122: 0 | O122: 0 | P122: 3 | Q122: 0 | R122: 51.32 | S122: 86.8 | T122: Low | U122: Green

Sheet P2_Strategic_Risk
A1: PILLAR 2 | Strategic Risk – BSC & KPI Dashboard | Bank Risk Management Dashboard
A2: Record_ID | B2: Quarter | C2: Strategic_Objective | D2: KPI_Name | E2: Target_Value | F2: Actual_Value | G2: Variance_% | H2: Weight_% | I2: Weighted_Score | J2: Market_Share_% | K2: Competitor_Benchmark | L2: ROCE_% | M2: ROA_% | N2: ROE_% | O2: Cost_Income_Ratio_% | P2: Net_Interest_Margin_% | Q2: Credit_Growth_% | R2: Deposit_Growth_% | S2: Digital_Txn_% | T2: BSC_Perspective | U2: Status | V2: RAG
A3: STR0001 | B3: Q3-FY26 | C3: Grow Retail Franchise | D3: MSME Share | E3: 17.81 | F3: 20.18 | G3: =ROUND((F3-E3)/ABS(E3)*100,1) -> 13.3 | H3: 17.9 | I3: =ROUND(H3*F3/100,2) -> 3.61 | J3: 19.54 | K3: 18.56 | L3: 13.29 | M3: 1.1 | N3: 14.15 | O3: 48.48 | P3: 3.81 | Q3: 9.44 | R3: 8.89 | S3: 78.43 | T3: Financial | U3: Normal | V3: Green
A4: STR0002 | B4: Q2-FY24 | C4: Grow Retail Franchise | D4: Fee Income Ratio | E4: 7.95 | F4: 7.58 | G4: =ROUND((F4-E4)/ABS(E4)*100,1) -> -4.7 | H4: 13.7 | I4: =ROUND(H4*F4/100,2) -> 1.04 | J4: 18.39 | K4: 19.04 | L4: 14.42 | M4: 0.97 | N4: 12.76 | O4: 46.51 | P4: 3.31 | Q4: 11.34 | R4: 12.7 | S4: 63.93 | T4: Learning & Growth | U4: Normal | V4: Green
A5: STR0003 | B5: Q1-FY25 | C5: Digital Transformation | D5: Fee Income Ratio | E5: 13.12 | F5: 10.05 | G5: =ROUND((F5-E5)/ABS(E5)*100,1) -> -23.4 | H5: 13.4 | I5: =ROUND(H5*F5/100,2) -> 1.35 | J5: 20.3 | K5: 23.71 | L5: 10.4 | M5: 0.62 | N5: 10.57 | O5: 60.15 | P5: 2.76 | Q5: 18.84 | R5: 7.53 | S5: 91.55 | T5: Internal Process | U5: High | V5: Red
A6: STR0004 | B6: Q1-FY25 | C6: International Expansion | D6: Cost-Income Ratio | E6: 11.52 | F6: 11.49 | G6: =ROUND((F6-E6)/ABS(E6)*100,1) -> -0.3 | H6: 14.5 | I6: =ROUND(H6*F6/100,2) -> 1.67 | J6: 16.84 | K6: 14.37 | L6: 17.98 | M6: 1.18 | N6: 18.75 | O6: 63 | P6: 2.62 | Q6: 5.16 | R6: 14.7 | S6: 88.37 | T6: Customer | U6: Normal | V6: Green
A7: STR0005 | B7: Q4-FY24 | C7: Digital Transformation | D7: Credit Growth | E7: 9.3 | F7: 9.28 | G7: =ROUND((F7-E7)/ABS(E7)*100,1) -> -0.2 | H7: 13.8 | I7: =ROUND(H7*F7/100,2) -> 1.28 | J7: 24.39 | K7: 20.95 | L7: 10.23 | M7: 0.86 | N7: 10.09 | O7: 56.03 | P7: 2.9 | Q7: 11.77 | R7: 15.7 | S7: 92.44 | T7: Financial | U7: Normal | V7: Green
A8: STR0006 | B8: Q4-FY26 | C8: Capital Optimization | D8: Deposit Mobilisation | E8: 17.98 | F8: 16.62 | G8: =ROUND((F8-E8)/ABS(E8)*100,1) -> -7.6 | H8: 7 | I8: =ROUND(H8*F8/100,2) -> 1.16 | J8: 22.54 | K8: 19.96 | L8: 11.18 | M8: 1.34 | N8: 18.91 | O8: 51.17 | P8: 3.03 | Q8: 8.33 | R8: 14.93 | S8: 68.95 | T8: Financial | U8: Watch | V8: Amber
A9: STR0007 | B9: Q4-FY24 | C9: HR & Talent | D9: Fee Income Ratio | E9: 20.8 | F9: 22.66 | G9: =ROUND((F9-E9)/ABS(E9)*100,1) -> 8.9 | H9: 9.2 | I9: =ROUND(H9*F9/100,2) -> 2.08 | J9: 15.16 | K9: 12.59 | L9: 12 | M9: 1.2 | N9: 18.4 | O9: 62.98 | P9: 3.32 | Q9: 6.78 | R9: 16.37 | S9: 79.95 | T9: Learning & Growth | U9: Normal | V9: Green
A10: STR0008 | B10: Q2-FY25 | C10: HR & Talent | D10: Credit Growth | E10: 10.53 | F10: 11.12 | G10: =ROUND((F10-E10)/ABS(E10)*100,1) -> 5.6 | H10: 11.2 | I10: =ROUND(H10*F10/100,2) -> 1.25 | J10: 24.99 | K10: 29.6 | L10: 10.31 | M10: 0.54 | N10: 14.03 | O10: 54.27 | P10: 3.66 | Q10: 19.55 | R10: 10.3 | S10: 80.49 | T10: Customer | U10: Normal | V10: Green
A11: STR0009 | B11: Q3-FY25 | C11: Capital Optimization | D11: ROE Target | E11: 16.34 | F11: 15.4 | G11: =ROUND((F11-E11)/ABS(E11)*100,1) -> -5.8 | H11: 18.7 | I11: =ROUND(H11*F11/100,2) -> 2.88 | J11: 23.87 | K11: 27.92 | L11: 9.35 | M11: 0.55 | N11: 12.57 | O11: 57.1 | P11: 3.08 | Q11: 7.49 | R11: 10.34 | S11: 81.7 | T11: Financial | U11: Watch | V11: Amber
A12: STR0010 | B12: Q4-FY24 | C12: Fee Income Growth | D12: Deposit Mobilisation | E12: 6.45 | F12: 5.98 | G12: =ROUND((F12-E12)/ABS(E12)*100,1) -> -7.3 | H12: 19 | I12: =ROUND(H12*F12/100,2) -> 1.14 | J12: 20.83 | K12: 17.6 | L12: 16.93 | M12: 0.88 | N12: 19.85 | O12: 63.17 | P12: 3.92 | Q12: 14.86 | R12: 7.01 | S12: 92.02 | T12: Customer | U12: Watch | V12: Amber
A13: STR0011 | B13: Q2-FY26 | C13: MSME Penetration | D13: MSME Share | E13: 19.7 | F13: 22.31 | G13: =ROUND((F13-E13)/ABS(E13)*100,1) -> 13.2 | H13: 11 | I13: =ROUND(H13*F13/100,2) -> 2.45 | J13: 20.15 | K13: 22.25 | L13: 12.51 | M13: 0.69 | N13: 19.16 | O13: 53.68 | P13: 2.95 | Q13: 8.71 | R13: 11.83 | S13: 61.71 | T13: Internal Process | U13: Normal | V13: Green
A14: STR0012 | B14: Q3-FY25 | C14: Cost Efficiency | D14: NPA Reduction | E14: 11.55 | F14: 11.57 | G14: =ROUND((F14-E14)/ABS(E14)*100,1) -> 0.2 | H14: 16.2 | I14: =ROUND(H14*F14/100,2) -> 1.87 | J14: 24.76 | K14: 25.75 | L14: 9.55 | M14: 0.63 | N14: 10.1 | O14: 45.09 | P14: 2.6 | Q14: 9.46 | R14: 13.48 | S14: 83.04 | T14: Learning & Growth | U14: Normal | V14: Green
... A102: STR0100 | B102: Q2-FY24 | C102: Digital Transformation | D102: Digital Adoption | E102: 10.56 | F102: 7.56 | G102: =ROUND((F102-E102)/ABS(E102)*100,1) -> -28.4 | H102: 9.8 | I102: =ROUND(H102*F102/100,2) -> 0.74 | J102: 23.69 | K102: 24.56 | L102: 9.84 | M102: 0.68 | N102: 13.72 | O102: 47.8 | P102: 2.54 | Q102: 19.41 | R102: 14.61 | S102: 86.51 | T102: Financial | U102: High | V102: Red
A103: STR0101 | B103: Q3-FY26 | C103: Cost Efficiency | D103: ROE Target | E103: 15.68 | F103: 12.62 | G103: -19.5 | H103: 13.6 | I103: 10.95 | J103: 16.92 | K103: 18.34 | L103: 11.64 | M103: 1.02 | N103: 19.55 | O103: 47.33 | P103: 2.82 | Q103: 8.65 | R103: 12.77 | S103: 71.74 | T103: Learning & Growth | U103: High | V103: Red
A104: STR0102 | B104: Q4-FY24 | C104: International Expansion | D104: Credit Growth | E104: 7.52 | F104: 6.41 | G104: -14.8 | H104: 12.5 | I104: 10.65 | J104: 17.98 | K104: 21.02 | L104: 14.09 | M104: 0.93 | N104: 10.05 | O104: 50.27 | P104: 3.27 | Q104: 11.44 | R104: 8.48 | S104: 86.09 | T104: Internal Process | U104: Watch | V104: Amber
A105: STR0103 | B105: Q3-FY25 | C105: Fee Income Growth | D105: Fee Income Ratio | E105: 17.73 | F105: 16.61 | G105: -6.3 | H105: 18.6 | I105: 17.43 | J105: 23.21 | K105: 20.98 | L105: 13.73 | M105: 1.14 | N105: 13.61 | O105: 57.44 | P105: 3.75 | Q105: 10.34 | R105: 15.85 | S105: 63.22 | T105: Customer | U105: Watch | V105: Amber
A106: STR0104 | B106: Q2-FY25 | C106: Fee Income Growth | D106: Credit Growth | E106: 21.28 | F106: 20.88 | G106: -1.9 | H106: 6 | I106: 5.89 | J106: 19.88 | K106: 23.85 | L106: 17.6 | M106: 0.87 | N106: 12.46 | O106: 57.79 | P106: 2.59 | Q106: 18.74 | R106: 10.41 | S106: 63.68 | T106: Learning & Growth | U106: Normal | V106: Green
A107: STR0105 | B107: Q3-FY24 | C107: Cost Efficiency | D107: Cost-Income Ratio | E107: 13.09 | F107: 12.97 | G107: -0.9 | H107: 10.6 | I107: 10.5 | J107: 17.89 | K107: 17.31 | L107: 17.92 | M107: 0.77 | N107: 17.65 | O107: 53.69 | P107: 2.98 | Q107: 8.5 | R107: 7.71 | S107: 80.32 | T107: Learning & Growth | U107: Normal | V107: Green
A108: STR0106 | B108: Q4-FY24 | C108: Capital Optimization | D108: MSME Share | E108: 22.76 | F108: 24.44 | G108: 7.4 | H108: 7.3 | I108: 7.84 | J108: 17.03 | K108: 21.14 | L108: 15.55 | M108: 0.89 | N108: 19.24 | O108: 48.01 | P108: 2.65 | Q108: 12.12 | R108: 7.04 | S108: 76.02 | T108: Learning & Growth | U108: Normal | V108: Green
A109: STR0107 | B109: Q2-FY26 | C109: HR & Talent | D109: Cost-Income Ratio | E109: 11.48 | F109: 9.26 | G109: -19.3 | H109: 14.9 | I109: 12.02 | J109: 19.11 | K109: 17.4 | L109: 15.49 | M109: 0.75 | N109: 15.78 | O109: 53.26 | P109: 2.65 | Q109: 15.96 | R109: 6.91 | S109: 79.79 | T109: Customer | U109: High | V109: Red
A110: STR0108 | B110: Q4-FY25 | C110: Capital Optimization | D110: MSME Share | E110: 20.75 | F110: 15.33 | G110: -26.1 | H110: 6.4 | I110: 4.73 | J110: 23.6 | K110: 25.34 | L110: 13 | M110: 0.6 | N110: 18.97 | O110: 55.31 | P110: 2.8 | Q110: 11.93 | R110: 5.38 | S110: 60.81 | T110: Customer | U110: High | V110: Red
A111: STR0109 | B111: Q2-FY26 | C111: Digital Transformation | D111: Deposit Mobilisation | E111: 6.18 | F111: 6.46 | G111: 4.5 | H111: 16.6 | I111: 17.35 | J111: 22.73 | K111: 27.16 | L111: 10.74 | M111: 1.11 | N111: 18.15 | O111: 64.18 | P111: 3.86 | Q111: 5.29 | R111: 16.65 | S111: 73.53 | T111: Internal Process | U111: Normal | V111: Green
A112: STR0110 | B112: Q3-FY25 | C112: Cost Efficiency | D112: NPA Reduction | E112: 7.64 | F112: 5.82 | G112: -23.8 | H112: 9.3 | I112: 7.08 | J112: 22.84 | K112: 23.76 | L112: 10.98 | M112: 1.27 | N112: 13.97 | O112: 51.47 | P112: 2.92 | Q112: 7.16 | R112: 12.52 | S112: 89.1 | T112: Customer | U112: High | V112: Red
A113: STR0111 | B113: Q3-FY26 | C113: International Expansion | D113: Credit Growth | E113: 20.01 | F113: 16.06 | G113: -19.7 | H113: 17.2 | I113: 13.8 | J113: 20.98 | K113: 20.58 | L113: 15.48 | M113: 1.09 | N113: 18.07 | O113: 57.61 | P113: 2.95 | Q113: 8.23 | R113: 15.67 | S113: 69.18 | T113: Financial | U113: High | V113: Red
A114: STR0112 | B114: Q2-FY24 | C114: Improve Asset Quality | D114: Digital Adoption | E114: 17.84 | F114: 18.75 | G114: 5.1 | H114: 10.7 | I114: 11.25 | J114: 17.92 | K114: 17.52 | L114: 14.2 | M114: 0.95 | N114: 16.72 | O114: 53.23 | P114: 3.83 | Q114: 8.36 | R114: 9.27 | S114: 81 | T114: Financial | U114: Normal | V114: Green
... A122: STR0120 | B122: Q3-FY24 | C122: Liability Franchise | D122: MSME Share | E122: 12.37 | F122: 11.01 | G122: -11 | H122: 17.9 | I122: 15.93 | J122: 16.88 | K122: 12.6 | L122: 13.54 | M122: 1.46 | N122: 10.38 | O122: 57.74 | P122: 2.95 | Q122: 19.56 | R122: 13.55 | S122: 73.26 | T122: Internal Process | U122: Watch | V122: Amber

Sheet KRI_Thresholds
A1: KRI THRESHOLD REFERENCE TABLE – BANK ENTERPRISE RISK DASHBOARD
A2: KRI_ID | B2: Pillar | C2: Risk_Type | D2: KRI_Name | E2: Unit | F2: Green_Min | G2: Green_Max | H2: Amber_Min | I2: Amber_Max | J2: Red_Trigger | K2: Direction | L2: Frequency | M2: Regulatory_Ref | N2: Data_Source | O2: Formula_Logic | P2: Owner | Q2: Review_Cycle
A3: KRI001 | B3: P1 | C3: Credit | D3: Gross NPA Ratio | E3: % | F3: 0 | G3: 5 | H3: 5 | I3: 6 | J3: >6 | K3: Lower Better | L3: Monthly | M3: RBI IRAC | N3: CRILC/Finacle | O3: NPA Amt/Gross Adv *100 | P3: Credit Risk Head | Q3: Quarterly
A4: KRI002 | B4: P1 | C4: Credit | D4: Net NPA Ratio | E4: % | F4: 0 | G4: 2 | H4: 2 | I4: 3 | J4: >3 | K4: Lower Better | L4: Monthly | M4: RBI IRAC | N4: CRILC/Finacle | O4: Net NPA/Net Adv *100 | P4: Credit Risk Head | Q4: Quarterly
A5: KRI003 | B5: P1 | C5: Credit | D5: SMA-0 Ratio | E5: % | F5: 0 | G5: 3 | H5: 3 | I5: 5 | J5: >5 | K5: Lower Better | L5: Monthly | M5: RBI Circular | N5: Finacle | O5: SMA-0 Bal/Gross Adv *100 | P5: Credit Risk Head | Q5: Monthly
A6: KRI004 | B6: P1 | C6: Credit | D6: SMA-1 Ratio | E6: % | F6: 0 | G6: 1 | H6: 1 | I6: 2 | J6: >2 | K6: Lower Better | L6: Monthly | M6: RBI Circular | N6: Finacle | O6: SMA-1 Bal/Gross Adv *100 | P6: Credit Risk Head | Q6: Monthly
A7: KRI005 | B7: P1 | C7: Credit | D7: SMA-2 Ratio | E7: % | F7: 0 | G7: 0.5 | H7: 0.5 | I7: 1 | J7: >1 | K7: Lower Better | L7: Monthly | M7: RBI Circular | N7: Finacle | O7: SMA-2 Bal/Gross Adv *100 | P7: Credit Risk Head | Q7: Monthly
A8: KRI006 | B8: P1 | C8: Credit | D8: PCR | E8: % | F8: 75 | G8: 100 | H8: 65 | I8: 75 | J8: <65 | K8: Higher Better | L8: Quarterly | M8: RBI | N8: Finacle | O8: Provisions/Gross NPA *100 | P8: Credit Risk Head | Q8: Quarterly
A9: KRI007 | B9: P1 | C9: Credit | D9: Slippage Ratio | E9: % | F9: 0 | G9: 2 | H9: 2 | I9: 3 | J9: >3 | K9: Lower Better | L9: Quarterly | M9: Internal | N9: DW | O9: New NPA in Qtr/Gross Adv | P9: Credit Risk Head | Q9: Quarterly
A10: KRI008 | B10: P1 | C10: Credit | D10: ECL Stage 3 Coverage | E10: % | F10: 60 | G10: 100 | H10: 50 | I10: 60 | J10: <50 | K10: Higher Better | L10: Quarterly | M10: Ind AS 109 | N10: ECL Engine | O10: Stage3 Prov/Stage3 EAD | P10: Risk Analytics | Q10: Quarterly
A11: KRI009 | B11: P1 | C11: Market | D11: VaR Utilisation | E11: % | F11: 0 | G11: 70 | H11: 70 | I11: 85 | J11: >85 | K11: Lower Better | L11: Daily | M11: Basel III | N11: Treasury System | O11: Trading VaR/VaR Limit*100 | P11: Market Risk Head | Q11: Monthly
A12: KRI010 | B12: P1 | C12: Market | D12: SVaR | E12: ₹Cr | F12: 0 | G12: 4000 | H12: 4000 | I12: 5000 | J12: >5000 | K12: Lower Better | L12: Daily | M12: Basel 2.5 | N12: Treasury System | O12: Historical SVaR (99%, 10D) | P12: Market Risk Head | Q12: Monthly
A13: KRI011 | B13: P1 | C13: Market | D13: IRC | E13: ₹Cr | F13: 0 | G13: 1500 | H13: 1500 | I13: 2000 | J13: >2000 | K13: Lower Better | L13: Weekly | M13: Basel III | N13: Treasury System | O13: IRC per Basel III methodology | P13: Market Risk Head | Q13: Quarterly
... A42: KRI040 | B42: P3 | C42: Disclosure | D42: Leverage Ratio Disclosure | E42: % | F42: 95 | G42: 100 | H42: 90 | I42: 95 | J42: <90 | K42: Higher Better | L42: Quarterly | M42: Basel III | N42: CAR Return | O42: Disclosure completeness % | P42: CFO | Q42: Quarterly

Sheet P3_Capital_Disclosure
A1: PILLAR 3 | Capital Adequacy Disclosure | XYZ Bank — Quarterly (Standalone & Consolidated)
A2: Regulatory Minimums (RBI Basel III incl. CCB): CET1 ≥ 8.0% | Tier 1 ≥ 9.5% | CRAR ≥ 11.5% | Leverage Ratio ≥ 3.5%
A3: Quarter | B3: Entity | C3: CET1 (%) | D3: Tier 1 (%) | E3: CRAR (%) | F3: Leverage Ratio (%) | G3: Completeness (%) | H3: Status
A4: Q1-FY24 | B4: XYZ Standalone | C4: 15.59 | D4: 16.43 | E4: 19.37 | F4: 1.49 | G4: 94.6 | H4: Amber
A5: Q2-FY24 | B5: XYZ Standalone | C5: 15.53 | D5: 16.36 | E5: 19.29 | F5: 1.51 | G5: 94.3 | H5: Amber
A6: Q3-FY24 | B6: XYZ Standalone | C6: 15.47 | D6: 16.34 | E6: 19.3 | F6: 1.47 | G6: 99.2 | H6: Green
A7: Q4-FY24 | B7: XYZ Standalone | C7: 15.54 | D7: 16.37 | E7: 19.33 | F7: 1.55 | G7: 96.2 | H7: Green
A8: Q1-FY25 | B8: XYZ Standalone | C8: 15.58 | D8: 16.44 | E8: 19.37 | F8: 1.45 | G8: 93.4 | H8: Amber
A9: Q2-FY25 | B9: XYZ Standalone | C9: 15.64 | D9: 16.52 | E9: 19.5 | F9: 1.57 | G9: 98.5 | H9: Green
A10: Q3-FY25 | B10: XYZ Standalone | C10: 15.61 | D10: 16.44 | E10: 19.39 | F10: 1.47 | G10: 99.2 | H10: Green
A11: Q4-FY25 | B11: XYZ Standalone | C11: 15.46 | D11: 16.31 | E11: 19.28 | F11: 1.45 | G11: 99.4 | H11: Green
A12: Q1-FY26 | B12: XYZ Standalone | C12: 15.52 | D12: 16.35 | E12: 19.3 | F12: 1.49 | G12: 97.6 | H12: Green
A13: Q2-FY26 | B13: XYZ Standalone | C13: 15.6 | D13: 16.49 | E13: 19.41 | F13: 1.57 | G13: 94.1 | H13: Amber
A14: Q3-FY26 | B14: XYZ Standalone | C14: 15.61 | D14: 16.46 | E14: 19.4 | F14: 1.48 | G14: 96.5 | H14: Green
A15: Q4-FY26 | B15: XYZ Standalone | C15: 15.62 | D15: 16.48 | E15: 19.42 | F15: 1.57 | G15: 93.5 | H15: Amber
... A39: Q4-FY26 | B39: XYZ Life | C39: 22.11 | D39: 23.36 | E39: 27.57 | F39: 2.07 | G39: 94.6 | H39: Amber

Sheet P3_Market_Disclosure
A1: PILLAR 3 | Pillar 3 – Market Discipline Disclosure Tracker | Bank Risk Management Dashboard
A2: Disclosure_ID | B2: Quarter | C2: Table_Ref | D2: Risk_Type | E2: Disclosure_Item | F2: Required_Value | G2: Disclosed_Value | H2: Deviation | I2: Completeness_% | J2: Format | K2: Filing_Mode | L2: Reviewed_by | M2: Approved_by | N2: Submission_Date | O2: Regulatory_Deadline | P2: Timeliness | Q2: External_Auditor_Sign | R2: Disclosure_URL | S2: Status | T2: RAG
A3: P3D0001 | B3: Q1-FY23 | C3: CR4 | D3: Capital | E3: Basel III Pillar 3 – Capital – Table CR4 – Item 1 | F3: 5365.84 | G3: 5146.38 | H3: -4.09 | I3: 91.2 | J3: PDF | K3: Bank Website | L3: DGM_Risk_5 | M3: ED (Risk) | N3: 13-May-2025 | O3: 10-Sep-2024 | P3: On-Time | Q3: No | R3: https://www.sbi.co.in/pillar3/Q1_FY23/cr4 | S3: Green | T3: Green
A4: P3D0002 | B4: Q2-FY23 | C4: MR2 | D4: CCR | E4: Basel III Pillar 3 – CCR – Table MR2 – Item 2 | F4: 7337.76 | G4: 7335.56 | H4: -0.03 | I4: 99.3 | J4: PDF | K4: BSE/NSE Filing | L4: DGM_Risk_2 | M4: ED (Risk) | N4: 10-Jul-2024 | O4: 31-Jan-2024 | P4: On-Time | Q4: Yes | R4: https://www.sbi.co.in/pillar3/Q2_FY23/mr2 | S4: Green | T4: Green
A5: P3D0003 | B5: Q2-FY23 | C5: OR1 | D5: CCR | E5: Basel III Pillar 3 – CCR – Table OR1 – Item 3 | F5: 3429.08 | G5: 3418.11 | H5: -0.32 | I5: 90 | J5: Excel | K5: BSE/NSE Filing | L5: DGM_Risk_5 | M5: ED (Risk) | N5: 08-Apr-2024 | O5: 17-Sep-2025 | P5: On-Time | Q5: Yes | R5: https://www.sbi.co.in/pillar3/Q2_FY23/or1 | S5: Green | T5: Green
A6: P3D0004 | B6: Q2-FY25 | C6: LR2 | D6: Market Risk | E6: Basel III Pillar 3 – Market Risk – Table LR2 – Item 4 | F6: 1706.74 | G6: 1649.22 | H6: -3.37 | I6: 95.1 | J6: Excel | K6: RBI Submission | L6: DGM_Risk_1 | M6: ED (Risk) | N6: 12-Jan-2025 | O6: 18-Jun-2025 | P6: On-Time | Q6: Yes | R6: https://www.sbi.co.in/pillar3/Q2_FY25/lr2 | S6: Green | T6: Green
A7: P3D0005 | B7: Q2-FY25 | C7: CR5 | D7: CCR | E7: Basel III Pillar 3 – CCR – Table CR5 – Item 5 | F7: 3063 | G7: 2987.34 | H7: -2.47 | I7: 92.7 | J7: XBRL | K7: BSE/NSE Filing | L7: DGM_Risk_6 | M7: ED (Risk) | N7: 09-Jul-2024 | O7: 18-Nov-2025 | P7: On-Time | Q7: Pending | R7: https://www.sbi.co.in/pillar3/Q2_FY25/cr5 | S7: Green | T7: Green
A8: P3D0006 | B8: Q1-FY26 | C8: LIQB | D8: Operational Risk | E8: Basel III Pillar 3 – Operational Risk – Table LIQB – Item 6 | F8: 9733.97 | G8: 9372.84 | H8: -3.71 | I8: 99 | J8: XBRL | K8: RBI Submission | L8: DGM_Risk_3 | M8: ED (Risk) | N8: 11-Aug-2024 | O8: 11-Oct-2025 | P8: On-Time | Q8: Yes | R8: https://www.sbi.co.in/pillar3/Q1_FY26/liqb | S8: Green | T8: Green
A9: P3D0007 | B9: Q3-FY26 | C9: OV2 | D9: Market Risk | E9: Basel III Pillar 3 – Market Risk – Table OV2 – Item 7 | F9: 8177.3 | G9: 7789.7 | H9: -4.74 | I9: 94.6 | J9: XBRL | K9: Bank Website | L9: DGM_Risk_3 | M9: ED (Risk) | N9: 06-Mar-2025 | O9: 22-Apr-2024 | P9: On-Time | Q9: No | R9: https://www.sbi.co.in/pillar3/Q3_FY26/ov2 | S9: Green | T9: Green
A10: P3D0008 | B10: Q2-FY24 | C10: IRRBB1 | D10: Market Risk | E10: Basel III Pillar 3 – Market Risk – Table IRRBB1 – Item 8 | F10: 9400.23 | G10: 9692.58 | H10: 3.11 | I10: 96.7 | J10: HTML | K10: BSE/NSE Filing | L10: DGM_Risk_4 | M10: ED (Risk) | N10: 24-Jan-2025 | O10: 10-Feb-2025 | P10: On-Time | Q10: Yes | R10: https://www.sbi.co.in/pillar3/Q2_FY24/irrbb1 | S10: Green | T10: Green
A11: P3D0009 | B11: Q2-FY23 | C11: CR3 | D11: IRRBB | E11: Basel III Pillar 3 – IRRBB – Table CR3 – Item 9 | F11: 10862.45 | G11: 10438.81 | H11: -3.9 | I11: 95 | J11: Excel | K11: Bank Website | L11: DGM_Risk_2 | M11: ED (Risk) | N11: 05-Nov-2024 | O11: 08-Apr-2025 | P11: Delayed | Q11: Yes | R11: https://www.sbi.co.in/pillar3/Q2_FY23/cr3 | S11: Amber | T11: Amber
A12: P3D0010 | B12: Q1-FY23 | C12: CC1 | D12: IRRBB | E12: Basel III Pillar 3 – IRRBB – Table CC1 – Item 10 | F12: 9433.35 | G12: 9710.69 | H12: 2.94 | I12: 91.9 | J12: Excel | K12: Bank Website | L12: DGM_Risk_5 | M12: ED (Risk) | N12: 25-Aug-2024 | O12: 10-Apr-2025 | P12: On-Time | Q12: No | R12: https://www.sbi.co.in/pillar3/Q1_FY23/cc1 | S12: Green | T12: Green
A13: P3D0011 | B13: Q4-FY26 | C13: LIQB | D13: Leverage | E13: Basel III Pillar 3 – Leverage – Table LIQB – Item 11 | F13: 4642.12 | G13: 4736.82 | H13: 2.04 | I13: 96.4 | J13: XBRL | K13: Bank Website | L13: DGM_Risk_3 | M13: ED (Risk) | N13: 28-Feb-2024 | O13: 25-Jun-2025 | P13: On-Time | Q13: No | R13: https://www.sbi.co.in/pillar3/Q4_FY26/liqb | S13: Green | T13: Green
A14: P3D0012 | B14: Q3-FY23 | C14: LR2 | D14: IRRBB | E14: Basel III Pillar 3 – IRRBB – Table LR2 – Item 12 | F14: 3004.75 | G14: 2984.02 | H14: -0.69 | I14: 89.8 | J14: XBRL | K14: RBI Submission | L14: DGM_Risk_4 | M14: ED (Risk) | N14: 20-Nov-2024 | O14: 24-Nov-2025 | P14: On-Time | Q14: No | R14: https://www.sbi.co.in/pillar3/Q3_FY23/lr2 | S14: Amber | T14: Amber
... A62: P3D0060 | B62: Q2-FY24 | C62: OV2 | D62: IRRBB | E62: Basel III Pillar 3 – IRRBB – Table OV2 – Item 60 | F62: 11093.97 | G62: 10963.06 | H62: -1.18 | I62: 97 | J62: Excel | K62: Annual Report | L62: DGM_Risk_3 | M62: ED (Risk) | N62: 22-Mar-2025 | O62: 17-Mar-2024 | P62: On-Time | Q62: No | R62: https://www.sbi.co.in/pillar3/Q2_FY24/ov2 | S62: Green | T62: Green

Sheet Monthly_KRI_Trend
A1: 12-MONTH KRI TREND | SBI Enterprise Risk Dashboard | All monthly KRI values are Excel formulas derived from Monthly_Data sheet
A2: NOTE: Blue text = hardcoded base inputs (Monthly_Data sheet) | Green text = formula referencing Monthly_Data | Change any input in Monthly_Data → all KRIs auto-recalculate
A3: # | B3: KRI Name | C3: Unit | D3: Direction | E3: Red Thresh | F3: Amber Thresh | G3: May-25 | H3: Jun-25 | I3: Jul-25 | J3: Aug-25 | K3: Sep-25 | L3: Oct-25 | M3: Nov-25 | N3: Dec-25 | O3: Jan-26 | P3: Feb-26 | Q3: Mar-26 | R3: Apr-26 | S3: 12M Avg | T3: Apr-26 (Current) | U3: 3M Avg | V3: MoM Change | W3: Trend
A4: 1 | B4: Gross NPA Ratio | C4: % | D4: Lower Better | E4: 6 | F4: 5 | G4: =IF(Monthly_Data!C5=0,"",((Monthly_Data!C4/Monthly_Data!C5)*100)) -> 5.7999303 | H4: =IF(Monthly_Data!D5=0,"",((Monthly_Data!D4/Monthly_Data!D5)*100)) -> 5.6977964 | I4: =IF(Monthly_Data!E5=0,"",((Monthly_Data!E4/Monthly_Data!E5)*100)) -> 5.5031447 | J4: =IF(Monthly_Data!F5=0,"",((Monthly_Data!F4/Monthly_Data!F5)*100)) -> 5.3981059 | K4: =IF(Monthly_Data!G5=0,"",((Monthly_Data!G4/Monthly_Data!G5)*100)) -> 5.2978276 | L4: =IF(Monthly_Data!H5=0,"",((Monthly_Data!H4/Monthly_Data!H5)*100)) -> 5.2036517 | M4: =IF(Monthly_Data!I5=0,"",((Monthly_Data!I4/Monthly_Data!I5)*100)) -> 5.101683 | N4: =IF(Monthly_Data!J5=0,"",((Monthly_Data!J4/Monthly_Data!J5)*100)) -> 5 | ... R4: =IF(Monthly_Data!N5=0,"",((Monthly_Data!N4/Monthly_Data!N5)*100)) -> 5 | S4: =IFERROR(AVERAGE(G4:R4),"") -> 5.233052 | T4: =R4 -> 5 | U4: =IFERROR(AVERAGE(P4:R4),"") -> 4.9660342 | V4: =IFERROR(R4-Q4,"") -> 0 | W4: =IFERROR(IF((R4-G4)<0,"↑ Improving",IF((R4-G4)>0,"↓ Worsening","→ Stable")),"N/A") -> ↑ Improving
A5: 2 | B5: Net NPA Ratio | C5: % | D5: Lower Better | E5: 3 | F5: 2 | G5: =IF(Monthly_Data!C7=0,"",((Monthly_Data!C6/Monthly_Data!C7)*100)) -> 2.8006274 | H5: =IF(Monthly_Data!D7=0,"",((Monthly_Data!D6/Monthly_Data!D7)*100)) -> 2.7026932 | I5: =IF(Monthly_Data!E7=0,"",((Monthly_Data!E6/Monthly_Data!E7)*100)) -> 2.6016771 | J5: =IF(Monthly_Data!F7=0,"",((Monthly_Data!F6/Monthly_Data!F7)*100)) -> 2.5001754 | K5: =IF(Monthly_Data!G7=0,"",((Monthly_Data!G6/Monthly_Data!G7)*100)) -> 2.3966363 | L5: =IF(Monthly_Data!H7=0,"",((Monthly_Data!H6/Monthly_Data!H7)*100)) -> 2.3005618 | M5: =IF(Monthly_Data!I7=0,"",((Monthly_Data!I6/Monthly_Data!I7)*100)) -> 2.1984572 | N5: =IF(Monthly_Data!J7=0,"",((Monthly_Data!J6/Monthly_Data!J7)*100)) -> 2.1 | ... R5: =IF(Monthly_Data!N7=0,"",((Monthly_Data!N6/Monthly_Data!N7)*100)) -> 2.1 | S5: =IFERROR(AVERAGE(G5:R5),"") -> 2.3254877 | T5: =R5 -> 2.1 | U5: =IFERROR(AVERAGE(P5:R5),"") -> 2.0676037 | V5: =IFERROR(R5-Q5,"") -> 0 | W5: =IFERROR(IF((R5-G5)<0,"↑ Improving",IF((R5-G5)>0,"↓ Worsening","→ Stable")),"N/A") -> ↑ Improving
A6: 3 | B6: SMA-0 Ratio | C6: % | D6: Lower Better | E6: 5 | F6: 3 | G6: =IF(Monthly_Data!C5=0,"",((Monthly_Data!C8/Monthly_Data!C5)*100)) -> 3.3900314 | H6: =IF(Monthly_Data!D5=0,"",((Monthly_Data!D8/Monthly_Data!D5)*100)) -> 3.3018538 | I6: =IF(Monthly_Data!E5=0,"",((Monthly_Data!E8/Monthly_Data!E5)*100)) -> 3.3504542 | J6: =IF(Monthly_Data!F5=0,"",((Monthly_Data!F8/Monthly_Data!F5)*100)) -> 3.3703964 | K6: =IF(Monthly_Data!G5=0,"",((Monthly_Data!G8/Monthly_Data!G5)*100)) -> 3.3538893 | L6: =IF(Monthly_Data!H5=0,"",((Monthly_Data!H8/Monthly_Data!H5)*100)) -> 3.292486 | M6: =IF(Monthly_Data!I5=0,"",((Monthly_Data!I8/Monthly_Data!I5)*100)) -> 3.2177419 | N6: =IF(Monthly_Data!J5=0,"",((Monthly_Data!J8/Monthly_Data!J5)*100)) -> 3.2 | ... R6: =IF(Monthly_Data!N5=0,"",((Monthly_Data!N8/Monthly_Data!N5)*100)) -> 3.2 | S6: =IFERROR(AVERAGE(G6:R6),"") -> 3.2737269 | T6: =R6 -> 3.2 | U6: =IFERROR(AVERAGE(P6:R6),"") -> 3.2014992 | V6: =IFERROR(R6-Q6,"") -> 0 | W6: =IFERROR(IF((R6-G6)<0,"↑ Improving",IF((R6-G6)>0,"↓ Worsening","→ Stable")),"N/A") -> ↑ Improving
A7: 4 | B7: SMA-1 Ratio | C7: % | D7: Lower Better | E7: 2 | F7: 1 | G7: =IF(Monthly_Data!C5=0,"",((Monthly_Data!C9/Monthly_Data!C5)*100)) -> 1.2011154 | H7: =IF(Monthly_Data!D5=0,"",((Monthly_Data!D9/Monthly_Data!D5)*100)) -> 1.119972 | I7: =IF(Monthly_Data!E5=0,"",((Monthly_Data!E9/Monthly_Data!E5)*100)) -> 1.1044724 | J7: =IF(Monthly_Data!F5=0,"",((Monthly_Data!F9/Monthly_Data!F5)*100)) -> 1.1080323 | K7: =IF(Monthly_Data!G5=0,"",((Monthly_Data!G9/Monthly_Data!G5)*100)) -> 1.1040645 | L7: =IF(Monthly_Data!H5=0,"",((Monthly_Data!H9/Monthly_Data!H5)*100)) -> 1.1594101 | M7: =IF(Monthly_Data!I5=0,"",((Monthly_Data!I9/Monthly_Data!I5)*100)) -> 1.1584853 | N7: =IF(Monthly_Data!J5=0,"",((Monthly_Data!J9/Monthly_Data!J5)*100)) -> 1.2 | ... R7: =IF(Monthly_Data!N5=0,"",((Monthly_Data!N9/Monthly_Data!N5)*100)) -> 1.2 | S7: =IFERROR(AVERAGE(G7:R7),"") -> 1.1632086 | T7: =R7 -> 1.2 | U7: =IFERROR(AVERAGE(P7:R7),"") -> 1.2005622 | V7: =IFERROR(R7-Q7,"") -> 0 | W7: =IFERROR(IF((R7-G7)<0,"↑ Improving",IF((R7-G7)>0,"↓ Worsening","→ Stable")),"N/A") -> ↑ Improving
A8: 5 | B8: SMA-2 Ratio | C8: % | D8: Lower Better | E8: 1 | F8: 0.5 | G8: =IF(Monthly_Data!C5=0,"",((Monthly_Data!C10/Monthly_Data!C5)*100)) -> 0.59986058 | H8: =IF(Monthly_Data!D5=0,"",((Monthly_Data!D10/Monthly_Data!D5)*100)) -> 0.61245191 | I8: =IF(Monthly_Data!E5=0,"",((Monthly_Data!E10/Monthly_Data!E5)*100)) -> 0.60202655 | J8: =IF(Monthly_Data!F5=0,"",((Monthly_Data!F10/Monthly_Data!F5)*100)) -> 0.60329709 | K8: =IF(Monthly_Data!G5=0,"",((Monthly_Data!G10/Monthly_Data!G5)*100)) -> 0.60056062 | L8: =IF(Monthly_Data!H5=0,"",((Monthly_Data!H10/Monthly_Data!H5)*100)) -> 0.60007022 | M8: =IF(Monthly_Data!I5=0,"",((Monthly_Data!I10/Monthly_Data!I5)*100)) -> 0.59782609 | N8: =IF(Monthly_Data!J5=0,"",((Monthly_Data!J10/Monthly_Data!J5)*100)) -> 0.7 | ... R8: =IF(Monthly_Data!N5=0,"",((Monthly_Data!N10/Monthly_Data!N5)*100)) -> 0.7 | S8: =IFERROR(AVERAGE(G8:R8),"") -> 0.64315121 | T8: =R8 -> 0.7 | U8: =IFERROR(AVERAGE(P8:R8),"") -> 0.70032795 | V8: =IFERROR(R8-Q8,"") -> 0 | W8: =IFERROR(IF((R8-G8)<0,"↑ Improving",IF((R8-G8)>0,"↓ Worsening","→ Stable")),"N/A") -> ↓ Worsening
A9: 6 | B9: PCR (Provision Coverage Ratio) | C9: % | D9: Higher Better | E9: 65 | F9: 75 | G9: =IF(Monthly_Data!C4=0,"",((Monthly_Data!C12/Monthly_Data!C4)*100)) -> 76.033654 | H9: =IF(Monthly_Data!D4=0,"",((Monthly_Data!D12/Monthly_Data!D4)*100)) -> 71.706568 | I9: =IF(Monthly_Data!E4=0,"",((Monthly_Data!E12/Monthly_Data!E4)*100)) -> 74.234921 | J9: =IF(Monthly_Data!F4=0,"",((Monthly_Data!F12/Monthly_Data!F4)*100)) -> 70.506823 | K9: =IF(Monthly_Data!G4=0,"",((Monthly_Data!G12/Monthly_Data!G4)*100)) -> 72.162698 | L9: =IF(Monthly_Data!H4=0,"",((Monthly_Data!H12/Monthly_Data!H4)*100)) -> 72.989204 | M9: =IF(Monthly_Data!I4=0,"",((Monthly_Data!I12/Monthly_Data!I4)*100)) -> 76 | N9: =IF(Monthly_Data!J4=0,"",((Monthly_Data!J12/Monthly_Data!J4)*100)) -> 76 | ... R9: =IF(Monthly_Data!N4=0,"",((Monthly_Data!N12/Monthly_Data!N4)*100)) -> 76 | S9: =IFERROR(AVERAGE(G9:R9),"") -> 74.749977 | T9: =R9 -> 76 | U9: =IFERROR(AVERAGE(P9:R9),"") -> 76.560976 | V9: =IFERROR(R9-Q9,"") -> 0 | W9: =IFERROR(IF((R9-G9)>0,"↑ Improving",IF((R9-G9)<0,"↓ Worsening","→ Stable")),"N/A") -> ↓ Worsening
A10: 8 | B10: ECL Stage 3 Coverage | C10: % | D10: Higher Better | E10: 50 | F10: 60 | G10: =IF(Monthly_Data!C13=0,"",((Monthly_Data!C14/Monthly_Data!C13)*100)) -> 61.502404 | H10: =IF(Monthly_Data!D13=0,"",((Monthly_Data!D14/Monthly_Data!D13)*100)) -> 61.5531 | I10: =IF(Monthly_Data!E13=0,"",((Monthly_Data!E14/Monthly_Data!E13)*100)) -> 63.142857 | J10: =IF(Monthly_Data!F13=0,"",((Monthly_Data!F14/Monthly_Data!F13)*100)) -> 63.365822 | K10: =IF(Monthly_Data!G13=0,"",((Monthly_Data!G14/Monthly_Data!G13)*100)) -> 63.789683 | L10: =IF(Monthly_Data!H13=0,"",((Monthly_Data!H14/Monthly_Data!H13)*100)) -> 63.481781 | M10: =IF(Monthly_Data!I13=0,"",((Monthly_Data!I14/Monthly_Data!I13)*100)) -> 63.56701 | N10: =IF(Monthly_Data!J13=0,"",((Monthly_Data!J14/Monthly_Data!J13)*100)) -> 63.101754 | ... R10: =IF(Monthly_Data!N13=0,"",((Monthly_Data!N14/Monthly_Data!N13)*100)) -> 63.101754 | S10: =IFERROR(AVERAGE(G10:R10),"") -> 63.006507 | T10: =R10 -> 63.101754 | U10: =IFERROR(AVERAGE(P10:R10),"") -> 63.129529 | V10: =IFERROR(R10-Q10,"") -> 0 | W10: =IFERROR(IF((R10-G10)>0,"↑ Improving",IF((R10-G10)<0,"↓ Worsening","→ Stable")),"N/A") -> ↑ Improving
A11: 10 | B11: VaR Utilisation (1D 99%) | C11: % | D11: Lower Better | E11: 85 | F11: 70 | G11: =IF(Monthly_Data!C17=0,"",((Monthly_Data!C16/Monthly_Data!C17)*100)) -> 72 | H11: =IF(Monthly_Data!D17=0,"",((Monthly_Data!D16/Monthly_Data!D17)*100)) -> 68 | I11: =IF(Monthly_Data!E17=0,"",((Monthly_Data!E16/Monthly_Data!E17)*100)) -> 66 | J11: =IF(Monthly_Data!F17=0,"",((Monthly_Data!F16/Monthly_Data!F17)*100)) -> 66.5 | K11: =IF(Monthly_Data!G17=0,"",((Monthly_Data!G16/Monthly_Data!G17)*100)) -> 63 | L11: =IF(Monthly_Data!H17=0,"",((Monthly_Data!H16/Monthly_Data!H17)*100)) -> 64 | M11: =IF(Monthly_Data!I17=0,"",((Monthly_Data!I16/Monthly_Data!I17)*100)) -> 64 | N11: =IF(Monthly_Data!J17=0,"",((Monthly_Data!J16/Monthly_Data!J17)*100)) -> 65 | ... R11: =IF(Monthly_Data!N17=0,"",((Monthly_Data!N16/Monthly_Data!N17)*100)) -> 64 | S11: =IFERROR(AVERAGE(G11:R11),"") -> 65.458333 | T11: =R11 -> 64 | U11: =IFERROR(AVERAGE(P11:R11),"") -> 64 | V11: =IFERROR(R11-Q11,"") -> 0 | W11: =IFERROR(IF((R11-G11)<0,"↑ Improving",IF((R11-G11)>0,"↓ Worsening","→ Stable")),"N/A") -> ↑ Improving
A12: 11 | B12: SVaR (Stressed VaR) | C12: ₹ Cr | D12: Lower Better | E12: 5000 | F12: 4000 | G12: =Monthly_Data!C18 -> 4250 | H12: =Monthly_Data!D18 -> 4300 | I12: =Monthly_Data!E18 -> 4280 | J12: =Monthly_Data!F18 -> 4210 | K12: =Monthly_Data!G18 -> 4150 | L12: =Monthly_Data!H18 -> 4100 | M12: =Monthly_Data!I18 -> 4080 | N12: =Monthly_Data!J18 -> 4060 | ... R12: =Monthly_Data!N18 -> 4050 | S12: =IFERROR(AVERAGE(G12:R12),"") -> 4135.8333 | T12: =R12 -> 4050 | U12: =IFERROR(AVERAGE(P12:R12),"") -> 4050 | V12: =IFERROR(R12-Q12,"") -> 0 | W12: =IFERROR(IF((R12-G12)<0,"↑ Improving",IF((R12-G12)>0,"↓ Worsening","→ Stable")),"N/A") -> ↑ Improving
A13: 12 | B13: IRC (Incremental Risk Charge) | C13: ₹ Cr | D13: Lower Better | E13: 2000 | F13: 1500 | G13: =Monthly_Data!C19 -> 1820 | H13: =Monthly_Data!D19 -> 1800 | I13: =Monthly_Data!E19 -> 1780 | J13: =Monthly_Data!F19 -> 1760 | K13: =Monthly_Data!G19 -> 1750 | L13: =Monthly_Data!H19 -> 1740 | M13: =Monthly_Data!I19 -> 1730 | N13: =Monthly_Data!J19 -> 1720 | ... R13: =Monthly_Data!N19 -> 1720 | S13: =IFERROR(AVERAGE(G13:R13),"") -> 1748.3333 | T13: =R13 -> 1720 | U13: =IFERROR(AVERAGE(P13:R13),"") -> 1720 | V13: =IFERROR(R13-Q13,"") -> 0 | W13: =IFERROR(IF((R13-G13)<0,"↑ Improving",IF((R13-G13)>0,"↓ Worsening","→ Stable")),"N/A") -> ↑ Improving
A14: 13 | B14: FX Open Position | C14: ₹ Cr | D14: Lower Better | E14: 150 | F14: 100 | G14: =Monthly_Data!C20 -> 92 | H14: =Monthly_Data!D20 -> 94 | I14: =Monthly_Data!E20 -> 91 | J14: =Monthly_Data!F20 -> 88 | K14: =Monthly_Data!G20 -> 85 | L14: =Monthly_Data!H20 -> 87 | M14: =Monthly_Data!I20 -> 88 | N14: =Monthly_Data!J20 -> 89 | ... R14: =Monthly_Data!N20 -> 88 | S14: =IFERROR(AVERAGE(G14:R14),"") -> 89 | T14: =R14 -> 88 | U14: =IFERROR(AVERAGE(P14:R14),"") -> 88 | V14: =IFERROR(R14-Q14,"") -> 0 | W14: =IFERROR(IF((R14-G14)<0,"↑ Improving",IF((R14-G14)>0,"↓ Worsening","→ Stable")),"N/A") -> ↑ Improving
A15: 14 | B15: DV01 Limit Utilisation | C15: % | D15: Lower Better | E15: 80 | F15: 60 | G15: =IF(Monthly_Data!C22=0,"",((Monthly_Data!C21/Monthly_Data!C22)*100)) -> 60.222222 | H15: =IF(Monthly_Data!D22=0,"",((Monthly_Data!D21/Monthly_Data!D22)*100)) -> 59.777778 | I15: =IF(Monthly_Data!E22=0,"",((Monthly_Data!E21/Monthly_Data!E22)*100)) -> 59.444444 | J15: =IF(Monthly_Data!F22=0,"",((Monthly_Data!F21/Monthly_Data!F22)*100)) -> 59.111111 | K15: =IF(Monthly_Data!G22=0,"",((Monthly_Data!G21/Monthly_Data!G22)*100)) -> 58.777778 | L15: =IF(Monthly_Data!H22=0,"",((Monthly_Data!H21/Monthly_Data!H22)*100)) -> 58.444444 | M15: =IF(Monthly_Data!I22=0,"",((Monthly_Data!I21/Monthly_Data!I22)*100)) -> 58.222222 | N15: =IF(Monthly_Data!J22=0,"",((Monthly_Data!J21/Monthly_Data!J22)*100)) -> 58 | ... R15: =IF(Monthly_Data!N22=0,"",((Monthly_Data!N21/Monthly_Data!N22)*100)) -> 57.777778 | S15: =IFERROR(AVERAGE(G15:R15),"") -> 58.592593 | T15: =R15 -> 57.777778 | U15: =IFERROR(AVERAGE(P15:R15),"") -> 57.777778 | V15: =IFERROR(R15-Q15,"") -> 0 | W15: =IFERROR(IF((R15-G15)<0,"↑ Improving",IF((R15-G15)>0,"↓ Worsening","→ Stable")),"N/A") -> ↑ Improving
A16: 15 | B16: Operational Loss Ratio | C16: % of NII | D16: Lower Better | E16: 0.15 | F16: 0.1 | G16: =IF(Monthly_Data!C25=0,"",((Monthly_Data!C24/100)/Monthly_Data!C25*100)) -> 1.1999657e-05 | H16: =IF(Monthly_Data!D25=0,"",((Monthly_Data!D24/100)/Monthly_Data!D25*100)) -> 1.1142539e-05 | I16: =IF(Monthly_Data!E25=0,"",((Monthly_Data!E24/100)/Monthly_Data!E25*100)) -> 1.1142539e-05 | J16: =IF(Monthly_Data!F25=0,"",((Monthly_Data!F24/100)/Monthly_Data!F25*100)) -> 1.028542e-05 | K16: =IF(Monthly_Data!G25=0,"",((Monthly_Data!G24/100)/Monthly_Data!G25*100)) -> 1.1142539e-05 | L16: =IF(Monthly_Data!H25=0,"",((Monthly_Data!H24/100)/Monthly_Data!H25*100)) -> 1.028542e-05 | M16: =IF(Monthly_Data!I25=0,"",((Monthly_Data!I24/100)/Monthly_Data!I25*100)) -> 1.028542e-05 | N16: =IF(Monthly_Data!J25=0,"",((Monthly_Data!J24/100)/Monthly_Data!J25*100)) -> 1.028542e-05 | ... R16: =IF(Monthly_Data!N25=0,"",((Monthly_Data!N24/100)/Monthly_Data!N25*100)) -> 1.028542e-05 | S16: =IFERROR(AVERAGE(G16:R16),"") -> 1.0571127e-05 | T16: =R16 -> 1.028542e-05 | U16: =IFERROR(AVERAGE(P16:R16),"") -> 9.9997143e-06 | V16: =IFERROR(R16-Q16,"") -> 0 | W16: =IFERROR(IF((R16-G16)<0,"↑ Improving",IF((R16-G16)>0,"↓ Worsening","→ Stable")),"N/A") -> ↑ Improving
A17: 16 | B17: KCI Breach Count | C17: Count | D17: Lower Better | E17: 6 | F17: 3 | G17: =Monthly_Data!C26 -> 3 | H17: =Monthly_Data!D26 -> 3 | I17: =Monthly_Data!E26 -> 3 | J17: =Monthly_Data!F26 -> 3 | K17: =Monthly_Data!G26 -> 3 | L17: =Monthly_Data!H26 -> 3 | M17: =Monthly_Data!I26 -> 3 | N17: =Monthly_Data!J26 -> 3 | ... R17: =Monthly_Data!N26 -> 3 | S17: =IFERROR(AVERAGE(G17:R17),"") -> 3 | T17: =R17 -> 3 | U17: =IFERROR(AVERAGE(P17:R17),"") -> 3 | V17: =IFERROR(R17-Q17,"") -> 0 | W17: =IFERROR(IF((R17-G17)<0,"↑ Improving",IF((R17-G17)>0,"↓ Worsening","→ Stable")),"N/A") -> → Stable
A18: 17 | B18: Overdue Action Items | C18: Count | D18: Lower Better | E18: 20 | F18: 10 | G18: =Monthly_Data!C27 -> 20 | H18: =Monthly_Data!D27 -> 20 | I18: =Monthly_Data!E27 -> 19 | J18: =Monthly_Data!F27 -> 18 | K18: =Monthly_Data!G27 -> 18 | L18: =Monthly_Data!H27 -> 18 | M18: =Monthly_Data!I27 -> 18 | N18: =Monthly_Data!J27 -> 18 | ... R18: =Monthly_Data!N27 -> 18 | S18: =IFERROR(AVERAGE(G18:R18),"") -> 18.416667 | T18: =R18 -> 18 | U18: =IFERROR(AVERAGE(P18:R18),"") -> 18 | V18: =IFERROR(R18-Q18,"") -> 0 | W18: =IFERROR(IF((R18-G18)<0,"↑ Improving",IF((R18-G18)>0,"↓ Worsening","→ Stable")),"N/A") -> ↑ Improving
A19: 18 | B19: CRAR (Total) | C19: % | D19: Higher Better | E19: 13 | F19: 15 | G19: =IF(Monthly_Data!C32=0,"",((Monthly_Data!C31/Monthly_Data!C32)*100)) -> 19.122807 | H19: =IF(Monthly_Data!D32=0,"",((Monthly_Data!D31/Monthly_Data!D32)*100)) -> 19.16849 | I19: =IF(Monthly_Data!E32=0,"",((Monthly_Data!E31/Monthly_Data!E32)*100)) -> 19.213974 | J19: =IF(Monthly_Data!F32=0,"",((Monthly_Data!F31/Monthly_Data!F32)*100)) -> 19.259259 | K19: =IF(Monthly_Data!G32=0,"",((Monthly_Data!G31/Monthly_Data!G32)*100)) -> 19.304348 | L19: =IF(Monthly_Data!H32=0,"",((Monthly_Data!H31/Monthly_Data!H32)*100)) -> 19.349241 | M19: =IF(Monthly_Data!I32=0,"",((Monthly_Data!I31/Monthly_Data!I32)*100)) -> 19.307359 | N19: =IF(Monthly_Data!J32=0,"",((Monthly_Data!J31/Monthly_Data!J32)*100)) -> 19.265659 | ... R19: =IF(Monthly_Data!N32=0,"",((Monthly_Data!N31/Monthly_Data!N32)*100)) -> 19.3235 | S19: =IFERROR(AVERAGE(G19:R19),"") -> 19.263886 | T19: =R19 -> 19.3235 | U19: =IFERROR(AVERAGE(P19:R19),"") -> 19.279555 | V19: =IFERROR(R19-Q19,"") -> 0.11777418 | W19: =IFERROR(IF((R19-G19)>0,"↑ Improving",IF((R19-G19)<0,"↓ Worsening","→ Stable")),"N/A") -> ↑ Improving
A20: 19 | B20: CET-1 Ratio | C20: % | D20: Higher Better | E20: 9 | F20: 11 | G20: =IF(Monthly_Data!C32=0,"",((Monthly_Data!C29/Monthly_Data!C32)*100)) -> 15.614035 | H20: =IF(Monthly_Data!D32=0,"",((Monthly_Data!D29/Monthly_Data!D32)*100)) -> 15.667396 | I20: =IF(Monthly_Data!E32=0,"",((Monthly_Data!E29/Monthly_Data!E32)*100)) -> 15.720524 | J20: =IF(Monthly_Data!F32=0,"",((Monthly_Data!F29/Monthly_Data!F32)*100)) -> 15.77342 | K20: =IF(Monthly_Data!G32=0,"",((Monthly_Data!G29/Monthly_Data!G32)*100)) -> 15.826087 | L20: =IF(Monthly_Data!H32=0,"",((Monthly_Data!H29/Monthly_Data!H32)*100)) -> 15.878525 | M20: =IF(Monthly_Data!I32=0,"",((Monthly_Data!I29/Monthly_Data!I32)*100)) -> 15.844156 | N20: =IF(Monthly_Data!J32=0,"",((Monthly_Data!J29/Monthly_Data!J32)*100)) -> 15.809935 | ... R20: =IF(Monthly_Data!N32=0,"",((Monthly_Data!N29/Monthly_Data!N32)*100)) -> 15.62585 | S20: =IFERROR(AVERAGE(G20:R20),"") -> 15.705676 | T20: =R20 -> 15.62585 | U20: =IFERROR(AVERAGE(P20:R20),"") -> 15.573983 | V20: =IFERROR(R20-Q20,"") -> 0.12646807 | W20: =IFERROR(IF((R20-G20)>0,"↑ Improving",IF((R20-G20)<0,"↓ Worsening","→ Stable")),"N/A") -> ↑ Improving
A21: 20 | B21: Leverage Ratio (Basel III) | C21: % | D21: Higher Better | E21: 3.5 | F21: 4 | G21: =IF(Monthly_Data!C33=0,"",((Monthly_Data!C30/Monthly_Data!C33)*100)) -> 1.5080645 | H21: =IF(Monthly_Data!D33=0,"",((Monthly_Data!D30/Monthly_Data!D33)*100)) -> 1.5100402 | I21: =IF(Monthly_Data!E33=0,"",((Monthly_Data!E30/Monthly_Data!E33)*100)) -> 1.512 | J21: =IF(Monthly_Data!F33=0,"",((Monthly_Data!F30/Monthly_Data!F33)*100)) -> 1.5139442 | K21: =IF(Monthly_Data!G33=0,"",((Monthly_Data!G30/Monthly_Data!G33)*100)) -> 1.515873 | L21: =IF(Monthly_Data!H33=0,"",((Monthly_Data!H30/Monthly_Data!H33)*100)) -> 1.5177866 | M21: =IF(Monthly_Data!I33=0,"",((Monthly_Data!I30/Monthly_Data!I33)*100)) -> 1.511811 | N21: =IF(Monthly_Data!J33=0,"",((Monthly_Data!J30/Monthly_Data!J33)*100)) -> 1.5058824 | ... R21: =IF(Monthly_Data!N33=0,"",((Monthly_Data!N30/Monthly_Data!N33)*100)) -> 1.5515904 | S21: =IFERROR(AVERAGE(G21:R21),"") -> 1.5133288 | T21: =R21 -> 1.5515904 | U21: =IFERROR(AVERAGE(P21:R21),"") -> 1.5232605 | V21: =IFERROR(R21-Q21,"") -> 0.08538704 | W21: =IFERROR(IF((R21-G21)>0,"↑ Improving",IF((R21-G21)<0,"↓ Worsening","→ Stable")),"N/A") -> ↑ Improving
A22: 21 | B22: LCR (Liquidity Coverage Ratio) | C22: % | D22: Higher Better | E22: 100 | F22: 120 | G22: =IF(Monthly_Data!C36=0,"",((Monthly_Data!C35/Monthly_Data!C36)*100)) -> 117.9941 | H22: =IF(Monthly_Data!D36=0,"",((Monthly_Data!D35/Monthly_Data!D36)*100)) -> 119.99324 | I22: =IF(Monthly_Data!E36=0,"",((Monthly_Data!E35/Monthly_Data!E36)*100)) -> 121.99254 | J22: =IF(Monthly_Data!F36=0,"",((Monthly_Data!F35/Monthly_Data!F36)*100)) -> 124.00794 | K22: =IF(Monthly_Data!G36=0,"",((Monthly_Data!G35/Monthly_Data!G36)*100)) -> 125 | L22: =IF(Monthly_Data!H36=0,"",((Monthly_Data!H35/Monthly_Data!H36)*100)) -> 125.98934 | M22: =IF(Monthly_Data!I36=0,"",((Monthly_Data!I35/Monthly_Data!I36)*100)) -> 127.00429 | N22: =IF(Monthly_Data!J36=0,"",((Monthly_Data!J35/Monthly_Data!J36)*100)) -> 128.005 | ... R22: =IF(Monthly_Data!N36=0,"",((Monthly_Data!N35/Monthly_Data!N36)*100)) -> 128.005 | S22: =IFERROR(AVERAGE(G22:R22),"") -> 125.41652 | T22: =R22 -> 128.005 | U22: =IFERROR(AVERAGE(P22:R22),"") -> 128.67306 | V22: =IFERROR(R22-Q22,"") -> 0 | W22: =IFERROR(IF((R22-G22)>0,"↑ Improving",IF((R22-G22)<0,"↓ Worsening","→ Stable")),"N/A") -> ↑ Improving
A23: 22 | B23: NSFR | C23: % | D23: Higher Better | E23: 100 | F23: 110 | G23: =IF(Monthly_Data!C38=0,"",((Monthly_Data!C37/Monthly_Data!C38)*100)) -> 108.33333 | H23: =IF(Monthly_Data!D38=0,"",((Monthly_Data!D37/Monthly_Data!D38)*100)) -> 109.00044 | I23: =IF(Monthly_Data!E38=0,"",((Monthly_Data!E37/Monthly_Data!E38)*100)) -> 110 | J23: =IF(Monthly_Data!F38=0,"",((Monthly_Data!F37/Monthly_Data!F38)*100)) -> 111.01836 | K23: =IF(Monthly_Data!G38=0,"",((Monthly_Data!G37/Monthly_Data!G38)*100)) -> 110.99974 | L23: =IF(Monthly_Data!H38=0,"",((Monthly_Data!H37/Monthly_Data!H38)*100)) -> 111.99973 | M23: =IF(Monthly_Data!I38=0,"",((Monthly_Data!I37/Monthly_Data!I38)*100)) -> 111.9996 | N23: =IF(Monthly_Data!J38=0,"",((Monthly_Data!J37/Monthly_Data!J38)*100)) -> 112.99994 | ... R23: =IF(Monthly_Data!N38=0,"",((Monthly_Data!N37/Monthly_Data!N38)*100)) -> 112.99994 | S23: =IFERROR(AVERAGE(G23:R23),"") -> 111.44593 | T23: =R23 -> 112.99994 | U23: =IFERROR(AVERAGE(P23:R23),"") -> 112.99992 | V23: =IFERROR(R23-Q23,"") -> 0 | W23: =IFERROR(IF((R23-G23)>0,"↑ Improving",IF((R23-G23)<0,"↓ Worsening","→ Stable")),"N/A") -> ↑ Improving
A24: 23 | B24: SLR (Statutory Liquidity Ratio) | C24: % | D24: Higher Better | E24: 18 | F24: 18 | G24: =Monthly_Data!C39 -> 23.06 | H24: =Monthly_Data!D39 -> 21.85 | I24: =Monthly_Data!E39 -> 22.06 | J24: =Monthly_Data!F39 -> 22.82 | K24: =Monthly_Data!G39 -> 23.25 | L24: =Monthly_Data!H39 -> 22.62 | M24: =Monthly_Data!I39 -> 22.71 | N24: =Monthly_Data!J39 -> 22.6 | ... R24: =Monthly_Data!N39 -> 22.6 | S24: =IFERROR(AVERAGE(G24:R24),"") -> 22.6525 | T24: =R24 -> 22.6 | U24: =IFERROR(AVERAGE(P24:R24),"") -> 22.6 | V24: =IFERROR(R24-Q24,"") -> 0 | W24: =IFERROR(IF((R24-G24)>0,"↑ Improving",IF((R24-G24)<0,"↓ Worsening","→ Stable")),"N/A") -> ↓ Worsening
A25: 24 | B25: CRR (Cash Reserve Ratio) | C25: % | D25: Higher Better | E25: 4 | F25: 4 | G25: =Monthly_Data!C40 -> 4 | H25: =Monthly_Data!D40 -> 4.5 | I25: =Monthly_Data!E40 -> 4.5 | J25: =Monthly_Data!F40 -> 4.5 | K25: =Monthly_Data!G40 -> 4 | L25: =Monthly_Data!H40 -> 4.5 | M25: =Monthly_Data!I40 -> 4.5 | N25: =Monthly_Data!J40 -> 4.5 | ... R25: =Monthly_Data!N40 -> 4.5 | S25: =IFERROR(AVERAGE(G25:R25),"") -> 4.375 | T25: =R25 -> 4.5 | U25: =IFERROR(AVERAGE(P25:R25),"") -> 4.5 | V25: =IFERROR(R25-Q25,"") -> 0 | W25: =IFERROR(IF((R25-G25)>0,"↑ Improving",IF((R25-G25)<0,"↓ Worsening","→ Stable")),"N/A") -> ↑ Improving
A26: 25 | B26: Cumulative Gap (1M bucket)₹Cr | C26: ₹ Cr | D26: Higher Better | E26: -8000 | F26: -5000 | G26: =Monthly_Data!C41 -> -3800 | H26: =Monthly_Data!D41 -> -3500 | I26: =Monthly_Data!E41 -> -3200 | J26: =Monthly_Data!F41 -> -2900 | K26: =Monthly_Data!G41 -> -2700 | L26: =Monthly_Data!H41 -> -2600 | M26: =Monthly_Data!I41 -> -2500 | N26: =Monthly_Data!J41 -> -2400 | ... R26: =Monthly_Data!N41 -> -2400 | S26: =IFERROR(AVERAGE(G26:R26),"") -> -2766.6667 | T26: =R26 -> -2400 | U26: =IFERROR(AVERAGE(P26:R26),"") -> -2400 | V26: =IFERROR(R26-Q26,"") -> 0 | W26: =IFERROR(IF((R26-G26)>0,"↑ Improving",IF((R26-G26)<0,"↓ Worsening","→ Stable")),"N/A") -> ↑ Improving
A27: 26 | B27: NII Sensitivity (+200bps) | C27: % NII | D27: Higher Better | E27: -8 | F27: -5 | G27: =Monthly_Data!C43 -> -4.2 | H27: =Monthly_Data!D43 -> -4 | I27: =Monthly_Data!E43 -> -3.8 | J27: =Monthly_Data!F43 -> -3.6 | K27: =Monthly_Data!G43 -> -3.5 | L27: =Monthly_Data!H43 -> -3.4 | M27: =Monthly_Data!I43 -> -3.3 | N27: =Monthly_Data!J43 -> -3.2 | ... R27: =Monthly_Data!N43 -> -3.2 | S27: =IFERROR(AVERAGE(G27:R27),"") -> -3.475 | T27: =R27 -> -3.2 | U27: =IFERROR(AVERAGE(P27:R27),"") -> -3.1666667 | V27: =IFERROR(R27-Q27,"") -> 0 | W27: =IFERROR(IF((R27-G27)>0,"↑ Improving",IF((R27-G27)<0,"↓ Worsening","→ Stable")),"N/A") -> ↑ Improving
A28: 27 | B28: EVE Sensitivity (+200bps) | C28: % Tier1 | D28: Higher Better | E28: -12 | F28: -8 | G28: =Monthly_Data!C44 -> -6.8 | H28: =Monthly_Data!D44 -> -6.7 | I28: =Monthly_Data!E44 -> -6.6 | J28: =Monthly_Data!F44 -> -6.5 | K28: =Monthly_Data!G44 -> -6.5 | L28: =Monthly_Data!H44 -> -6.4 | M28: =Monthly_Data!I44 -> -6.3 | N28: =Monthly_Data!J44 -> -6.2 | ... R28: =Monthly_Data!N44 -> -6.2 | S28: =IFERROR(AVERAGE(G28:R28),"") -> -6.3916667 | T28: =R28 -> -6.2 | U28: =IFERROR(AVERAGE(P28:R28),"") -> -6.1666667 | V28: =IFERROR(R28-Q28,"") -> 0 | W28: =IFERROR(IF((R28-G28)>0,"↑ Improving",IF((R28-G28)<0,"↓ Worsening","→ Stable")),"N/A") -> ↑ Improving
A29: 28 | B29: Duration Gap | C29: Years | D29: Lower Better | E29: 2 | F29: 1.5 | G29: =Monthly_Data!C45 -> 1.4 | H29: =Monthly_Data!D45 -> 1.4 | I29: =Monthly_Data!E45 -> 1.3 | J29: =Monthly_Data!F45 -> 1.3 | K29: =Monthly_Data!G45 -> 1.2 | L29: =Monthly_Data!H45 -> 1.2 | M29: =Monthly_Data!I45 -> 1.2 | N29: =Monthly_Data!J45 -> 1.2 | ... R29: =Monthly_Data!N45 -> 1.2 | S29: =IFERROR(AVERAGE(G29:R29),"") -> 1.2416667 | T29: =R29 -> 1.2 | U29: =IFERROR(AVERAGE(P29:R29),"") -> 1.1666667 | V29: =IFERROR(R29-Q29,"") -> 0 | W29: =IFERROR(IF((R29-G29)<0,"↑ Improving",IF((R29-G29)>0,"↓ Worsening","→ Stable")),"N/A") -> ↑ Improving
A30: 29 | B30: Repricing Gap (1Y bucket) % | C30: % | D30: Higher Better | E30: -8 | F30: -5 | G30: =Monthly_Data!C46 -> -4.5 | H30: =Monthly_Data!D46 -> -4.3 | I30: =Monthly_Data!E46 -> -4.2 | J30: =Monthly_Data!F46 -> -4.2 | K30: =Monthly_Data!G46 -> -4.1 | L30: =Monthly_Data!H46 -> -4 | M30: =Monthly_Data!I46 -> -4 | N30: =Monthly_Data!J46 -> -4.1 | ... R30: =Monthly_Data!N46 -> -4.1 | S30: =IFERROR(AVERAGE(G30:R30),"") -> -4.15 | T30: =R30 -> -4.1 | U30: =IFERROR(AVERAGE(P30:R30),"") -> -4.1 | V30: =IFERROR(R30-Q30,"") -> 0 | W30: =IFERROR(IF((R30-G30)>0,"↑ Improving",IF((R30-G30)<0,"↓ Worsening","→ Stable")),"N/A") -> ↑ Improving
A31: 30 | B31: Physical Risk Exposure (High) | C31: ₹ Cr | D31: Lower Better | E31: 6000 | F31: 4000 | G31: =Monthly_Data!C48 -> 5200 | H31: =Monthly_Data!D48 -> 5100 | I31: =Monthly_Data!E48 -> 5000 | J31: =Monthly_Data!F48 -> 4900 | K31: =Monthly_Data!G48 -> 4700 | L31: =Monthly_Data!H48 -> 4600 | M31: =Monthly_Data!I48 -> 4500 | N31: =Monthly_Data!J48 -> 4400 | ... R31: =Monthly_Data!N48 -> 4200 | S31: =IFERROR(AVERAGE(G31:R31),"") -> 4608.3333 | T31: =R31 -> 4200 | U31: =IFERROR(AVERAGE(P31:R31),"") -> 4200 | V31: =IFERROR(R31-Q31,"") -> 0 | W31: =IFERROR(IF((R31-G31)<0,"↑ Improving",IF((R31-G31)>0,"↓ Worsening","→ Stable")),"N/A") -> ↑ Improving
A32: 31 | B32: Green Finance Ratio | C32: % | D32: Higher Better | E32: 7 | F32: 10 | G32: =IF(Monthly_Data!C49=0,"",((Monthly_Data!C50/Monthly_Data!C49)*100)) -> 7.2000697 | H32: =IF(Monthly_Data!D49=0,"",((Monthly_Data!D50/Monthly_Data!D49)*100)) -> 7.5001749 | I32: =IF(Monthly_Data!E49=0,"",((Monthly_Data!E50/Monthly_Data!E49)*100)) -> 7.7861635 | J32: =IF(Monthly_Data!F49=0,"",((Monthly_Data!F50/Monthly_Data!F49)*100)) -> 8 | K32: =IF(Monthly_Data!G49=0,"",((Monthly_Data!G50/Monthly_Data!G49)*100)) -> 8.3139453 | L32: =IF(Monthly_Data!H49=0,"",((Monthly_Data!H50/Monthly_Data!H49)*100)) -> 8.5 | M32: =IF(Monthly_Data!I49=0,"",((Monthly_Data!I50/Monthly_Data!I49)*100)) -> 8.7896213 | N32: =IF(Monthly_Data!J49=0,"",((Monthly_Data!J50/Monthly_Data!J49)*100)) -> 9 | ... R32: =IF(Monthly_Data!N49=0,"",((Monthly_Data!N50/Monthly_Data!N49)*100)) -> 9.6 | S32: =IFERROR(AVERAGE(G32:R32),"") -> 8.5658371 | T32: =R32 -> 9.6 | U32: =IFERROR(AVERAGE(P32:R32),"") -> 9.5000703 | V32: =IFERROR(R32-Q32,"") -> 0.1 | W32: =IFERROR(IF((R32-G32)>0,"↑ Improving",IF((R32-G32)<0,"↓ Worsening","→ Stable")),"N/A") -> ↑ Improving
A33: 32 | B33: Critical Vulns Unpatched | C33: Count | D33: Lower Better | E33: 10 | F33: 5 | G33: =Monthly_Data!C52 -> 8 | H33: =Monthly_Data!D52 -> 7 | I33: =Monthly_Data!E52 -> 7 | J33: =Monthly_Data!F52 -> 6 | K33: =Monthly_Data!G52 -> 5 | L33: =Monthly_Data!H52 -> 5 | M33: =Monthly_Data!I52 -> 4 | N33: =Monthly_Data!J52 -> 4 | ... R33: =Monthly_Data!N52 -> 4 | S33: =IFERROR(AVERAGE(G33:R33),"") -> 5.1666667 | T33: =R33 -> 4 | U33: =IFERROR(AVERAGE(P33:R33),"") -> 4 | V33: =IFERROR(R33-Q33,"") -> 0 | W33: =IFERROR(IF((R33-G33)<0,"↑ Improving",IF((R33-G33)>0,"↓ Worsening","→ Stable")),"N/A") -> ↑ Improving
A34: 33 | B34: MTTD (Mean Time to Detect) | C34: Hours | D34: Lower Better | E34: 8 | F34: 4 | G34: =Monthly_Data!C53 -> 5.2 | H34: =Monthly_Data!D53 -> 4.8 | I34: =Monthly_Data!E53 -> 4.5 | J34: =Monthly_Data!F53 -> 4.2 | K34: =Monthly_Data!G53 -> 4 | L34: =Monthly_Data!H53 -> 3.8 | M34: =Monthly_Data!I53 -> 3.5 | N34: =Monthly_Data!J53 -> 3.2 | ... R34: =Monthly_Data!N53 -> 2.8 | S34: =IFERROR(AVERAGE(G34:R34),"") -> 3.7166667 | T34: =R34 -> 2.8 | U34: =IFERROR(AVERAGE(P34:R34),"") -> 2.8 | V34: =IFERROR(R34-Q34,"") -> 0 | W34: =IFERROR(IF((R34-G34)<0,"↑ Improving",IF((R34-G34)>0,"↓ Worsening","→ Stable")),"N/A") -> ↑ Improving
A35: 34 | B35: MTTR (Mean Time to Respond) | C35: Hours | D35: Lower Better | E35: 24 | F35: 8 | G35: =Monthly_Data!C54 -> 44.8 | H35: =Monthly_Data!D54 -> 43.2 | I35: =Monthly_Data!E54 -> 42 | J35: =Monthly_Data!F54 -> 40.5 | K35: =Monthly_Data!G54 -> 39.1 | L35: =Monthly_Data!H54 -> 37.4 | M35: =Monthly_Data!I54 -> 36.1 | N35: =Monthly_Data!J54 -> 34.5 | ... R35: =Monthly_Data!N54 -> 31.5 | S35: =IFERROR(AVERAGE(G35:R35),"") -> 37.091667 | T35: =R35 -> 31.5 | U35: =IFERROR(AVERAGE(P35:R35),"") -> 31.5 | V35: =IFERROR(R35-Q35,"") -> 0 | W35: =IFERROR(IF((R35-G35)<0,"↑ Improving",IF((R35-G35)>0,"↓ Worsening","→ Stable")),"N/A") -> ↑ Improving
A36: 35 | B36: Fraud Loss Ratio | C36: % Inc | D36: Lower Better | E36: 0.2 | F36: 0.1 | G36: =IF(Monthly_Data!C57=0,"",((Monthly_Data!C56/100)/Monthly_Data!C57*100)) -> 9.6551724e-06 | H36: =IF(Monthly_Data!D57=0,"",((Monthly_Data!D56/100)/Monthly_Data!D57*100)) -> 8.8275862e-06 | I36: =IF(Monthly_Data!E57=0,"",((Monthly_Data!E56/100)/Monthly_Data!E57*100)) -> 8.6896552e-06 | J36: =IF(Monthly_Data!F57=0,"",((Monthly_Data!F56/100)/Monthly_Data!F57*100)) -> 8.0689655e-06 | K36: =IF(Monthly_Data!G57=0,"",((Monthly_Data!G56/100)/Monthly_Data!G57*100)) -> 8.0689655e-06 | L36: =IF(Monthly_Data!H57=0,"",((Monthly_Data!H56/100)/Monthly_Data!H57*100)) -> 7.2413793e-06 | M36: =IF(Monthly_Data!I57=0,"",((Monthly_Data!I56/100)/Monthly_Data!I57*100)) -> 7.2413793e-06 | N36: =IF(Monthly_Data!J57=0,"",((Monthly_Data!J56/100)/Monthly_Data!J57*100)) -> 6.4827586e-06 | ... R36: =IF(Monthly_Data!N57=0,"",((Monthly_Data!N56/100)/Monthly_Data!N57*100)) -> 6.4827586e-06 | S36: =IFERROR(AVERAGE(G36:R36),"") -> 7.5172414e-06 | T36: =R36 -> 6.4827586e-06 | U36: =IFERROR(AVERAGE(P36:R36),"") -> 6.4827586e-06 | V36: =IFERROR(R36-Q36,"") -> 0 | W36: =IFERROR(IF((R36-G36)<0,"↑ Improving",IF((R36-G36)>0,"↓ Worsening","→ Stable")),"N/A") -> ↑ Improving
A37: 36 | B37: Fraud Recovery Rate | C37: % | D37: Higher Better | E37: 50 | F37: 65 | G37: =IF(Monthly_Data!C59=0,"",((Monthly_Data!C58/Monthly_Data!C59)*100)) -> 65.060241 | H37: =IF(Monthly_Data!D59=0,"",((Monthly_Data!D58/Monthly_Data!D59)*100)) -> 69.230769 | I37: =IF(Monthly_Data!E59=0,"",((Monthly_Data!E58/Monthly_Data!E59)*100)) -> 69.406393 | J37: =IF(Monthly_Data!F59=0,"",((Monthly_Data!F58/Monthly_Data!F59)*100)) -> 71.06599 | K37: =IF(Monthly_Data!G59=0,"",((Monthly_Data!G58/Monthly_Data!G59)*100)) -> 70.29703 | L37: =IF(Monthly_Data!H59=0,"",((Monthly_Data!H58/Monthly_Data!H59)*100)) -> 71.910112 | M37: =IF(Monthly_Data!I59=0,"",((Monthly_Data!I58/Monthly_Data!I59)*100)) -> 72.625698 | N37: =IF(Monthly_Data!J59=0,"",((Monthly_Data!J58/Monthly_Data!J59)*100)) -> 74.683544 | ... R37: =IF(Monthly_Data!N59=0,"",((Monthly_Data!N58/Monthly_Data!N59)*100)) -> 74.683544 | S37: =IFERROR(AVERAGE(G37:R37),"") -> 71.91783 | T37: =R37 -> 74.683544 | U37: =IFERROR(AVERAGE(P37:R37),"") -> 74.683544 | V37: =IFERROR(R37-Q37,"") -> 0 | W37: =IFERROR(IF((R37-G37)>0,"↑ Improving",IF((R37-G37)<0,"↓ Worsening","→ Stable")),"N/A") -> ↑ Improving
A38: 37 | B38: Critical Vendors SLA Breach | C38: Count | D38: Lower Better | E38: 5 | F38: 3 | G38: =Monthly_Data!C61 -> 5 | H38: =Monthly_Data!D61 -> 5 | I38: =Monthly_Data!E61 -> 4 | J38: =Monthly_Data!F61 -> 4 | K38: =Monthly_Data!G61 -> 3 | L38: =Monthly_Data!H61 -> 3 | M38: =Monthly_Data!I61 -> 2 | N38: =Monthly_Data!J61 -> 2 | ... R38: =Monthly_Data!N61 -> 2 | S38: =IFERROR(AVERAGE(G38:R38),"") -> 3 | T38: =R38 -> 2 | U38: =IFERROR(AVERAGE(P38:R38),"") -> 2 | V38: =IFERROR(R38-Q38,"") -> 0 | W38: =IFERROR(IF((R38-G38)<0,"↑ Improving",IF((R38-G38)>0,"↓ Worsening","→ Stable")),"N/A") -> ↑ Improving
A39: 38 | B39: Media Sentiment Score | C39: Score | D39: Higher Better | E39: 50 | F39: 60 | G39: =Monthly_Data!C63 -> 58 | H39: =Monthly_Data!D63 -> 59 | I39: =Monthly_Data!E63 -> 60 | J39: =Monthly_Data!F63 -> 61 | K39: =Monthly_Data!G63 -> 62 | L39: =Monthly_Data!H63 -> 62 | M39: =Monthly_Data!I63 -> 63 | N39: =Monthly_Data!J63 -> 63 | ... R39: =Monthly_Data!N63 -> 62 | S39: =IFERROR(AVERAGE(G39:R39),"") -> 61.333333 | T39: =R39 -> 62 | U39: =IFERROR(AVERAGE(P39:R39),"") -> 62 | V39: =IFERROR(R39-Q39,"") -> 0 | W39: =IFERROR(IF((R39-G39)>0,"↑ Improving",IF((R39-G39)<0,"↓ Worsening","→ Stable")),"N/A") -> ↑ Improving
A40: 39 | B40: Complaint Resolution Rate | C40: % | D40: Higher Better | E40: 80 | F40: 90 | G40: =IF(Monthly_Data!C64=0,"",((Monthly_Data!C65/Monthly_Data!C64)*100)) -> 90 | H40: =IF(Monthly_Data!D64=0,"",((Monthly_Data!D65/Monthly_Data!D64)*100)) -> 91 | I40: =IF(Monthly_Data!E64=0,"",((Monthly_Data!E65/Monthly_Data!E64)*100)) -> 92.983607 | J40: =IF(Monthly_Data!F64=0,"",((Monthly_Data!F65/Monthly_Data!F64)*100)) -> 94 | K40: =IF(Monthly_Data!G64=0,"",((Monthly_Data!G65/Monthly_Data!G64)*100)) -> 90.482759 | L40: =IF(Monthly_Data!H64=0,"",((Monthly_Data!H65/Monthly_Data!H64)*100)) -> 96 | M40: =IF(Monthly_Data!I64=0,"",((Monthly_Data!I65/Monthly_Data!I64)*100)) -> 99.5 | N40: =IF(Monthly_Data!J64=0,"",((Monthly_Data!J65/Monthly_Data!J64)*100)) -> 96.981818 | ... R40: =IF(Monthly_Data!N64=0,"",((Monthly_Data!N65/Monthly_Data!N64)*100)) -> 96.981818 | S40: =IFERROR(AVERAGE(G40:R40),"") -> 94.910891 | T40: =R40 -> 96.981818 | U40: =IFERROR(AVERAGE(P40:R40),"") -> 96.994168 | V40: =IFERROR(R40-Q40,"") -> 0 | W40: =IFERROR(IF((R40-G40)>0,"↑ Improving",IF((R40-G40)<0,"↓ Worsening","→ Stable")),"N/A") -> ↑ Improving
A41: 40 | B41: Single Borrower Limit Util | C41: % | D41: Lower Better | E41: 90 | F41: 80 | G41: =IF(Monthly_Data!C68=0,"",(Monthly_Data!C67/(0.15*Monthly_Data!C68)*100)) -> 99 | H41: =IF(Monthly_Data!D68=0,"",(Monthly_Data!D67/(0.15*Monthly_Data!D68)*100)) -> 99.502488 | I41: =IF(Monthly_Data!E68=0,"",(Monthly_Data!E67/(0.15*Monthly_Data!E68)*100)) -> 102.47525 | J41: =IF(Monthly_Data!F68=0,"",(Monthly_Data!F67/(0.15*Monthly_Data!F68)*100)) -> 103.44828 | K41: =IF(Monthly_Data!G68=0,"",(Monthly_Data!G67/(0.15*Monthly_Data!G68)*100)) -> 103.92157 | L41: =IF(Monthly_Data!H68=0,"",(Monthly_Data!H67/(0.15*Monthly_Data!H68)*100)) -> 104.87805 | M41: =IF(Monthly_Data!I68=0,"",(Monthly_Data!I67/(0.15*Monthly_Data!I68)*100)) -> 104.87805 | N41: =IF(Monthly_Data!J68=0,"",(Monthly_Data!J67/(0.15*Monthly_Data!J68)*100)) -> 106.34146 | ... R41: =IF(Monthly_Data!N68=0,"",(Monthly_Data!N67/(0.15*Monthly_Data!N68)*100)) -> 94.760361 | S41: =IFERROR(AVERAGE(G41:R41),"") -> 100.71771 | T41: =R41 -> 94.760361 | U41: =IFERROR(AVERAGE(P41:R41),"") -> 95.688751 | V41: =IFERROR(R41-Q41,"") -> -1.2731895 | W41: =IFERROR(IF((R41-G41)<0,"↑ Improving",IF((R41-G41)>0,"↓ Worsening","→ Stable")),"N/A") -> ↑ Improving
